Workbook
Name CC: COMPRAS!$G$2831:$H$2853
Name CC: VENTAS!$F$430:$G$452
Name OP: COMPRAS!$A$2831:$B$2889
Name OP: CONSOLIDADO!$B$1502:$C$1538
Name OP: VENTAS!$A$430:$B$467
Name SegmentaciónDeDatos_PERIODO: #N/A
Name SegmentaciónDeDatos_PERIODO1: #N/A
Name TIPODOC: COMPRAS!$J$2831:$K$2839
Name TIPODOC: VENTAS!$J$1374:$K$1382

Sheet R.Tributaria
D2: FORMATO ADMINISTRATIVO DE GESTION | R2: COD: S/N
D3: DETERMINACION DE IMPUESTOS - PDT 621 (INGRESOS Y GASTOS) | R3: VERSIÓN:01
R4: ÁREA: Contabilidad
D5: CONTABILIDAD | R5: =TODAY() -> 45979
B7: N° | C7: CONCEPTO | D7: DESCRIPCIÓN | E7: MEDIDA | F7: ENERO | G7: FEBRERO | H7: MARZO | I7: ABRIL | J7: MAYO | K7: JUNIO | L7: JULIO | M7: AGOSTO | N7: SETIEMBRE | O7: OCTUBRE | P7: NOVIEMBRE | Q7: DICIEMBRE | R7: TOTAL | S7: PROMEDIO
B8: 1 | C8: COMPRAS | D8: Base Imponible | E8: S/ | F8: =107127+2220 -> 109347 | G8: =166185+1107+3392 -> 170684 | H8: =171179+1020+3753 -> 175952 | I8: =124124+1127+2401 -> 127652 | J8: =330256+255+10336 -> 340847 | K8: =+'COMPRAS Y VENTAS'!K8+'COMPRAS Y VENTAS'!K9+'COMPRAS Y VENTAS'!K10+'COMPRAS Y VENTAS'!K11 -> 273829.72 | L8: =+'COMPRAS Y VENTAS'!L8+'COMPRAS Y VENTAS'!L9+'COMPRAS Y VENTAS'!L10+'COMPRAS Y VENTAS'!L11 -> 179668.9 | M8: =+'COMPRAS Y VENTAS'!M8+'COMPRAS Y VENTAS'!M9+'COMPRAS Y VENTAS'!M10+'COMPRAS Y VENTAS'!M11 -> 63276.2 | N8: =+'COMPRAS Y VENTAS'!N8+'COMPRAS Y VENTAS'!N9+'COMPRAS Y VENTAS'!N10 -> 145965.7 | O8: =+'COMPRAS Y VENTAS'!O8+'COMPRAS Y VENTAS'!O9+'COMPRAS Y VENTAS'!O10+'COMPRAS Y VENTAS'!O11 -> 175464.32 | P8: =+'COMPRAS Y VENTAS'!P8+'COMPRAS Y VENTAS'!P9+'COMPRAS Y VENTAS'!P10+'COMPRAS Y VENTAS'!P11 -> 0 | Q8: =+'COMPRAS Y VENTAS'!Q8+'COMPRAS Y VENTAS'!Q9+'COMPRAS Y VENTAS'!Q10+'COMPRAS Y VENTAS'!Q11 -> 0 | R8: =SUM(F8:Q8) -> 1762686.8 | S8: =AVERAGE(F8:Q8) -> 146890.57
D9: IGV 18% | E9: S/ | F9: 19283 | G9: =29913+111 -> 30024 | H9: =30812+102 -> 30914 | I9: =22342+113 -> 22455 | J9: =59446+26 -> 59472 | K9: =+'COMPRAS Y VENTAS'!K12+'COMPRAS Y VENTAS'!K13+'COMPRAS Y VENTAS'!K14 -> 49104.051 | L9: =+'COMPRAS Y VENTAS'!L12+'COMPRAS Y VENTAS'!L13+'COMPRAS Y VENTAS'!L14 -> 31931.185 | M9: =+'COMPRAS Y VENTAS'!M12+'COMPRAS Y VENTAS'!M13+'COMPRAS Y VENTAS'!M14 -> 10997.283 | N9: =+'COMPRAS Y VENTAS'!N12+'COMPRAS Y VENTAS'!N13+'COMPRAS Y VENTAS'!N14 -> 26138.016 | O9: =+'COMPRAS Y VENTAS'!O12+'COMPRAS Y VENTAS'!O13+'COMPRAS Y VENTAS'!O14 -> 31095.92 | P9: =+'COMPRAS Y VENTAS'!P12+'COMPRAS Y VENTAS'!P13+'COMPRAS Y VENTAS'!P14 -> 0 | Q9: =+'COMPRAS Y VENTAS'!Q12+'COMPRAS Y VENTAS'!Q13+'COMPRAS Y VENTAS'!Q14 -> 0 | R9: =SUM(F9:Q9) -> 311414.46 | S9: =AVERAGE(F9:Q9) -> 25951.205
B10: 2 | C10: VENTAS | D10: Base Imponible | E10: S/ | F10: 189659 | G10: 271705 | H10: =203341-3317 -> 200024 | I10: =377701-3299 -> 374402 | J10: =244467-10975 -> 233492 | K10: =+'COMPRAS Y VENTAS'!K17 -> 325085.7 | L10: =+'COMPRAS Y VENTAS'!L17 -> 256600.5 | M10: =+'COMPRAS Y VENTAS'!M17 -> 219647.64 | N10: =+'COMPRAS Y VENTAS'!N17 -> 247364.37 | O10: =+'COMPRAS Y VENTAS'!O17 -> 211332.06 | P10: =+'COMPRAS Y VENTAS'!P17 -> 0 | Q10: =+'COMPRAS Y VENTAS'!Q17 -> 0 | R10: =SUM(F10:Q10) -> 2529312.3 | S10: =AVERAGE(F10:Q10) -> 210776.02
D11: IGV 18% | E11: S/ | F11: 34139 | G11: 48907 | H11: =36601-597 -> 36004 | I11: =67986-594 -> 67392 | J11: =44004-1976 -> 42028 | K11: =ROUND('COMPRAS Y VENTAS'!K18,0) -> 58517 | L11: =ROUND('COMPRAS Y VENTAS'!L18,0) -> 46188 | M11: =ROUND('COMPRAS Y VENTAS'!M18,0) -> 39537 | N11: =ROUND('COMPRAS Y VENTAS'!N18,0) -> 44526 | O11: =ROUND('COMPRAS Y VENTAS'!O18,0) -> 38040 | P11: =ROUND('COMPRAS Y VENTAS'!P18,0) -> 0 | Q11: =ROUND('COMPRAS Y VENTAS'!Q18,0) -> 0
B12: 3 | C12: IGV | D12: Diferencia de IGV | E12: S/ | F12: =ROUND(F11-F9,0) -> 14856 | G12: =ROUND(G11-G9,0) -> 18883 | H12: =ROUND(H11-H9,0) -> 5090 | I12: =ROUND(I11-I9,0) -> 44937 | J12: =ROUND(J11-J9,0) -> -17444 | K12: =ROUND(K11-K9,0) -> 9413 | L12: =ROUND(L11-L9,0) -> 14257 | M12: =ROUND(M11-M9,0) -> 28540 | ... Q12: =ROUND(Q11-Q9,0) -> 0 | R12: =SUM(F12:Q12) -> 143864 | S12: =AVERAGE(F12:Q12) -> 11988.667
D13: Saldo de IGV | E13: S/ | K13: 17444 | L13: 8032 | R13: =SUM(F13:Q13) -> 25476 | S13: =AVERAGE(F13:Q13) -> 12738
D14: (-) Retenciones | E14: S/ | F14: 130 | G14: 127 | H14: 418 | I14: 81 | K14: 51 | L14: =119+51 -> 170 | M14: 28 | R14: =SUM(F14:Q14) -> 1005 | S14: =AVERAGE(F14:Q14) -> 143.57143
D15: IGV a Pagar | E15: S/ | F15: =F12-F13-F14 -> 14726 | G15: =G12-G13-G14 -> 18756 | H15: =H12-H13-H14 -> 4672 | I15: =I12-I13-I14 -> 44856 | J15: =J12-J13-J14 -> -17444 | K15: =K12-K13-K14 -> -8082 | L15: =L12-L13-L14 -> 6055 | M15: =M12-M13-M14 -> 28512 | ... Q15: =Q12-Q13-Q14 -> 0 | R15: =SUM(F15:Q15) -> 117383 | S15: =AVERAGE(F15:Q15) -> 9781.9167
B16: 4 | C16: RENTA | D16: Coeficiente | E16: % | F16: 0.01 | G16: 0.01 | H16: 0.01 | I16: 0.01 | J16: 0.01 | K16: 0.01 | L16: 0.015 | M16: 0.015 | N16: 0.015 | O16: 0.015 | R16: =SUM(F16:Q16) -> 0.12 | S16: =AVERAGE(F16:Q16) -> 0.012
D17: Bruta | E17: S/ | F17: =ROUND(F16*F10,0) -> 1897 | G17: =ROUND(G16*G10,0) -> 2717 | H17: =ROUND(H16*H10,0) -> 2000 | I17: =ROUND(I16*I10,0) -> 3744 | J17: =ROUND(J16*J10,0) -> 2335 | K17: =ROUND(K16*K10,0) -> 3251 | L17: =ROUND(L16*L10,0) -> 3849 | M17: =ROUND(M16*M10,0) -> 3295 | ... Q17: =ROUND(Q16*Q10,0) -> 0 | R17: =SUM(F17:Q17) -> 29968 | S17: =AVERAGE(F17:Q17) -> 2497.3333
D18: Saldo de Renta | E18: S/ | R18: =SUM(F18:Q18) -> 0 | S18: =IFERROR(AVERAGE(F18:Q18),0) -> 0
D19: Renta a Pagar | E19: S/ | F19: =F17-F18 -> 1897 | G19: =G17-G18 -> 2717 | H19: =H17-H18 -> 2000 | I19: =I17-I18 -> 3744 | J19: =J17-J18 -> 2335 | K19: =K17-K18 -> 3251 | L19: =L17-L18 -> 3849 | M19: =M17-M18 -> 3295 | ... Q19: =Q17-Q18 -> 0 | R19: =SUM(F19:Q19) -> 29968 | S19: =ROUND(AVERAGE(F19:Q19),0) -> 2497
B20: 5 | C20: U. TRIBUTARIA | D20: DESPUES DE IMPUESTOS | E20: S/ | F20: =F10-F8-F15-F19 -> 63689 | G20: =G10-G8-G15-G19 -> 79548 | H20: =H10-H8-H15-H19 -> 17400 | I20: =I10-I8-I15-I19 -> 198150 | J20: =J10-J8-J15-J19 -> -92246 | K20: =K10-K8-K15-K19 -> 56086.98 | L20: =L10-L8-L15-L19 -> 67027.6 | M20: =M10-M8-M15-M19 -> 124564.44 | ... Q20: =Q10-Q8-Q15-Q19 -> 0 | R20: =SUM(F20:Q20) -> 619274.43 | S20: =ROUND(AVERAGE(F20:Q20),0) -> 51606

Sheet DET IMPUESTO
D2: FORMATO ADMINISTRATIVO DE GESTION | R2: COD: S/N
D3: DETERMINACION DE IMPUESTOS - PDT 621 (INGRESOS Y GASTOS) | R3: VERSIÓN:01
R4: AREÁ: Contabilidad
D5: CONTABILIDAD | R5: =TODAY() -> 45979
B7: N° | C7: INDICADOR | D7: FORMULA | E7: MEDIDA | F7: ENERO | G7: FEBRERO | H7: MARZO | I7: ABRIL | J7: MAYO | K7: JUNIO | L7: JULIO | M7: AGOSTO | N7: SETIEMBRE | O7: OCTUBRE | P7: NOVIEMBRE | Q7: DICIEMBRE | R7: TOTAL | S7: PROMEDIO
B8: 1 | C8: IGV | D8: IGV de las ventas | E8: Numero | F8: 34139 | G8: 48907 | H8: 36601 | I8: 67392 | J8: 42028 | K8: =SUMIFS(Anexo_5[igv_18],Anexo_5[periodo],K7) -> 58515.386 | L8: =SUMIFS(Anexo_5[igv_18],Anexo_5[periodo],L7) -> 46188.157 | M8: =SUMIFS(Anexo_5[igv_18],Anexo_5[periodo],M7) -> 39536.553 | N8: =SUMIFS(Anexo_5[igv_18],Anexo_5[periodo],N7) -> 44525.59 | O8: =SUMIFS(Anexo_5[igv_18],Anexo_5[periodo],O7) -> 38039.79 | P8: =SUMIFS(Anexo_5[igv_18],Anexo_5[periodo],P7) -> 0 | Q8: =SUMIFS(Anexo_5[igv_18],Anexo_5[periodo],Q7) -> 0 | R8: =SUM(F8:Q8) -> 455872.48 | S8: =AVERAGE(F8:Q8) -> 37989.373
D9: IGV de las compras | E9: Numero | F9: 19283 | G9: 30024 | H9: 30914 | I9: 22455 | J9: 59472 | K9: =SUMIFS(Anexo_4[igv_18],Anexo_4[periodo],K7)+SUMIFS(Anexo_4[igv_10],Anexo_4[periodo],K7) -> 49104.051 | L9: =SUMIFS(Anexo_4[igv_18],Anexo_4[periodo],L7)+SUMIFS(Anexo_4[igv_10],Anexo_4[periodo],L7) -> 31931.185 | M9: =SUMIFS(Anexo_4[igv_18],Anexo_4[periodo],M7)+SUMIFS(Anexo_4[igv_10],Anexo_4[periodo],M7) -> 10996.283 | N9: =SUMIFS(Anexo_4[igv_18],Anexo_4[periodo],N7)+SUMIFS(Anexo_4[igv_10],Anexo_4[periodo],N7) -> 26138.016 | O9: =SUMIFS(Anexo_4[igv_18],Anexo_4[periodo],O7)+SUMIFS(Anexo_4[igv_10],Anexo_4[periodo],O7) -> 31095.92 | P9: =SUMIFS(Anexo_4[igv_18],Anexo_4[periodo],P7)+SUMIFS(Anexo_4[igv_10],Anexo_4[periodo],P7) -> 0 | Q9: =SUMIFS(Anexo_4[igv_18],Anexo_4[periodo],Q7)+SUMIFS(Anexo_4[igv_10],Anexo_4[periodo],Q7) -> 0 | R9: =SUM(F9:Q9) -> 311413.46 | S9: =AVERAGE(F9:Q9) -> 25951.121
D10: ="+ IGV Ventas - IGV Compras =" -> + IGV Ventas - IGV Compras = | E10: Numero | F10: =+F8-F9 -> 14856 | G10: =+G8-G9 -> 18883 | H10: =+H8-H9 -> 5687 | I10: =+I8-I9 -> 44937 | J10: =+J8-J9 -> -17444 | K10: =+K8-K9 -> 9411.335 | L10: =+L8-L9 -> 14256.972 | M10: =+M8-M9 -> 28540.27 | ... Q10: =+Q8-Q9 -> 0 | R10: =SUM(F10:Q10) -> 144459.02 | S10: =AVERAGE(F10:Q10) -> 12038.252
D11: (-) Saldo a Favor del Periodo Anterior | E11: Numero | F11: 0 | H11: 0 | I11: 0 | J11: 0 | K11: -17444 | L11: =+K13 -> -8032.665 | M11: 0 | N11: 0 | R11: =SUM(F11:Q11) -> -25476.665 | S11: =AVERAGE(F11:Q11) -> -3184.5831
D12: (-) Reteciones del Periodo | E12: Numero | F12: 130 | G12: 127 | H12: 418 | I12: 81 | J12: 0 | K12: -51 | L12: -119 | M12: -28 | R12: =SUM(F12:Q12) -> 558 | S12: =AVERAGE(F12:Q12) -> 69.75
D13: IGV por Pagar | E13: Numero | F13: =+F10-F11-F12 -> 14726 | G13: =+G10-G11-G12 -> 18756 | H13: =+H10-H11-H12 -> 5269 | I13: =+I10-I11-I12 -> 44856 | J13: =+J10-J11-J12 -> -17444 | K13: =+K10+K11 -> -8032.665 | L13: =+L10+L11+L12+K12 -> 6054.307 | M13: =+M10+M11+M12 -> 28512.27 | N13: =+N10+N11+N12 -> 18387.574 | O13: =+O10+O11+O12 -> 6943.87 | P13: =+P10+P11+P12 -> 0 | Q13: =+Q10+Q11+Q12 -> 0 | R13: =SUM(F13:Q13) -> 118028.36 | S13: =AVERAGE(F13:Q13) -> 9835.6963
D14: Método de pago | E14: Letra | F14: Pagado con B.Nación | G14: Pagado con B.Nación | H14: Pagado con B.Nación | I14: Pagado con B.Nación/BCP | J14: Crédito a favor | K14: Crédito a favor | L14: Pagado con B.Nación | M14: IGV justo | N14: Pagado con B.Nación
D15: Indicador | E15: Letra | G15: =IF((G13-F13)/F13>0,"se pago más que el mes ant.","Se pago menos que el mes ant.") -> se pago más que el mes ant. | H15: =IF((H13-G13)/G13>0,"se pago más que el mes ant.","Se pago menos que el mes ant.") -> Se pago menos que el mes ant. | I15: =IF((I13-H13)/H13>0,"se pago más que el mes ant.","Se pago menos que el mes ant.") -> se pago más que el mes ant. | J15: =IF((J13-I13)/I13>0,"se pago más que el mes ant.","Se pago menos que el mes ant.") -> Se pago menos que el mes ant. | K15: =IF((K13-J13)/J13>0,"se pago más que el mes ant.","Se pago menos que el mes ant.") -> Se pago menos que el mes ant. | L15: =IF((L13-K13)/K13>0,"se pago más que el mes ant.","Se pago menos que el mes ant.") -> Se pago menos que el mes ant. | M15: =IF((M13-L13)/L13>0,"se pago más que el mes ant.","Se pago menos que el mes ant.") -> se pago más que el mes ant. | N15: =IF((N13-M13)/M13>0,"se pago más que el mes ant.","Se pago menos que el mes ant.") -> Se pago menos que el mes ant. | O15: =IFERROR(O8/O10,0) -> 5.4781829 | P15: =IFERROR(P8/P10,0) -> 0 | Q15: =IFERROR(Q8/Q10,0) -> 0
B16: 2 | C16: RENTA | D16: Ingresos Netos | E16: Numero | F16: 189659 | G16: 271705 | H16: 200024 | I16: 374402 | J16: 233493 | K16: =SUMIFS(Anexo_5[base_imponible_18],Anexo_5[periodo],K7) -> 325085.7 | L16: =SUMIFS(Anexo_5[base_imponible_18],Anexo_5[periodo],L7) -> 256600.5 | M16: =SUMIFS(Anexo_5[base_imponible_18],Anexo_5[periodo],M7) -> 219647.64 | N16: =SUMIFS(Anexo_5[base_imponible_18],Anexo_5[periodo],N7) -> 247364.37 | O16: =SUMIFS(Anexo_5[base_imponible_18],Anexo_5[periodo],O7) -> 211332.06 | P16: =SUMIFS(Anexo_5[base_imponible_18],Anexo_5[periodo],P7) -> 0 | Q16: =SUMIFS(Anexo_5[base_imponible_18],Anexo_5[periodo],Q7) -> 0 | R16: =SUM(F16:Q16) -> 2529313.3 | S16: =AVERAGE(F16:Q16) -> 210776.11
D17: Coeficiente | E17: Factor | F17: 0.01 | G17: 0.01 | H17: 0.01 | I17: 0.01 | J17: 0.01 | K17: 0.01 | L17: 0.015 | M17: 0.015 | N17: 0.015 | O17: 0.015 | R17: =SUM(F17:Q17) -> 0.12 | S17: =AVERAGE(F17:Q17) -> 0.012
D18: Renta Bruta | E18: Numero | F18: =F16*F17 -> 1896.59 | G18: =G16*G17 -> 2717.05 | H18: =H16*H17 -> 2000.24 | I18: =I16*I17 -> 3744.02 | J18: =J16*J17 -> 2334.93 | K18: =K16*K17 -> 3250.857 | L18: =L16*L17 -> 3849.0075 | M18: =M16*M17 -> 3294.7146 | ... Q18: =Q16*Q17 -> 0 | R18: =SUM(F18:Q18) -> 29967.856 | S18: =AVERAGE(F18:Q18) -> 2497.3213
D19: (-) Saldo a Favor del Periodo Anterior | E19: Numero | F19: 0 | G19: 0 | H19: 0 | I19: 0 | K19: 0 | R19: =SUM(F19:Q19) -> 0 | S19: =AVERAGE(F19:Q19) -> 0
D20: Renta Por Pagar | E20: Numero | F20: =+F18-F19 -> 1896.59 | G20: =+G18-G19 -> 2717.05 | H20: =+H18-H19 -> 2000.24 | I20: =+I18-I19 -> 3744.02 | J20: =+J18-J19 -> 2334.93 | K20: =+K18-K19 -> 3250.857 | L20: =+L18-L19 -> 3849.0075 | M20: =+M18-M19 -> 3294.7146 | ... Q20: =+Q18-Q19 -> 0 | R20: =SUM(F20:Q20) -> 29967.856 | S20: =AVERAGE(F20:Q20) -> 2497.3213
D21: Método de pago | E21: Letra | F21: Pagado con B.Nación | G21: Pagado con B.Nación | H21: Pagado con B.Nación | I21: Pagado con B.Nación | J21: Pagado con B.Nación | K21: Pagado con B.Nación | L21: Pagado con B.Nación | M21: Pagado con B.Nación | N21: Pagado con B.Nación
D22: Indicador | E22: % | G22: =IF((G20-F20)/F20>0,"se pago más que el mes ant.","Se pago menos que el mes ant.") -> se pago más que el mes ant. | H22: =IF((H20-G20)/G20>0,"se pago más que el mes ant.","Se pago menos que el mes ant.") -> Se pago menos que el mes ant. | I22: =IF((I20-H20)/H20>0,"se pago más que el mes ant.","Se pago menos que el mes ant.") -> se pago más que el mes ant. | J22: =IF((J20-I20)/I20>0,"se pago más que el mes ant.","Se pago menos que el mes ant.") -> Se pago menos que el mes ant. | K22: =IF((K20-J20)/J20>0,"se pago más que el mes ant.","Se pago menos que el mes ant.") -> se pago más que el mes ant. | L22: =IF((L20-K20)/K20>0,"se pago más que el mes ant.","Se pago menos que el mes ant.") -> se pago más que el mes ant. | M22: =IF((M20-L20)/L20>0,"se pago más que el mes ant.","Se pago menos que el mes ant.") -> Se pago menos que el mes ant. | N22: =IF((N20-M20)/M20>0,"se pago más que el mes ant.","Se pago menos que el mes ant.") -> se pago más que el mes ant. | P22: =IFERROR(P18/P17,0) -> 0 | Q22: =IFERROR(Q18/Q17,0) -> 0

Sheet COMPRAS Y VENTAS
D2: FORMATO ADMINISTRATIVO DE GESTION | R2: COD: S/N
D3: RESUMEN COMPRAS Y VENTAS 2025 | R3: VERSIÓN:01
R4: AREÁ: Contabilidad
D5: CONTABILIDAD | R5: =TODAY() -> 45979
B7: N° | C7: INDICADOR | D7: FORMULA | E7: MEDIDA | F7: ENERO | G7: FEBRERO | H7: MARZO | I7: ABRIL | J7: MAYO | K7: JUNIO | L7: JULIO | M7: AGOSTO | N7: SETIEMBRE | O7: OCTUBRE | P7: NOVIEMBRE | Q7: DICIEMBRE | R7: TOTAL | S7: PROMEDIO
B8: 1 | C8: COMPRAS | D8: Base Imponible (18%) | E8: Moneda | K8: =SUMIFS(Anexo_4[base_imponible_18],Anexo_4[periodo],K7,Anexo_4[cod_doc],"01")+SUMIFS(Anexo_4[base_imponible_18],Anexo_4[periodo],K7,Anexo_4[cod_doc],"14") -> 274431.24 | L8: =SUMIFS(Anexo_4[base_imponible_18],Anexo_4[periodo],L7,Anexo_4[cod_doc],"01")+SUMIFS(Anexo_4[base_imponible_18],Anexo_4[periodo],L7,Anexo_4[cod_doc],"14") -> 178793.11 | M8: =SUMIFS(Anexo_4[base_imponible_18],Anexo_4[periodo],M7,Anexo_4[cod_doc],"01")+SUMIFS(Anexo_4[base_imponible_18],Anexo_4[periodo],M7,Anexo_4[cod_doc],"14") -> 125800.76 | N8: =SUMIFS(Anexo_4[base_imponible_18],Anexo_4[periodo],N7) -> 144247.98 | O8: =SUMIFS(Anexo_4[base_imponible_18],Anexo_4[periodo],O7) -> 172316.66 | P8: =SUMIFS(Anexo_4[base_imponible_18],Anexo_4[periodo],P7) -> 0 | Q8: =SUMIFS(Anexo_4[base_imponible_18],Anexo_4[periodo],Q7) -> 0 | R8: =SUM(F8:Q8) -> 895589.75 | S8: =AVERAGE(F8:Q8) -> 127941.39
D9: Base Imponible (10%) | E9: Moneda | K9: =SUMIFS(Anexo_4[base_imponible_10],Anexo_4[periodo],K7)-1 -> 712.65 | L9: =SUMIFS(Anexo_4[base_imponible_10],Anexo_4[periodo],L7) -> 933.63 | M9: =SUMIFS(Anexo_4[base_imponible_10],Anexo_4[periodo],M7) -> 287.28 | N9: =SUMIFS(Anexo_4[base_imponible_10],Anexo_4[periodo],N7) -> 1717.72 | O9: =SUMIFS(Anexo_4[base_imponible_10],Anexo_4[periodo],O7) -> 785.63 | P9: =SUMIFS(Anexo_4[base_imponible_10],Anexo_4[periodo],P7) -> 0 | Q9: =SUMIFS(Anexo_4[base_imponible_10],Anexo_4[periodo],Q7) -> 0 | R9: =SUM(F9:Q9) -> 4436.91 | S9: =AVERAGE(F9:Q9) -> 633.84429
D10: Base Imponible NC (18%) | E10: Moneda | K10: =SUMIFS(Anexo_4[base_imponible_18],Anexo_4[periodo],K7,Anexo_4[cod_doc],"07") -> -2027.36 | L10: =SUMIFS(Anexo_4[base_imponible_18],Anexo_4[periodo],L7,Anexo_4[cod_doc],"07") -> -1916.49 | M10: =SUMIFS(Anexo_4[base_imponible_18],Anexo_4[periodo],M7,Anexo_4[cod_doc],"07") -> -64870.04
D11: Compras No gravadas | E11: Moneda | K11: =SUMIFS(Anexo_4[base_no_grabada],Anexo_4[periodo],K7) -> 713.19 | L11: =SUMIFS(Anexo_4[base_no_grabada],Anexo_4[periodo],L7) -> 1858.65 | M11: =SUMIFS(Anexo_4[base_no_grabada],Anexo_4[periodo],M7) -> 2058.2 | N11: =SUMIFS(Anexo_4[base_no_grabada],Anexo_4[periodo],N7) -> 5115.07 | O11: =SUMIFS(Anexo_4[base_no_grabada],Anexo_4[periodo],O7) -> 2362.03 | P11: =SUMIFS(Anexo_4[base_no_grabada],Anexo_4[periodo],P7) -> 0 | Q11: =SUMIFS(Anexo_4[base_no_grabada],Anexo_4[periodo],Q7) -> 0 | R11: =SUM(F11:Q11) -> 12107.14 | S11: =AVERAGE(F11:Q11) -> 1729.5914
D12: IGV de las compras (18%) | E12: Moneda | K12: =SUMIFS(Anexo_4[igv_18],Anexo_4[periodo],K7,Anexo_4[cod_doc],"01")+SUMIFS(Anexo_4[igv_18],Anexo_4[periodo],K7,Anexo_4[cod_doc],"14") -> 49397.621 | L12: =SUMIFS(Anexo_4[igv_18],Anexo_4[periodo],L7,Anexo_4[cod_doc],"01")+SUMIFS(Anexo_4[igv_18],Anexo_4[periodo],L7,Anexo_4[cod_doc],"14") -> 32182.775 | M12: =SUMIFS(Anexo_4[igv_18],Anexo_4[periodo],M7,Anexo_4[cod_doc],"01")+SUMIFS(Anexo_4[igv_18],Anexo_4[periodo],M7,Anexo_4[cod_doc],"14")+1 -> 22645.163 | N12: =SUMIFS(Anexo_4[igv_18],Anexo_4[periodo],N7) -> 25966.236 | O12: =SUMIFS(Anexo_4[igv_18],Anexo_4[periodo],O7) -> 31017.35 | P12: =SUMIFS(Anexo_4[igv_18],Anexo_4[periodo],P7) -> 0 | Q12: =SUMIFS(Anexo_4[igv_18],Anexo_4[periodo],Q7) -> 0 | R12: =SUM(F12:Q12) -> 161209.15 | S12: =AVERAGE(F12:Q12) -> 23029.878
D13: IGV de las compras (10%) | E13: Moneda | K13: =SUMIFS(Anexo_4[igv_10],Anexo_4[periodo],K7,Anexo_4[cod_doc],"01") -> 71.35 | L13: =SUMIFS(Anexo_4[igv_10],Anexo_4[periodo],L7,Anexo_4[cod_doc],"01") -> 93.37 | M13: =SUMIFS(Anexo_4[igv_10],Anexo_4[periodo],M7,Anexo_4[cod_doc],"01") -> 28.72 | N13: =SUMIFS(Anexo_4[igv_10],Anexo_4[periodo],N7) -> 171.78 | O13: =SUMIFS(Anexo_4[igv_10],Anexo_4[periodo],O7) -> 78.57 | P13: =SUMIFS(Anexo_4[igv_10],Anexo_4[periodo],P7) -> 0 | Q13: =SUMIFS(Anexo_4[igv_10],Anexo_4[periodo],Q7) -> 0 | R13: =SUM(F13:Q13) -> 443.79 | S13: =AVERAGE(F13:Q13) -> 63.398571
D14: IGV de las compras NC (18%) | E14: Moneda | K14: =SUMIFS(Anexo_4[igv_18],Anexo_4[periodo],K7,Anexo_4[cod_doc],"07") -> -364.92 | L14: =SUMIFS(Anexo_4[igv_18],Anexo_4[periodo],L7,Anexo_4[cod_doc],"07") -> -344.96 | M14: =SUMIFS(Anexo_4[igv_18],Anexo_4[periodo],M7,Anexo_4[cod_doc],"07") -> -11676.6
D15: Total Compras | E15: Moneda | K15: =SUMIFS(Anexo_4[total],Anexo_4[periodo],K7) -> 352727.3 | L15: =SUMIFS(Anexo_4[total],Anexo_4[periodo],L7) -> 231640.04 | M15: =SUMIFS(Anexo_4[total],Anexo_4[periodo],M7) -> 107190.99 | N15: =SUMIFS(Anexo_4[total],Anexo_4[periodo],N7) -> 177218.79 | O15: =SUMIFS(Anexo_4[total],Anexo_4[periodo],O7) -> 206560.24 | P15: =SUMIFS(Anexo_4[total],Anexo_4[periodo],P7) -> 0 | Q15: =SUMIFS(Anexo_4[total],Anexo_4[periodo],Q7) -> 0 | R15: =SUM(F15:Q15) -> 1075337.4 | S15: =AVERAGE(F15:Q15) -> 153619.62
D16: Indicador | E16: % | F16: =IFERROR(F8/F11,0) -> 0 | G16: =IFERROR(G8/G11,0) -> 0 | H16: =IFERROR(H8/H11,0) -> 0 | I16: =IFERROR(I8/I11,0) -> 0 | J16: =IFERROR(J8/J11,0) -> 0 | K16: =IFERROR(((K15-J15)/J15),"") | L16: =IF((L15-K15)/K15>0,"Más compras que el mes ant.","Menos compras que el mes ant.") -> Menos compras que el mes ant. | M16: =IF((M15-L15)/L15>0,"Más compras que el mes ant.","Menos compras que el mes ant.") -> Menos compras que el mes ant. | N16: =IF((N15-M15)/M15>0,"Más compras que el mes ant.","Menos compras que el mes ant.") -> Más compras que el mes ant. | P16: =IFERROR(IF(P15="","",((P15-O15)/O15)),"") -> -1 | Q16: =IFERROR(IF(Q15="","",((Q15-P15)/P15)),"")
B17: 2 | C17: VENTAS | D17: Base Imponible | E17: Moneda | K17: =SUMIFS(Anexo_5[base_imponible_18],Anexo_5[periodo],K7) -> 325085.7 | L17: =SUMIFS(Anexo_5[base_imponible_18],Anexo_5[periodo],L7) -> 256600.5 | M17: =SUMIFS(Anexo_5[base_imponible_18],Anexo_5[periodo],M7) -> 219647.64 | N17: =SUMIFS(Anexo_5[base_imponible_18],Anexo_5[periodo],N7) -> 247364.37 | O17: =SUMIFS(Anexo_5[base_imponible_18],Anexo_5[periodo],O7) -> 211332.06 | P17: =SUMIFS(Anexo_5[base_imponible_18],Anexo_5[periodo],P7) -> 0 | Q17: =SUMIFS(Anexo_5[base_imponible_18],Anexo_5[periodo],Q7) -> 0 | R17: =SUM(F17:Q17) -> 1260030.3 | S17: =AVERAGE(F17:Q17) -> 180004.32
D18: IGV de las ventas | E18: Moneda | K18: =SUMIFS(Anexo_5[igv_18],Anexo_5[periodo],K7)+2 -> 58517.386 | L18: =SUMIFS(Anexo_5[igv_18],Anexo_5[periodo],L7) -> 46188.157 | M18: =SUMIFS(Anexo_5[igv_18],Anexo_5[periodo],M7) -> 39536.553 | N18: =SUMIFS(Anexo_5[igv_18],Anexo_5[periodo],N7) -> 44525.59 | O18: =SUMIFS(Anexo_5[igv_18],Anexo_5[periodo],O7) -> 38039.79 | P18: =SUMIFS(Anexo_5[igv_18],Anexo_5[periodo],P7) -> 0 | Q18: =SUMIFS(Anexo_5[igv_18],Anexo_5[periodo],Q7) -> 0 | R18: =SUM(F18:Q18) -> 226807.48 | S18: =AVERAGE(F18:Q18) -> 32401.068
D19: Total Ventas | E19: Moneda | K19: =SUMIFS(Anexo_5[total],Anexo_5[periodo],K7) -> 383601.09 | L19: =SUMIFS(Anexo_5[total],Anexo_5[periodo],L7) -> 302788.66 | M19: =SUMIFS(Anexo_5[total],Anexo_5[periodo],M7) -> 259184.19 | N19: =SUMIFS(Anexo_5[total],Anexo_5[periodo],N7) -> 291889.96 | O19: =SUMIFS(Anexo_5[total],Anexo_5[periodo],O7) -> 249371.85 | P19: =SUMIFS(Anexo_5[total],Anexo_5[periodo],P7) -> 0 | Q19: =SUMIFS(Anexo_5[total],Anexo_5[periodo],Q7) -> 0 | R19: =SUM(F19:Q19) -> 1486835.7 | S19: =AVERAGE(F19:Q19) -> 212405.11
D20: Indicador | E20: % | F20: =IFERROR(F19/F18,0) -> 0 | G20: =IFERROR(G19/G18,0) -> 0 | H20: =IFERROR(H19/H18,0) -> 0 | I20: =IFERROR(I19/I18,0) -> 0 | J20: =IFERROR(J19/J18,0) -> 0 | L20: =IF((L19-K19)/K19>0,"Más ventas que el mes ant.","Menos ventas que el mes ant.") -> Menos ventas que el mes ant. | M20: =IF((M19-L19)/L19>0,"Más ventas que el mes ant.","Menos ventas que el mes ant.") -> Menos ventas que el mes ant. | N20: =IF((N19-M19)/M19>0,"Más ventas que el mes ant.","Menos ventas que el mes ant.") -> Más ventas que el mes ant. | O20: =IFERROR(O19/O18,0) -> 6.5555528 | P20: =IFERROR(P19/P18,0) -> 0 | Q20: =IFERROR(Q19/Q18,0) -> 0

Sheet CONSOLIDADO
E2: FORMATO ADMINISTRATIVO DE GESTION | S2: COD: S/N
E3: INDICADORES DE GESTION - GASTOS OPERATIVOS | S3: VERSIÓN:01
S4: AREÁ: Gerencia
E5: CONTABILIDAD | S5: =TODAY() -> 45979
B7: KPI | C7: CONCEPTO | E7: DETALLE | F7: MEDIDA | G7: ENERO | H7: FEBRERO | I7: MARZO | J7: ABRIL | K7: MAYO | L7: JUNIO | M7: JULIO | N7: AGOSTO | O7: SETIEMBRE | P7: OCTUBRE | Q7: NOVIEMBRE | R7: DICIEMBRE | S7: TOTAL | T7: PROMEDIO
B8: I.3.1 (Det. Anexo 4) | C8: COMPRA DE RESIDUOS | E8: Materias Primas - RRSS | F8: Moneda | G8: =SUMIFS(Anexo_4[base_imponible_18],Anexo_4[gastos_operativos_kpi],$E$8,Anexo_4[periodo],$G$7)+SUMIFS(Anexo_4[base_imponible_10],Anexo_4[gastos_operativos_kpi],$E$8,Anexo_4[periodo],$G$7)+SUMIFS(Anexo_4[base_no_grabada],Anexo_4[gastos_operativos_kpi],$E$8,Anexo_4[periodo],$G$7) -> 0 | H8: =SUMIFS(Anexo_4[base_imponible_18],Anexo_4[gastos_operativos_kpi],$E$8,Anexo_4[periodo],$H$7)+SUMIFS(Anexo_4[base_imponible_10],Anexo_4[gastos_operativos_kpi],$E$8,Anexo_4[periodo],$H$7)+SUMIFS(Anexo_4[base_no_grabada],Anexo_4[gastos_operativos_kpi],$E$8,Anexo_4[periodo],$H$7) -> 0 | I8: =SUMIFS(Anexo_4[base_imponible_18],Anexo_4[gastos_operativos_kpi],$E$8,Anexo_4[periodo],$I$7)+SUMIFS(Anexo_4[base_imponible_10],Anexo_4[gastos_operativos_kpi],$E$8,Anexo_4[periodo],$I$7)+SUMIFS(Anexo_4[base_no_grabada],Anexo_4[gastos_operativos_kpi],$E$8,Anexo_4[periodo],$I$7) -> 0 | J8: =SUMIFS(Anexo_4[base_imponible_18],Anexo_4[gastos_operativos_kpi],$E$8,Anexo_4[periodo],$J$7)+SUMIFS(Anexo_4[base_imponible_10],Anexo_4[gastos_operativos_kpi],$E$8,Anexo_4[periodo],$J$7)+SUMIFS(Anexo_4[base_no_grabada],Anexo_4[gastos_operativos_kpi],$E$8,Anexo_4[periodo],$J$7) -> 0 | K8: =SUMIFS(Anexo_4[base_imponible_18],Anexo_4[gastos_operativos_kpi],$E$8,Anexo_4[periodo],$K$7)+SUMIFS(Anexo_4[base_imponible_10],Anexo_4[gastos_operativos_kpi],$E$8,Anexo_4[periodo],$K$7)+SUMIFS(Anexo_4[base_no_grabada],Anexo_4[gastos_operativos_kpi],$E$8,Anexo_4[periodo],$K$7) -> 0 | L8: =SUMIFS(Anexo_4[base_imponible_18],Anexo_4[gastos_operativos_kpi],$E$8,Anexo_4[periodo],$L$7)+SUMIFS(Anexo_4[base_imponible_10],Anexo_4[gastos_operativos_kpi],$E$8,Anexo_4[periodo],$L$7)+SUMIFS(Anexo_4[base_no_grabada],Anexo_4[gastos_operativos_kpi],$E$8,Anexo_4[periodo],$L$7) -> 58426.81 | M8: =SUMIFS(Anexo_4[base_imponible_18],Anexo_4[gastos_operativos_kpi],$E$8,Anexo_4[periodo],$M$7)+SUMIFS(Anexo_4[base_imponible_10],Anexo_4[gastos_operativos_kpi],$E$8,Anexo_4[periodo],$M$7)+SUMIFS(Anexo_4[base_no_grabada],Anexo_4[gastos_operativos_kpi],$E$8,Anexo_4[periodo],$M$7) -> 24376.79 | N8: =SUMIFS(Anexo_4[base_imponible_18],Anexo_4[gastos_operativos_kpi],$E$8,Anexo_4[periodo],$N$7)+SUMIFS(Anexo_4[base_imponible_10],Anexo_4[gastos_operativos_kpi],$E$8,Anexo_4[periodo],$N$7)+SUMIFS(Anexo_4[base_no_grabada],Anexo_4[gastos_operativos_kpi],$E$8,Anexo_4[periodo],$N$7) -> 29322.19 | O8: =SUMIFS(Anexo_4[base_imponible_18],Anexo_4[gastos_operativos_kpi],$E$8,Anexo_4[periodo],$O$7)+SUMIFS(Anexo_4[base_imponible_10],Anexo_4[gastos_operativos_kpi],$E$8,Anexo_4[periodo],$O$7)+SUMIFS(Anexo_4[base_no_grabada],Anexo_4[gastos_operativos_kpi],$E$8,Anexo_4[periodo],$O$7) -> 29736.01 | P8: =SUMIFS(Anexo_4[base_imponible_18],Anexo_4[gastos_operativos_kpi],$E$8,Anexo_4[periodo],$P$7)+SUMIFS(Anexo_4[base_imponible_10],Anexo_4[gastos_operativos_kpi],$E$8,Anexo_4[periodo],$P$7)+SUMIFS(Anexo_4[base_no_grabada],Anexo_4[gastos_operativos_kpi],$E$8,Anexo_4[periodo],$P$7) -> 0 | Q8: =SUMIFS(Anexo_4[base_imponible_18],Anexo_4[gastos_operativos_kpi],$E$8,Anexo_4[periodo],$Q$7)+SUMIFS(Anexo_4[base_imponible_10],Anexo_4[gastos_operativos_kpi],$E$8,Anexo_4[periodo],$Q$7)+SUMIFS(Anexo_4[base_no_grabada],Anexo_4[gastos_operativos_kpi],$E$8,Anexo_4[periodo],$Q$7) -> 0 | R8: =SUMIFS(Anexo_4[base_imponible_18],Anexo_4[gastos_operativos_kpi],$E$8,Anexo_4[periodo],$R$7)+SUMIFS(Anexo_4[base_imponible_10],Anexo_4[gastos_operativos_kpi],$E$8,Anexo_4[periodo],$R$7)+SUMIFS(Anexo_4[base_no_grabada],Anexo_4[gastos_operativos_kpi],$E$8,Anexo_4[periodo],$R$7) -> 0 | S8: =SUM(G8:R8) -> 141861.8 | T8: =AVERAGE(G8:R8) -> 11821.817
C10: GASTOS OPERATIVOS | D10: GASTOS INCURRIDOS PARA LA VENTA DE RESIDUOS | E10: Transporte de Carga - Ventas | F10: Moneda | G10: =SUMIFS(Anexo_4[base_imponible_18],Anexo_4[gastos_operativos_kpi],$E$10,Anexo_4[periodo],$G$7)+SUMIFS(Anexo_4[base_imponible_10],Anexo_4[gastos_operativos_kpi],$E$10,Anexo_4[periodo],$G$7)+SUMIFS(Anexo_4[base_no_grabada],Anexo_4[gastos_operativos_kpi],$E$10,Anexo_4[periodo],$G$7) -> 0 | H10: =SUMIFS(Anexo_4[base_imponible_18],Anexo_4[gastos_operativos_kpi],$E$10,Anexo_4[periodo],$H$7)+SUMIFS(Anexo_4[base_imponible_10],Anexo_4[gastos_operativos_kpi],$E$10,Anexo_4[periodo],$H$7)+SUMIFS(Anexo_4[base_no_grabada],Anexo_4[gastos_operativos_kpi],$E$10,Anexo_4[periodo],$H$7) -> 0 | I10: =SUMIFS(Anexo_4[base_imponible_18],Anexo_4[gastos_operativos_kpi],$E$10,Anexo_4[periodo],$I$7)+SUMIFS(Anexo_4[base_imponible_10],Anexo_4[gastos_operativos_kpi],$E$10,Anexo_4[periodo],$I$7)+SUMIFS(Anexo_4[base_no_grabada],Anexo_4[gastos_operativos_kpi],$E$10,Anexo_4[periodo],$I$7) -> 0 | J10: =SUMIFS(Anexo_4[base_imponible_18],Anexo_4[gastos_operativos_kpi],$E$10,Anexo_4[periodo],$J$7)+SUMIFS(Anexo_4[base_imponible_10],Anexo_4[gastos_operativos_kpi],$E$10,Anexo_4[periodo],$J$7)+SUMIFS(Anexo_4[base_no_grabada],Anexo_4[gastos_operativos_kpi],$E$10,Anexo_4[periodo],$J$7) -> 0 | K10: =SUMIFS(Anexo_4[base_imponible_18],Anexo_4[gastos_operativos_kpi],$E$10,Anexo_4[periodo],$K$7)+SUMIFS(Anexo_4[base_imponible_10],Anexo_4[gastos_operativos_kpi],$E$10,Anexo_4[periodo],$K$7)+SUMIFS(Anexo_4[base_no_grabada],Anexo_4[gastos_operativos_kpi],$E$10,Anexo_4[periodo],$K$7) -> 0 | L10: =SUMIFS(Anexo_4[base_imponible_18],Anexo_4[gastos_operativos_kpi],$E$10,Anexo_4[periodo],$L$7)+SUMIFS(Anexo_4[base_imponible_10],Anexo_4[gastos_operativos_kpi],$E$10,Anexo_4[periodo],$L$7)+SUMIFS(Anexo_4[base_no_grabada],Anexo_4[gastos_operativos_kpi],$E$10,Anexo_4[periodo],$L$7) -> 15040.69 | M10: =SUMIFS(Anexo_4[base_imponible_18],Anexo_4[gastos_operativos_kpi],$E$10,Anexo_4[periodo],$M$7)+SUMIFS(Anexo_4[base_imponible_10],Anexo_4[gastos_operativos_kpi],$E$10,Anexo_4[periodo],$M$7)+SUMIFS(Anexo_4[base_no_grabada],Anexo_4[gastos_operativos_kpi],$E$10,Anexo_4[periodo],$M$7) -> 8148.31 | N10: =SUMIFS(Anexo_4[base_imponible_18],Anexo_4[gastos_operativos_kpi],$E$10,Anexo_4[periodo],$N$7)+SUMIFS(Anexo_4[base_imponible_10],Anexo_4[gastos_operativos_kpi],$E$10,Anexo_4[periodo],$N$7)+SUMIFS(Anexo_4[base_no_grabada],Anexo_4[gastos_operativos_kpi],$E$10,Anexo_4[periodo],$N$7) -> 7318.64 | O10: =SUMIFS(Anexo_4[base_imponible_18],Anexo_4[gastos_operativos_kpi],$E$10,Anexo_4[periodo],$O$7)+SUMIFS(Anexo_4[base_imponible_10],Anexo_4[gastos_operativos_kpi],$E$10,Anexo_4[periodo],$O$7)+SUMIFS(Anexo_4[base_no_grabada],Anexo_4[gastos_operativos_kpi],$E$10,Anexo_4[periodo],$O$7) -> 8298.31 | P10: =SUMIFS(Anexo_4[base_imponible_18],Anexo_4[gastos_operativos_kpi],$E$10,Anexo_4[periodo],$P$7)+SUMIFS(Anexo_4[base_imponible_10],Anexo_4[gastos_operativos_kpi],$E$10,Anexo_4[periodo],$P$7)+SUMIFS(Anexo_4[base_no_grabada],Anexo_4[gastos_operativos_kpi],$E$10,Anexo_4[periodo],$P$7) -> 0 | Q10: =SUMIFS(Anexo_4[base_imponible_18],Anexo_4[gastos_operativos_kpi],$E$10,Anexo_4[periodo],$Q$7)+SUMIFS(Anexo_4[base_imponible_10],Anexo_4[gastos_operativos_kpi],$E$10,Anexo_4[periodo],$Q$7)+SUMIFS(Anexo_4[base_no_grabada],Anexo_4[gastos_operativos_kpi],$E$10,Anexo_4[periodo],$Q$7) -> 0 | R10: =SUMIFS(Anexo_4[base_imponible_18],Anexo_4[gastos_operativos_kpi],$E$10,Anexo_4[periodo],$R$7)+SUMIFS(Anexo_4[base_imponible_10],Anexo_4[gastos_operativos_kpi],$E$10,Anexo_4[periodo],$R$7)+SUMIFS(Anexo_4[base_no_grabada],Anexo_4[gastos_operativos_kpi],$E$10,Anexo_4[periodo],$R$7) -> 0 | S10: =SUM(G10:R10) -> 38805.95 | T10: =AVERAGE(G10:R10) -> 3233.8292
E11: Transporte peajes - Ventas | F11: Moneda | G11: =SUMIFS(Anexo_4[base_imponible_18],Anexo_4[gastos_operativos_kpi],$E$11,Anexo_4[periodo],$G$7)+SUMIFS(Anexo_4[base_imponible_10],Anexo_4[gastos_operativos_kpi],$E$11,Anexo_4[periodo],$G$7)+SUMIFS(Anexo_4[base_no_grabada],Anexo_4[gastos_operativos_kpi],$E$11,Anexo_4[periodo],$G$7) -> 0 | H11: =SUMIFS(Anexo_4[base_imponible_18],Anexo_4[gastos_operativos_kpi],$E$11,Anexo_4[periodo],$H$7)+SUMIFS(Anexo_4[base_imponible_10],Anexo_4[gastos_operativos_kpi],$E$11,Anexo_4[periodo],$H$7)+SUMIFS(Anexo_4[base_no_grabada],Anexo_4[gastos_operativos_kpi],$E$11,Anexo_4[periodo],$H$7) -> 0 | I11: =SUMIFS(Anexo_4[base_imponible_18],Anexo_4[gastos_operativos_kpi],$E$11,Anexo_4[periodo],$I$7)+SUMIFS(Anexo_4[base_imponible_10],Anexo_4[gastos_operativos_kpi],$E$11,Anexo_4[periodo],$I$7)+SUMIFS(Anexo_4[base_no_grabada],Anexo_4[gastos_operativos_kpi],$E$11,Anexo_4[periodo],$I$7) -> 0 | J11: =SUMIFS(Anexo_4[base_imponible_18],Anexo_4[gastos_operativos_kpi],$E$11,Anexo_4[periodo],$J$7)+SUMIFS(Anexo_4[base_imponible_10],Anexo_4[gastos_operativos_kpi],$E$11,Anexo_4[periodo],$J$7)+SUMIFS(Anexo_4[base_no_grabada],Anexo_4[gastos_operativos_kpi],$E$11,Anexo_4[periodo],$J$7) -> 0 | K11: =SUMIFS(Anexo_4[base_imponible_18],Anexo_4[gastos_operativos_kpi],$E$11,Anexo_4[periodo],$K$7)+SUMIFS(Anexo_4[base_imponible_10],Anexo_4[gastos_operativos_kpi],$E$11,Anexo_4[periodo],$K$7)+SUMIFS(Anexo_4[base_no_grabada],Anexo_4[gastos_operativos_kpi],$E$11,Anexo_4[periodo],$K$7) -> 0 | L11: =SUMIFS(Anexo_4[base_imponible_18],Anexo_4[gastos_operativos_kpi],$E$11,Anexo_4[periodo],$L$7)+SUMIFS(Anexo_4[base_imponible_10],Anexo_4[gastos_operativos_kpi],$E$11,Anexo_4[periodo],$L$7)+SUMIFS(Anexo_4[base_no_grabada],Anexo_4[gastos_operativos_kpi],$E$11,Anexo_4[periodo],$L$7) -> 306.79 | M11: =SUMIFS(Anexo_4[base_imponible_18],Anexo_4[gastos_operativos_kpi],$E$11,Anexo_4[periodo],$M$7)+SUMIFS(Anexo_4[base_imponible_10],Anexo_4[gastos_operativos_kpi],$E$11,Anexo_4[periodo],$M$7)+SUMIFS(Anexo_4[base_no_grabada],Anexo_4[gastos_operativos_kpi],$E$11,Anexo_4[periodo],$M$7) -> 417.75 | N11: =SUMIFS(Anexo_4[base_imponible_18],Anexo_4[gastos_operativos_kpi],$E$11,Anexo_4[periodo],$N$7)+SUMIFS(Anexo_4[base_imponible_10],Anexo_4[gastos_operativos_kpi],$E$11,Anexo_4[periodo],$N$7)+SUMIFS(Anexo_4[base_no_grabada],Anexo_4[gastos_operativos_kpi],$E$11,Anexo_4[periodo],$N$7) -> 233.91 | O11: =SUMIFS(Anexo_4[base_imponible_18],Anexo_4[gastos_operativos_kpi],$E$11,Anexo_4[periodo],$O$7)+SUMIFS(Anexo_4[base_imponible_10],Anexo_4[gastos_operativos_kpi],$E$11,Anexo_4[periodo],$O$7)+SUMIFS(Anexo_4[base_no_grabada],Anexo_4[gastos_operativos_kpi],$E$11,Anexo_4[periodo],$O$7) -> 183.06 | P11: =SUMIFS(Anexo_4[base_imponible_18],Anexo_4[gastos_operativos_kpi],$E$11,Anexo_4[periodo],$P$7)+SUMIFS(Anexo_4[base_imponible_10],Anexo_4[gastos_operativos_kpi],$E$11,Anexo_4[periodo],$P$7)+SUMIFS(Anexo_4[base_no_grabada],Anexo_4[gastos_operativos_kpi],$E$11,Anexo_4[periodo],$P$7) -> 0 | Q11: =SUMIFS(Anexo_4[base_imponible_18],Anexo_4[gastos_operativos_kpi],$E$11,Anexo_4[periodo],$Q$7)+SUMIFS(Anexo_4[base_imponible_10],Anexo_4[gastos_operativos_kpi],$E$11,Anexo_4[periodo],$Q$7)+SUMIFS(Anexo_4[base_no_grabada],Anexo_4[gastos_operativos_kpi],$E$11,Anexo_4[periodo],$Q$7) -> 0 | R11: =SUMIFS(Anexo_4[base_imponible_18],Anexo_4[gastos_operativos_kpi],$E$11,Anexo_4[periodo],$R$7)+SUMIFS(Anexo_4[base_imponible_10],Anexo_4[gastos_operativos_kpi],$E$11,Anexo_4[periodo],$R$7)+SUMIFS(Anexo_4[base_no_grabada],Anexo_4[gastos_operativos_kpi],$E$11,Anexo_4[periodo],$R$7) -> 0 | S11: =SUM(G11:R11) -> 1141.51 | T11: =AVERAGE(G11:R11) -> 95.125833
E12: Balanza - Ventas | F12: Moneda | G12: =SUMIFS(Anexo_4[base_imponible_18],Anexo_4[gastos_operativos_kpi],$E$12,Anexo_4[periodo],$G$7)+SUMIFS(Anexo_4[base_imponible_10],Anexo_4[gastos_operativos_kpi],$E$12,Anexo_4[periodo],$G$7)+SUMIFS(Anexo_4[base_no_grabada],Anexo_4[gastos_operativos_kpi],$E$12,Anexo_4[periodo],$G$7) -> 0 | H12: =SUMIFS(Anexo_4[base_imponible_18],Anexo_4[gastos_operativos_kpi],$E$12,Anexo_4[periodo],$H$7)+SUMIFS(Anexo_4[base_imponible_10],Anexo_4[gastos_operativos_kpi],$E$12,Anexo_4[periodo],$H$7)+SUMIFS(Anexo_4[base_no_grabada],Anexo_4[gastos_operativos_kpi],$E$12,Anexo_4[periodo],$H$7) -> 0 | I12: =SUMIFS(Anexo_4[base_imponible_18],Anexo_4[gastos_operativos_kpi],$E$12,Anexo_4[periodo],$I$7)+SUMIFS(Anexo_4[base_imponible_10],Anexo_4[gastos_operativos_kpi],$E$12,Anexo_4[periodo],$I$7)+SUMIFS(Anexo_4[base_no_grabada],Anexo_4[gastos_operativos_kpi],$E$12,Anexo_4[periodo],$I$7) -> 0 | J12: =SUMIFS(Anexo_4[base_imponible_18],Anexo_4[gastos_operativos_kpi],$E$12,Anexo_4[periodo],$J$7)+SUMIFS(Anexo_4[base_imponible_10],Anexo_4[gastos_operativos_kpi],$E$12,Anexo_4[periodo],$J$7)+SUMIFS(Anexo_4[base_no_grabada],Anexo_4[gastos_operativos_kpi],$E$12,Anexo_4[periodo],$J$7) -> 0 | K12: =SUMIFS(Anexo_4[base_imponible_18],Anexo_4[gastos_operativos_kpi],$E$12,Anexo_4[periodo],$K$7)+SUMIFS(Anexo_4[base_imponible_10],Anexo_4[gastos_operativos_kpi],$E$12,Anexo_4[periodo],$K$7)+SUMIFS(Anexo_4[base_no_grabada],Anexo_4[gastos_operativos_kpi],$E$12,Anexo_4[periodo],$K$7) -> 0 | L12: =SUMIFS(Anexo_4[base_imponible_18],Anexo_4[gastos_operativos_kpi],$E$12,Anexo_4[periodo],$L$7)+SUMIFS(Anexo_4[base_imponible_10],Anexo_4[gastos_operativos_kpi],$E$12,Anexo_4[periodo],$L$7)+SUMIFS(Anexo_4[base_no_grabada],Anexo_4[gastos_operativos_kpi],$E$12,Anexo_4[periodo],$L$7) -> 253.28 | M12: =SUMIFS(Anexo_4[base_imponible_18],Anexo_4[gastos_operativos_kpi],$E$12,Anexo_4[periodo],$M$7)+SUMIFS(Anexo_4[base_imponible_10],Anexo_4[gastos_operativos_kpi],$E$12,Anexo_4[periodo],$M$7)+SUMIFS(Anexo_4[base_no_grabada],Anexo_4[gastos_operativos_kpi],$E$12,Anexo_4[periodo],$M$7) -> 273.69 | N12: =SUMIFS(Anexo_4[base_imponible_18],Anexo_4[gastos_operativos_kpi],$E$12,Anexo_4[periodo],$N$7)+SUMIFS(Anexo_4[base_imponible_10],Anexo_4[gastos_operativos_kpi],$E$12,Anexo_4[periodo],$N$7)+SUMIFS(Anexo_4[base_no_grabada],Anexo_4[gastos_operativos_kpi],$E$12,Anexo_4[periodo],$N$7) -> 213.46 | O12: =SUMIFS(Anexo_4[base_imponible_18],Anexo_4[gastos_operativos_kpi],$E$12,Anexo_4[periodo],$O$7)+SUMIFS(Anexo_4[base_imponible_10],Anexo_4[gastos_operativos_kpi],$E$12,Anexo_4[periodo],$O$7)+SUMIFS(Anexo_4[base_no_grabada],Anexo_4[gastos_operativos_kpi],$E$12,Anexo_4[periodo],$O$7) -> 151.65 | P12: =SUMIFS(Anexo_4[base_imponible_18],Anexo_4[gastos_operativos_kpi],$E$12,Anexo_4[periodo],$P$7)+SUMIFS(Anexo_4[base_imponible_10],Anexo_4[gastos_operativos_kpi],$E$12,Anexo_4[periodo],$P$7)+SUMIFS(Anexo_4[base_no_grabada],Anexo_4[gastos_operativos_kpi],$E$12,Anexo_4[periodo],$P$7) -> 0 | Q12: =SUMIFS(Anexo_4[base_imponible_18],Anexo_4[gastos_operativos_kpi],$E$12,Anexo_4[periodo],$Q$7)+SUMIFS(Anexo_4[base_imponible_10],Anexo_4[gastos_operativos_kpi],$E$12,Anexo_4[periodo],$Q$7)+SUMIFS(Anexo_4[base_no_grabada],Anexo_4[gastos_operativos_kpi],$E$12,Anexo_4[periodo],$Q$7) -> 0 | R12: =SUMIFS(Anexo_4[base_imponible_18],Anexo_4[gastos_operativos_kpi],$E$12,Anexo_4[periodo],$R$7)+SUMIFS(Anexo_4[base_imponible_10],Anexo_4[gastos_operativos_kpi],$E$12,Anexo_4[periodo],$R$7)+SUMIFS(Anexo_4[base_no_grabada],Anexo_4[gastos_operativos_kpi],$E$12,Anexo_4[periodo],$R$7) -> 0 | S12: =SUM(G12:R12) -> 892.08 | T12: =AVERAGE(G12:R12) -> 74.34
E13: Montacarga - Ventas | F13: Moneda | G13: =SUMIFS(Anexo_4[base_imponible_18],Anexo_4[gastos_operativos_kpi],$E$13,Anexo_4[periodo],$G$7)+SUMIFS(Anexo_4[base_imponible_10],Anexo_4[gastos_operativos_kpi],$E$13,Anexo_4[periodo],$G$7)+SUMIFS(Anexo_4[base_no_grabada],Anexo_4[gastos_operativos_kpi],$E$13,Anexo_4[periodo],$G$7) -> 0 | H13: =SUMIFS(Anexo_4[base_imponible_18],Anexo_4[gastos_operativos_kpi],$E$13,Anexo_4[periodo],$H$7)+SUMIFS(Anexo_4[base_imponible_10],Anexo_4[gastos_operativos_kpi],$E$13,Anexo_4[periodo],$H$7)+SUMIFS(Anexo_4[base_no_grabada],Anexo_4[gastos_operativos_kpi],$E$13,Anexo_4[periodo],$H$7) -> 0 | I13: =SUMIFS(Anexo_4[base_imponible_18],Anexo_4[gastos_operativos_kpi],$E$13,Anexo_4[periodo],$I$7)+SUMIFS(Anexo_4[base_imponible_10],Anexo_4[gastos_operativos_kpi],$E$13,Anexo_4[periodo],$I$7)+SUMIFS(Anexo_4[base_no_grabada],Anexo_4[gastos_operativos_kpi],$E$13,Anexo_4[periodo],$I$7) -> 0 | J13: =SUMIFS(Anexo_4[base_imponible_18],Anexo_4[gastos_operativos_kpi],$E$13,Anexo_4[periodo],$J$7)+SUMIFS(Anexo_4[base_imponible_10],Anexo_4[gastos_operativos_kpi],$E$13,Anexo_4[periodo],$J$7)+SUMIFS(Anexo_4[base_no_grabada],Anexo_4[gastos_operativos_kpi],$E$13,Anexo_4[periodo],$J$7) -> 0 | K13: =SUMIFS(Anexo_4[base_imponible_18],Anexo_4[gastos_operativos_kpi],$E$13,Anexo_4[periodo],$K$7)+SUMIFS(Anexo_4[base_imponible_10],Anexo_4[gastos_operativos_kpi],$E$13,Anexo_4[periodo],$K$7)+SUMIFS(Anexo_4[base_no_grabada],Anexo_4[gastos_operativos_kpi],$E$13,Anexo_4[periodo],$K$7) -> 0 | L13: =SUMIFS(Anexo_4[base_imponible_18],Anexo_4[gastos_operativos_kpi],$E$13,Anexo_4[periodo],$L$7)+SUMIFS(Anexo_4[base_imponible_10],Anexo_4[gastos_operativos_kpi],$E$13,Anexo_4[periodo],$L$7)+SUMIFS(Anexo_4[base_no_grabada],Anexo_4[gastos_operativos_kpi],$E$13,Anexo_4[periodo],$L$7) -> 4207.5 | M13: =SUMIFS(Anexo_4[base_imponible_18],Anexo_4[gastos_operativos_kpi],$E$13,Anexo_4[periodo],$M$7)+SUMIFS(Anexo_4[base_imponible_10],Anexo_4[gastos_operativos_kpi],$E$13,Anexo_4[periodo],$M$7)+SUMIFS(Anexo_4[base_no_grabada],Anexo_4[gastos_operativos_kpi],$E$13,Anexo_4[periodo],$M$7) -> 2188.75 | N13: =SUMIFS(Anexo_4[base_imponible_18],Anexo_4[gastos_operativos_kpi],$E$13,Anexo_4[periodo],$N$7)+SUMIFS(Anexo_4[base_imponible_10],Anexo_4[gastos_operativos_kpi],$E$13,Anexo_4[periodo],$N$7)+SUMIFS(Anexo_4[base_no_grabada],Anexo_4[gastos_operativos_kpi],$E$13,Anexo_4[periodo],$N$7) -> 1643.75 | O13: =SUMIFS(Anexo_4[base_imponible_18],Anexo_4[gastos_operativos_kpi],$E$13,Anexo_4[periodo],$O$7)+SUMIFS(Anexo_4[base_imponible_10],Anexo_4[gastos_operativos_kpi],$E$13,Anexo_4[periodo],$O$7)+SUMIFS(Anexo_4[base_no_grabada],Anexo_4[gastos_operativos_kpi],$E$13,Anexo_4[periodo],$O$7) -> 1190 | P13: =SUMIFS(Anexo_4[base_imponible_18],Anexo_4[gastos_operativos_kpi],$E$13,Anexo_4[periodo],$P$7)+SUMIFS(Anexo_4[base_imponible_10],Anexo_4[gastos_operativos_kpi],$E$13,Anexo_4[periodo],$P$7)+SUMIFS(Anexo_4[base_no_grabada],Anexo_4[gastos_operativos_kpi],$E$13,Anexo_4[periodo],$P$7) -> 0 | Q13: =SUMIFS(Anexo_4[base_imponible_18],Anexo_4[gastos_operativos_kpi],$E$13,Anexo_4[periodo],$Q$7)+SUMIFS(Anexo_4[base_imponible_10],Anexo_4[gastos_operativos_kpi],$E$13,Anexo_4[periodo],$Q$7)+SUMIFS(Anexo_4[base_no_grabada],Anexo_4[gastos_operativos_kpi],$E$13,Anexo_4[periodo],$Q$7) -> 0 | R13: =SUMIFS(Anexo_4[base_imponible_18],Anexo_4[gastos_operativos_kpi],$E$13,Anexo_4[periodo],$R$7)+SUMIFS(Anexo_4[base_imponible_10],Anexo_4[gastos_operativos_kpi],$E$13,Anexo_4[periodo],$R$7)+SUMIFS(Anexo_4[base_no_grabada],Anexo_4[gastos_operativos_kpi],$E$13,Anexo_4[periodo],$R$7) -> 0 | S13: =SUM(G13:R13) -> 9230 | T13: =AVERAGE(G13:R13) -> 769.16667
E14: Maquinaria Pesada - Ventas | F14: Moneda | G14: =SUMIFS(Anexo_4[base_imponible_18],Anexo_4[gastos_operativos_kpi],$E$14,Anexo_4[periodo],$G$7)+SUMIFS(Anexo_4[base_imponible_10],Anexo_4[gastos_operativos_kpi],$E$14,Anexo_4[periodo],$G$7)+SUMIFS(Anexo_4[base_no_grabada],Anexo_4[gastos_operativos_kpi],$E$14,Anexo_4[periodo],$G$7) -> 0 | H14: =SUMIFS(Anexo_4[base_imponible_18],Anexo_4[gastos_operativos_kpi],$E$14,Anexo_4[periodo],$H$7)+SUMIFS(Anexo_4[base_imponible_10],Anexo_4[gastos_operativos_kpi],$E$14,Anexo_4[periodo],$H$7)+SUMIFS(Anexo_4[base_no_grabada],Anexo_4[gastos_operativos_kpi],$E$14,Anexo_4[periodo],$H$7) -> 0 | I14: =SUMIFS(Anexo_4[base_imponible_18],Anexo_4[gastos_operativos_kpi],$E$14,Anexo_4[periodo],$I$7)+SUMIFS(Anexo_4[base_imponible_10],Anexo_4[gastos_operativos_kpi],$E$14,Anexo_4[periodo],$I$7)+SUMIFS(Anexo_4[base_no_grabada],Anexo_4[gastos_operativos_kpi],$E$14,Anexo_4[periodo],$I$7) -> 0 | J14: =SUMIFS(Anexo_4[base_imponible_18],Anexo_4[gastos_operativos_kpi],$E$14,Anexo_4[periodo],$J$7)+SUMIFS(Anexo_4[base_imponible_10],Anexo_4[gastos_operativos_kpi],$E$14,Anexo_4[periodo],$J$7)+SUMIFS(Anexo_4[base_no_grabada],Anexo_4[gastos_operativos_kpi],$E$14,Anexo_4[periodo],$J$7) -> 0 | K14: =SUMIFS(Anexo_4[base_imponible_18],Anexo_4[gastos_operativos_kpi],$E$14,Anexo_4[periodo],$K$7)+SUMIFS(Anexo_4[base_imponible_10],Anexo_4[gastos_operativos_kpi],$E$14,Anexo_4[periodo],$K$7)+SUMIFS(Anexo_4[base_no_grabada],Anexo_4[gastos_operativos_kpi],$E$14,Anexo_4[periodo],$K$7) -> 0 | L14: =SUMIFS(Anexo_4[base_imponible_18],Anexo_4[gastos_operativos_kpi],$E$14,Anexo_4[periodo],$L$7)+SUMIFS(Anexo_4[base_imponible_10],Anexo_4[gastos_operativos_kpi],$E$14,Anexo_4[periodo],$L$7)+SUMIFS(Anexo_4[base_no_grabada],Anexo_4[gastos_operativos_kpi],$E$14,Anexo_4[periodo],$L$7) -> 0 | M14: =SUMIFS(Anexo_4[base_imponible_18],Anexo_4[gastos_operativos_kpi],$E$14,Anexo_4[periodo],$M$7)+SUMIFS(Anexo_4[base_imponible_10],Anexo_4[gastos_operativos_kpi],$E$14,Anexo_4[periodo],$M$7)+SUMIFS(Anexo_4[base_no_grabada],Anexo_4[gastos_operativos_kpi],$E$14,Anexo_4[periodo],$M$7) -> 330 | N14: =SUMIFS(Anexo_4[base_imponible_18],Anexo_4[gastos_operativos_kpi],$E$14,Anexo_4[periodo],$N$7)+SUMIFS(Anexo_4[base_imponible_10],Anexo_4[gastos_operativos_kpi],$E$14,Anexo_4[periodo],$N$7)+SUMIFS(Anexo_4[base_no_grabada],Anexo_4[gastos_operativos_kpi],$E$14,Anexo_4[periodo],$N$7) -> 0 | O14: =SUMIFS(Anexo_4[base_imponible_18],Anexo_4[gastos_operativos_kpi],$E$14,Anexo_4[periodo],$O$7)+SUMIFS(Anexo_4[base_imponible_10],Anexo_4[gastos_operativos_kpi],$E$14,Anexo_4[periodo],$O$7)+SUMIFS(Anexo_4[base_no_grabada],Anexo_4[gastos_operativos_kpi],$E$14,Anexo_4[periodo],$O$7) -> 0 | P14: =SUMIFS(Anexo_4[base_imponible_18],Anexo_4[gastos_operativos_kpi],$E$14,Anexo_4[periodo],$P$7)+SUMIFS(Anexo_4[base_imponible_10],Anexo_4[gastos_operativos_kpi],$E$14,Anexo_4[periodo],$P$7)+SUMIFS(Anexo_4[base_no_grabada],Anexo_4[gastos_operativos_kpi],$E$14,Anexo_4[periodo],$P$7) -> 0 | Q14: =SUMIFS(Anexo_4[base_imponible_18],Anexo_4[gastos_operativos_kpi],$E$14,Anexo_4[periodo],$Q$7)+SUMIFS(Anexo_4[base_imponible_10],Anexo_4[gastos_operativos_kpi],$E$14,Anexo_4[periodo],$Q$7)+SUMIFS(Anexo_4[base_no_grabada],Anexo_4[gastos_operativos_kpi],$E$14,Anexo_4[periodo],$Q$7) -> 0 | R14: =SUMIFS(Anexo_4[base_imponible_18],Anexo_4[gastos_operativos_kpi],$E$14,Anexo_4[periodo],$R$7)+SUMIFS(Anexo_4[base_imponible_10],Anexo_4[gastos_operativos_kpi],$E$14,Anexo_4[periodo],$R$7)+SUMIFS(Anexo_4[base_no_grabada],Anexo_4[gastos_operativos_kpi],$E$14,Anexo_4[periodo],$R$7) -> 0 | S14: =SUM(G14:R14) -> 330 | T14: =AVERAGE(G14:R14) -> 27.5
E15: Disposición Final de RR.SS - Peligrosos | F15: Moneda | G15: =SUMIFS(Anexo_4[base_imponible_18],Anexo_4[gastos_operativos_kpi],$E$15,Anexo_4[periodo],$G$7)+SUMIFS(Anexo_4[base_imponible_10],Anexo_4[gastos_operativos_kpi],$E$15,Anexo_4[periodo],$G$7)+SUMIFS(Anexo_4[base_no_grabada],Anexo_4[gastos_operativos_kpi],$E$15,Anexo_4[periodo],$G$7) -> 0 | H15: =SUMIFS(Anexo_4[base_imponible_18],Anexo_4[gastos_operativos_kpi],$E$15,Anexo_4[periodo],$H$7)+SUMIFS(Anexo_4[base_imponible_10],Anexo_4[gastos_operativos_kpi],$E$15,Anexo_4[periodo],$H$7)+SUMIFS(Anexo_4[base_no_grabada],Anexo_4[gastos_operativos_kpi],$E$15,Anexo_4[periodo],$H$7) -> 0 | I15: =SUMIFS(Anexo_4[base_imponible_18],Anexo_4[gastos_operativos_kpi],$E$15,Anexo_4[periodo],$I$7)+SUMIFS(Anexo_4[base_imponible_10],Anexo_4[gastos_operativos_kpi],$E$15,Anexo_4[periodo],$I$7)+SUMIFS(Anexo_4[base_no_grabada],Anexo_4[gastos_operativos_kpi],$E$15,Anexo_4[periodo],$I$7) -> 0 | J15: =SUMIFS(Anexo_4[base_imponible_18],Anexo_4[gastos_operativos_kpi],$E$15,Anexo_4[periodo],$J$7)+SUMIFS(Anexo_4[base_imponible_10],Anexo_4[gastos_operativos_kpi],$E$15,Anexo_4[periodo],$J$7)+SUMIFS(Anexo_4[base_no_grabada],Anexo_4[gastos_operativos_kpi],$E$15,Anexo_4[periodo],$J$7) -> 0 | K15: =SUMIFS(Anexo_4[base_imponible_18],Anexo_4[gastos_operativos_kpi],$E$15,Anexo_4[periodo],$K$7)+SUMIFS(Anexo_4[base_imponible_10],Anexo_4[gastos_operativos_kpi],$E$15,Anexo_4[periodo],$K$7)+SUMIFS(Anexo_4[base_no_grabada],Anexo_4[gastos_operativos_kpi],$E$15,Anexo_4[periodo],$K$7) -> 0 | L15: =SUMIFS(Anexo_4[base_imponible_18],Anexo_4[gastos_operativos_kpi],$E$15,Anexo_4[periodo],$L$7)+SUMIFS(Anexo_4[base_imponible_10],Anexo_4[gastos_operativos_kpi],$E$15,Anexo_4[periodo],$L$7)+SUMIFS(Anexo_4[base_no_grabada],Anexo_4[gastos_operativos_kpi],$E$15,Anexo_4[periodo],$L$7) -> 16437.48 | M15: =SUMIFS(Anexo_4[base_imponible_18],Anexo_4[gastos_operativos_kpi],$E$15,Anexo_4[periodo],$M$7)+SUMIFS(Anexo_4[base_imponible_10],Anexo_4[gastos_operativos_kpi],$E$15,Anexo_4[periodo],$M$7)+SUMIFS(Anexo_4[base_no_grabada],Anexo_4[gastos_operativos_kpi],$E$15,Anexo_4[periodo],$M$7) -> 26297 | N15: =SUMIFS(Anexo_4[base_imponible_18],Anexo_4[gastos_operativos_kpi],$E$15,Anexo_4[periodo],$N$7)+SUMIFS(Anexo_4[base_imponible_10],Anexo_4[gastos_operativos_kpi],$E$15,Anexo_4[periodo],$N$7)+SUMIFS(Anexo_4[base_no_grabada],Anexo_4[gastos_operativos_kpi],$E$15,Anexo_4[periodo],$N$7) -> 15935.08 | O15: =SUMIFS(Anexo_4[base_imponible_18],Anexo_4[gastos_operativos_kpi],$E$15,Anexo_4[periodo],$O$7)+SUMIFS(Anexo_4[base_imponible_10],Anexo_4[gastos_operativos_kpi],$E$15,Anexo_4[periodo],$O$7)+SUMIFS(Anexo_4[base_no_grabada],Anexo_4[gastos_operativos_kpi],$E$15,Anexo_4[periodo],$O$7) -> 22731.92 | P15: =SUMIFS(Anexo_4[base_imponible_18],Anexo_4[gastos_operativos_kpi],$E$15,Anexo_4[periodo],$P$7)+SUMIFS(Anexo_4[base_imponible_10],Anexo_4[gastos_operativos_kpi],$E$15,Anexo_4[periodo],$P$7)+SUMIFS(Anexo_4[base_no_grabada],Anexo_4[gastos_operativos_kpi],$E$15,Anexo_4[periodo],$P$7) -> 0 | Q15: =SUMIFS(Anexo_4[base_imponible_18],Anexo_4[gastos_operativos_kpi],$E$15,Anexo_4[periodo],$Q$7)+SUMIFS(Anexo_4[base_imponible_10],Anexo_4[gastos_operativos_kpi],$E$15,Anexo_4[periodo],$Q$7)+SUMIFS(Anexo_4[base_no_grabada],Anexo_4[gastos_operativos_kpi],$E$15,Anexo_4[periodo],$Q$7) -> 0 | R15: =SUMIFS(Anexo_4[base_imponible_18],Anexo_4[gastos_operativos_kpi],$E$15,Anexo_4[periodo],$R$7)+SUMIFS(Anexo_4[base_imponible_10],Anexo_4[gastos_operativos_kpi],$E$15,Anexo_4[periodo],$R$7)+SUMIFS(Anexo_4[base_no_grabada],Anexo_4[gastos_operativos_kpi],$E$15,Anexo_4[periodo],$R$7) -> 0 | S15: =SUM(G15:R15) -> 81401.48 | T15: =AVERAGE(G15:R15) -> 6783.4567
E16: Disposición Final de RR.SS - No Aprovechables | F16: Moneda | G16: =SUMIFS(Anexo_4[base_imponible_18],Anexo_4[gastos_operativos_kpi],$E$16,Anexo_4[periodo],$G$7)+SUMIFS(Anexo_4[base_imponible_10],Anexo_4[gastos_operativos_kpi],$E$16,Anexo_4[periodo],$G$7)+SUMIFS(Anexo_4[base_no_grabada],Anexo_4[gastos_operativos_kpi],$E$16,Anexo_4[periodo],$G$7) -> 0 | H16: =SUMIFS(Anexo_4[base_imponible_18],Anexo_4[gastos_operativos_kpi],$E$16,Anexo_4[periodo],$H$7)+SUMIFS(Anexo_4[base_imponible_10],Anexo_4[gastos_operativos_kpi],$E$16,Anexo_4[periodo],$H$7)+SUMIFS(Anexo_4[base_no_grabada],Anexo_4[gastos_operativos_kpi],$E$16,Anexo_4[periodo],$H$7) -> 0 | I16: =SUMIFS(Anexo_4[base_imponible_18],Anexo_4[gastos_operativos_kpi],$E$16,Anexo_4[periodo],$I$7)+SUMIFS(Anexo_4[base_imponible_10],Anexo_4[gastos_operativos_kpi],$E$16,Anexo_4[periodo],$I$7)+SUMIFS(Anexo_4[base_no_grabada],Anexo_4[gastos_operativos_kpi],$E$16,Anexo_4[periodo],$I$7) -> 0 | J16: =SUMIFS(Anexo_4[base_imponible_18],Anexo_4[gastos_operativos_kpi],$E$16,Anexo_4[periodo],$J$7)+SUMIFS(Anexo_4[base_imponible_10],Anexo_4[gastos_operativos_kpi],$E$16,Anexo_4[periodo],$J$7)+SUMIFS(Anexo_4[base_no_grabada],Anexo_4[gastos_operativos_kpi],$E$16,Anexo_4[periodo],$J$7) -> 0 | K16: =SUMIFS(Anexo_4[base_imponible_18],Anexo_4[gastos_operativos_kpi],$E$16,Anexo_4[periodo],$K$7)+SUMIFS(Anexo_4[base_imponible_10],Anexo_4[gastos_operativos_kpi],$E$16,Anexo_4[periodo],$K$7)+SUMIFS(Anexo_4[base_no_grabada],Anexo_4[gastos_operativos_kpi],$E$16,Anexo_4[periodo],$K$7) -> 0 | L16: =SUMIFS(Anexo_4[base_imponible_18],Anexo_4[gastos_operativos_kpi],$E$16,Anexo_4[periodo],$L$7)+SUMIFS(Anexo_4[base_imponible_10],Anexo_4[gastos_operativos_kpi],$E$16,Anexo_4[periodo],$L$7)+SUMIFS(Anexo_4[base_no_grabada],Anexo_4[gastos_operativos_kpi],$E$16,Anexo_4[periodo],$L$7) -> 362.6 | M16: =SUMIFS(Anexo_4[base_imponible_18],Anexo_4[gastos_operativos_kpi],$E$16,Anexo_4[periodo],$M$7)+SUMIFS(Anexo_4[base_imponible_10],Anexo_4[gastos_operativos_kpi],$E$16,Anexo_4[periodo],$M$7)+SUMIFS(Anexo_4[base_no_grabada],Anexo_4[gastos_operativos_kpi],$E$16,Anexo_4[periodo],$M$7) -> 1220.28 | N16: =SUMIFS(Anexo_4[base_imponible_18],Anexo_4[gastos_operativos_kpi],$E$16,Anexo_4[periodo],$N$7)+SUMIFS(Anexo_4[base_imponible_10],Anexo_4[gastos_operativos_kpi],$E$16,Anexo_4[periodo],$N$7)+SUMIFS(Anexo_4[base_no_grabada],Anexo_4[gastos_operativos_kpi],$E$16,Anexo_4[periodo],$N$7) -> 1907.34 | O16: =SUMIFS(Anexo_4[base_imponible_18],Anexo_4[gastos_operativos_kpi],$E$16,Anexo_4[periodo],$O$7)+SUMIFS(Anexo_4[base_imponible_10],Anexo_4[gastos_operativos_kpi],$E$16,Anexo_4[periodo],$O$7)+SUMIFS(Anexo_4[base_no_grabada],Anexo_4[gastos_operativos_kpi],$E$16,Anexo_4[periodo],$O$7) -> 3369.27 | P16: =SUMIFS(Anexo_4[base_imponible_18],Anexo_4[gastos_operativos_kpi],$E$16,Anexo_4[periodo],$P$7)+SUMIFS(Anexo_4[base_imponible_10],Anexo_4[gastos_operativos_kpi],$E$16,Anexo_4[periodo],$P$7)+SUMIFS(Anexo_4[base_no_grabada],Anexo_4[gastos_operativos_kpi],$E$16,Anexo_4[periodo],$P$7) -> 0 | Q16: =SUMIFS(Anexo_4[base_imponible_18],Anexo_4[gastos_operativos_kpi],$E$16,Anexo_4[periodo],$Q$7)+SUMIFS(Anexo_4[base_imponible_10],Anexo_4[gastos_operativos_kpi],$E$16,Anexo_4[periodo],$Q$7)+SUMIFS(Anexo_4[base_no_grabada],Anexo_4[gastos_operativos_kpi],$E$16,Anexo_4[periodo],$Q$7) -> 0 | R16: =SUMIFS(Anexo_4[base_imponible_18],Anexo_4[gastos_operativos_kpi],$E$16,Anexo_4[periodo],$R$7)+SUMIFS(Anexo_4[base_imponible_10],Anexo_4[gastos_operativos_kpi],$E$16,Anexo_4[periodo],$R$7)+SUMIFS(Anexo_4[base_no_grabada],Anexo_4[gastos_operativos_kpi],$E$16,Anexo_4[periodo],$R$7) -> 0 | S16: =SUM(G16:R16) -> 6859.49 | T16: =AVERAGE(G16:R16) -> 571.62417
E17: Disposición Final de RR.SS - SS | F17: Moneda | G17: =SUMIFS(Anexo_4[base_imponible_18],Anexo_4[gastos_operativos_kpi],$E$17,Anexo_4[periodo],$G$7)+SUMIFS(Anexo_4[base_imponible_10],Anexo_4[gastos_operativos_kpi],$E$17,Anexo_4[periodo],$G$7)+SUMIFS(Anexo_4[base_no_grabada],Anexo_4[gastos_operativos_kpi],$E$17,Anexo_4[periodo],$G$7) -> 0 | H17: =SUMIFS(Anexo_4[base_imponible_18],Anexo_4[gastos_operativos_kpi],$E$17,Anexo_4[periodo],$H$7)+SUMIFS(Anexo_4[base_imponible_10],Anexo_4[gastos_operativos_kpi],$E$17,Anexo_4[periodo],$H$7)+SUMIFS(Anexo_4[base_no_grabada],Anexo_4[gastos_operativos_kpi],$E$17,Anexo_4[periodo],$H$7) -> 0 | I17: =SUMIFS(Anexo_4[base_imponible_18],Anexo_4[gastos_operativos_kpi],$E$17,Anexo_4[periodo],$I$7)+SUMIFS(Anexo_4[base_imponible_10],Anexo_4[gastos_operativos_kpi],$E$17,Anexo_4[periodo],$I$7)+SUMIFS(Anexo_4[base_no_grabada],Anexo_4[gastos_operativos_kpi],$E$17,Anexo_4[periodo],$I$7) -> 0 | J17: =SUMIFS(Anexo_4[base_imponible_18],Anexo_4[gastos_operativos_kpi],$E$17,Anexo_4[periodo],$J$7)+SUMIFS(Anexo_4[base_imponible_10],Anexo_4[gastos_operativos_kpi],$E$17,Anexo_4[periodo],$J$7)+SUMIFS(Anexo_4[base_no_grabada],Anexo_4[gastos_operativos_kpi],$E$17,Anexo_4[periodo],$J$7) -> 0 | K17: =SUMIFS(Anexo_4[base_imponible_18],Anexo_4[gastos_operativos_kpi],$E$17,Anexo_4[periodo],$K$7)+SUMIFS(Anexo_4[base_imponible_10],Anexo_4[gastos_operativos_kpi],$E$17,Anexo_4[periodo],$K$7)+SUMIFS(Anexo_4[base_no_grabada],Anexo_4[gastos_operativos_kpi],$E$17,Anexo_4[periodo],$K$7) -> 0 | L17: =SUMIFS(Anexo_4[base_imponible_18],Anexo_4[gastos_operativos_kpi],$E$17,Anexo_4[periodo],$L$7)+SUMIFS(Anexo_4[base_imponible_10],Anexo_4[gastos_operativos_kpi],$E$17,Anexo_4[periodo],$L$7)+SUMIFS(Anexo_4[base_no_grabada],Anexo_4[gastos_operativos_kpi],$E$17,Anexo_4[periodo],$L$7) -> 0 | M17: =SUMIFS(Anexo_4[base_imponible_18],Anexo_4[gastos_operativos_kpi],$E$17,Anexo_4[periodo],$M$7)+SUMIFS(Anexo_4[base_imponible_10],Anexo_4[gastos_operativos_kpi],$E$17,Anexo_4[periodo],$M$7)+SUMIFS(Anexo_4[base_no_grabada],Anexo_4[gastos_operativos_kpi],$E$17,Anexo_4[periodo],$M$7) -> 0 | N17: =SUMIFS(Anexo_4[base_imponible_18],Anexo_4[gastos_operativos_kpi],$E$17,Anexo_4[periodo],$N$7)+SUMIFS(Anexo_4[base_imponible_10],Anexo_4[gastos_operativos_kpi],$E$17,Anexo_4[periodo],$N$7)+SUMIFS(Anexo_4[base_no_grabada],Anexo_4[gastos_operativos_kpi],$E$17,Anexo_4[periodo],$N$7) -> 0 | O17: =SUMIFS(Anexo_4[base_imponible_18],Anexo_4[gastos_operativos_kpi],$E$17,Anexo_4[periodo],$O$7)+SUMIFS(Anexo_4[base_imponible_10],Anexo_4[gastos_operativos_kpi],$E$17,Anexo_4[periodo],$O$7)+SUMIFS(Anexo_4[base_no_grabada],Anexo_4[gastos_operativos_kpi],$E$17,Anexo_4[periodo],$O$7) -> 0 | P17: =SUMIFS(Anexo_4[base_imponible_18],Anexo_4[gastos_operativos_kpi],$E$17,Anexo_4[periodo],$P$7)+SUMIFS(Anexo_4[base_imponible_10],Anexo_4[gastos_operativos_kpi],$E$17,Anexo_4[periodo],$P$7)+SUMIFS(Anexo_4[base_no_grabada],Anexo_4[gastos_operativos_kpi],$E$17,Anexo_4[periodo],$P$7) -> 0 | Q17: =SUMIFS(Anexo_4[base_imponible_18],Anexo_4[gastos_operativos_kpi],$E$17,Anexo_4[periodo],$Q$7)+SUMIFS(Anexo_4[base_imponible_10],Anexo_4[gastos_operativos_kpi],$E$17,Anexo_4[periodo],$Q$7)+SUMIFS(Anexo_4[base_no_grabada],Anexo_4[gastos_operativos_kpi],$E$17,Anexo_4[periodo],$Q$7) -> 0 | R17: =SUMIFS(Anexo_4[base_imponible_18],Anexo_4[gastos_operativos_kpi],$E$17,Anexo_4[periodo],$R$7)+SUMIFS(Anexo_4[base_imponible_10],Anexo_4[gastos_operativos_kpi],$E$17,Anexo_4[periodo],$R$7)+SUMIFS(Anexo_4[base_no_grabada],Anexo_4[gastos_operativos_kpi],$E$17,Anexo_4[periodo],$R$7) -> 0 | S17: =SUM(G17:R17) -> 0 | T17: =AVERAGE(G17:R17) -> 0
E18: Gastos Variables | F18: Moneda | G18: ='DETALLE GASTOS FIJOS Y VARIABLE'!$F$34*$G$47 -> 0 | H18: ='DETALLE GASTOS FIJOS Y VARIABLE'!$G$34*$H$47 -> 0 | I18: =+'DETALLE GASTOS FIJOS Y VARIABLE'!$H$34*$I$47 -> 0 | J18: ='DETALLE GASTOS FIJOS Y VARIABLE'!$I$34*$J$47 -> 0 | K18: ='DETALLE GASTOS FIJOS Y VARIABLE'!$J$34*$K$47 -> 0 | L18: ='DETALLE GASTOS FIJOS Y VARIABLE'!$K$34*$L$47 -> 0 | M18: ='DETALLE GASTOS FIJOS Y VARIABLE'!$L$34*$M$47 -> 0 | N18: ='DETALLE GASTOS FIJOS Y VARIABLE'!$M$34*$N$47 -> 0 | O18: ='DETALLE GASTOS FIJOS Y VARIABLE'!$N$34*$O$47 -> 0 | P18: ='DETALLE GASTOS FIJOS Y VARIABLE'!$O$34*$P$47 -> 0 | Q18: ='DETALLE GASTOS FIJOS Y VARIABLE'!$P$34*$Q$47 -> 0 | R18: ='DETALLE GASTOS FIJOS Y VARIABLE'!$Q$34*$R$47 -> 0 | S18: ='DETALLE GASTOS FIJOS Y VARIABLE'!$R$34*$S$47 -> 0 | T18: ='DETALLE GASTOS FIJOS Y VARIABLE'!$S$34*$T$47 -> 0
E19: Gastos Operativos Fijos | F19: Moneda | G19: =+'DETALLE GASTOS FIJOS Y VARIABLE'!$F$38*$G$47 -> 0 | H19: =+'DETALLE GASTOS FIJOS Y VARIABLE'!$G$38*$H$47 -> 0 | I19: =+'DETALLE GASTOS FIJOS Y VARIABLE'!$H$38*$I$47 -> 0 | J19: =+'DETALLE GASTOS FIJOS Y VARIABLE'!$I$38*$J$47 -> 0 | K19: =+'DETALLE GASTOS FIJOS Y VARIABLE'!$J$38*$K$47 -> 0 | L19: =+'DETALLE GASTOS FIJOS Y VARIABLE'!$K$38*$L$47 -> 0 | M19: =+'DETALLE GASTOS FIJOS Y VARIABLE'!$L$38*$M$47 -> 0 | N19: =+'DETALLE GASTOS FIJOS Y VARIABLE'!$M$38*$N$47 -> 0 | O19: =+'DETALLE GASTOS FIJOS Y VARIABLE'!$N$38*$O$47 -> 0 | P19: =+'DETALLE GASTOS FIJOS Y VARIABLE'!$O$38*$P$47 -> 0 | Q19: =+'DETALLE GASTOS FIJOS Y VARIABLE'!$P$38*$Q$47 -> 0 | R19: =+'DETALLE GASTOS FIJOS Y VARIABLE'!$Q$38*$R$47 -> 0 | S19: =+'DETALLE GASTOS FIJOS Y VARIABLE'!$R$38*$S$47 -> 0 | T19: =+'DETALLE GASTOS FIJOS Y VARIABLE'!$S$38*$T$47 -> 0
D21: GASTOS INCURRIDOS PARA LOS SERVICIOS DE TRANSPORTE Y DISPOSICIÓN | E21: Transporte de Carga - Servicios | F21: Moneda | G21: =SUMIFS(Anexo_4[base_imponible_18],Anexo_4[gastos_operativos_kpi],$E$21,Anexo_4[periodo],$G$7)+SUMIFS(Anexo_4[base_imponible_10],Anexo_4[gastos_operativos_kpi],$E$21,Anexo_4[periodo],$G$7)+SUMIFS(Anexo_4[base_no_grabada],Anexo_4[gastos_operativos_kpi],$E$21,Anexo_4[periodo],$G$7) -> 0 | H21: =SUMIFS(Anexo_4[base_imponible_18],Anexo_4[gastos_operativos_kpi],$E$21,Anexo_4[periodo],$H$7)+SUMIFS(Anexo_4[base_imponible_10],Anexo_4[gastos_operativos_kpi],$E$21,Anexo_4[periodo],$H$7)+SUMIFS(Anexo_4[base_no_grabada],Anexo_4[gastos_operativos_kpi],$E$21,Anexo_4[periodo],$H$7) -> 0 | I21: =SUMIFS(Anexo_4[base_imponible_18],Anexo_4[gastos_operativos_kpi],$E$21,Anexo_4[periodo],$I$7)+SUMIFS(Anexo_4[base_imponible_10],Anexo_4[gastos_operativos_kpi],$E$21,Anexo_4[periodo],$I$7)+SUMIFS(Anexo_4[base_no_grabada],Anexo_4[gastos_operativos_kpi],$E$21,Anexo_4[periodo],$I$7) -> 0 | J21: =SUMIFS(Anexo_4[base_imponible_18],Anexo_4[gastos_operativos_kpi],$E$21,Anexo_4[periodo],$J$7)+SUMIFS(Anexo_4[base_imponible_10],Anexo_4[gastos_operativos_kpi],$E$21,Anexo_4[periodo],$J$7)+SUMIFS(Anexo_4[base_no_grabada],Anexo_4[gastos_operativos_kpi],$E$21,Anexo_4[periodo],$J$7) -> 0 | K21: =SUMIFS(Anexo_4[base_imponible_18],Anexo_4[gastos_operativos_kpi],$E$21,Anexo_4[periodo],$K$7)+SUMIFS(Anexo_4[base_imponible_10],Anexo_4[gastos_operativos_kpi],$E$21,Anexo_4[periodo],$K$7)+SUMIFS(Anexo_4[base_no_grabada],Anexo_4[gastos_operativos_kpi],$E$21,Anexo_4[periodo],$K$7) -> 0 | L21: =SUMIFS(Anexo_4[base_imponible_18],Anexo_4[gastos_operativos_kpi],$E$21,Anexo_4[periodo],$L$7)+SUMIFS(Anexo_4[base_imponible_10],Anexo_4[gastos_operativos_kpi],$E$21,Anexo_4[periodo],$L$7)+SUMIFS(Anexo_4[base_no_grabada],Anexo_4[gastos_operativos_kpi],$E$21,Anexo_4[periodo],$L$7) -> 3391.53 | M21: =SUMIFS(Anexo_4[base_imponible_18],Anexo_4[gastos_operativos_kpi],$E$21,Anexo_4[periodo],$M$7)+SUMIFS(Anexo_4[base_imponible_10],Anexo_4[gastos_operativos_kpi],$E$21,Anexo_4[periodo],$M$7)+SUMIFS(Anexo_4[base_no_grabada],Anexo_4[gastos_operativos_kpi],$E$21,Anexo_4[periodo],$M$7) -> 2263.57 | N21: =SUMIFS(Anexo_4[base_imponible_18],Anexo_4[gastos_operativos_kpi],$E$21,Anexo_4[periodo],$N$7)+SUMIFS(Anexo_4[base_imponible_10],Anexo_4[gastos_operativos_kpi],$E$21,Anexo_4[periodo],$N$7)+SUMIFS(Anexo_4[base_no_grabada],Anexo_4[gastos_operativos_kpi],$E$21,Anexo_4[periodo],$N$7) -> 7670.34 | O21: =SUMIFS(Anexo_4[base_imponible_18],Anexo_4[gastos_operativos_kpi],$E$21,Anexo_4[periodo],$O$7)+SUMIFS(Anexo_4[base_imponible_10],Anexo_4[gastos_operativos_kpi],$E$21,Anexo_4[periodo],$O$7)+SUMIFS(Anexo_4[base_no_grabada],Anexo_4[gastos_operativos_kpi],$E$21,Anexo_4[periodo],$O$7) -> 4466.1 | P21: =SUMIFS(Anexo_4[base_imponible_18],Anexo_4[gastos_operativos_kpi],$E$21,Anexo_4[periodo],$P$7)+SUMIFS(Anexo_4[base_imponible_10],Anexo_4[gastos_operativos_kpi],$E$21,Anexo_4[periodo],$P$7)+SUMIFS(Anexo_4[base_no_grabada],Anexo_4[gastos_operativos_kpi],$E$21,Anexo_4[periodo],$P$7) -> 0 | Q21: =SUMIFS(Anexo_4[base_imponible_18],Anexo_4[gastos_operativos_kpi],$E$21,Anexo_4[periodo],$Q$7)+SUMIFS(Anexo_4[base_imponible_10],Anexo_4[gastos_operativos_kpi],$E$21,Anexo_4[periodo],$Q$7)+SUMIFS(Anexo_4[base_no_grabada],Anexo_4[gastos_operativos_kpi],$E$21,Anexo_4[periodo],$Q$7) -> 0 | R21: =SUMIFS(Anexo_4[base_imponible_18],Anexo_4[gastos_operativos_kpi],$E$21,Anexo_4[periodo],$R$7)+SUMIFS(Anexo_4[base_imponible_10],Anexo_4[gastos_operativos_kpi],$E$21,Anexo_4[periodo],$R$7)+SUMIFS(Anexo_4[base_no_grabada],Anexo_4[gastos_operativos_kpi],$E$21,Anexo_4[periodo],$R$7) -> 0 | S21: =SUM(G21:R21) -> 17791.54 | T21: =AVERAGE(G21:R21) -> 1482.6283
E22: Transporte peajes - Servicios | F22: Moneda | G22: =SUMIFS(Anexo_4[base_imponible_18],Anexo_4[gastos_operativos_kpi],$E$22,Anexo_4[periodo],$G$7)+SUMIFS(Anexo_4[base_imponible_10],Anexo_4[gastos_operativos_kpi],$E$22,Anexo_4[periodo],$G$7)+SUMIFS(Anexo_4[base_no_grabada],Anexo_4[gastos_operativos_kpi],$E$22,Anexo_4[periodo],$G$7) -> 0 | H22: =SUMIFS(Anexo_4[base_imponible_18],Anexo_4[gastos_operativos_kpi],$E$22,Anexo_4[periodo],$H$7)+SUMIFS(Anexo_4[base_imponible_10],Anexo_4[gastos_operativos_kpi],$E$22,Anexo_4[periodo],$H$7)+SUMIFS(Anexo_4[base_no_grabada],Anexo_4[gastos_operativos_kpi],$E$22,Anexo_4[periodo],$H$7) -> 0 | I22: =SUMIFS(Anexo_4[base_imponible_18],Anexo_4[gastos_operativos_kpi],$E$22,Anexo_4[periodo],$I$7)+SUMIFS(Anexo_4[base_imponible_10],Anexo_4[gastos_operativos_kpi],$E$22,Anexo_4[periodo],$I$7)+SUMIFS(Anexo_4[base_no_grabada],Anexo_4[gastos_operativos_kpi],$E$22,Anexo_4[periodo],$I$7) -> 0 | J22: =SUMIFS(Anexo_4[base_imponible_18],Anexo_4[gastos_operativos_kpi],$E$22,Anexo_4[periodo],$J$7)+SUMIFS(Anexo_4[base_imponible_10],Anexo_4[gastos_operativos_kpi],$E$22,Anexo_4[periodo],$J$7)+SUMIFS(Anexo_4[base_no_grabada],Anexo_4[gastos_operativos_kpi],$E$22,Anexo_4[periodo],$J$7) -> 0 | K22: =SUMIFS(Anexo_4[base_imponible_18],Anexo_4[gastos_operativos_kpi],$E$22,Anexo_4[periodo],$K$7)+SUMIFS(Anexo_4[base_imponible_10],Anexo_4[gastos_operativos_kpi],$E$22,Anexo_4[periodo],$K$7)+SUMIFS(Anexo_4[base_no_grabada],Anexo_4[gastos_operativos_kpi],$E$22,Anexo_4[periodo],$K$7) -> 0 | L22: =SUMIFS(Anexo_4[base_imponible_18],Anexo_4[gastos_operativos_kpi],$E$22,Anexo_4[periodo],$L$7)+SUMIFS(Anexo_4[base_imponible_10],Anexo_4[gastos_operativos_kpi],$E$22,Anexo_4[periodo],$L$7)+SUMIFS(Anexo_4[base_no_grabada],Anexo_4[gastos_operativos_kpi],$E$22,Anexo_4[periodo],$L$7) -> 1139.52 | M22: =SUMIFS(Anexo_4[base_imponible_18],Anexo_4[gastos_operativos_kpi],$E$22,Anexo_4[periodo],$M$7)+SUMIFS(Anexo_4[base_imponible_10],Anexo_4[gastos_operativos_kpi],$E$22,Anexo_4[periodo],$M$7)+SUMIFS(Anexo_4[base_no_grabada],Anexo_4[gastos_operativos_kpi],$E$22,Anexo_4[periodo],$M$7) -> 862.59 | N22: =SUMIFS(Anexo_4[base_imponible_18],Anexo_4[gastos_operativos_kpi],$E$22,Anexo_4[periodo],$N$7)+SUMIFS(Anexo_4[base_imponible_10],Anexo_4[gastos_operativos_kpi],$E$22,Anexo_4[periodo],$N$7)+SUMIFS(Anexo_4[base_no_grabada],Anexo_4[gastos_operativos_kpi],$E$22,Anexo_4[periodo],$N$7) -> 956.33 | O22: =SUMIFS(Anexo_4[base_imponible_18],Anexo_4[gastos_operativos_kpi],$E$22,Anexo_4[periodo],$O$7)+SUMIFS(Anexo_4[base_imponible_10],Anexo_4[gastos_operativos_kpi],$E$22,Anexo_4[periodo],$O$7)+SUMIFS(Anexo_4[base_no_grabada],Anexo_4[gastos_operativos_kpi],$E$22,Anexo_4[periodo],$O$7) -> 1379.95 | P22: =SUMIFS(Anexo_4[base_imponible_18],Anexo_4[gastos_operativos_kpi],$E$22,Anexo_4[periodo],$P$7)+SUMIFS(Anexo_4[base_imponible_10],Anexo_4[gastos_operativos_kpi],$E$22,Anexo_4[periodo],$P$7)+SUMIFS(Anexo_4[base_no_grabada],Anexo_4[gastos_operativos_kpi],$E$22,Anexo_4[periodo],$P$7) -> 0 | Q22: =SUMIFS(Anexo_4[base_imponible_18],Anexo_4[gastos_operativos_kpi],$E$22,Anexo_4[periodo],$Q$7)+SUMIFS(Anexo_4[base_imponible_10],Anexo_4[gastos_operativos_kpi],$E$22,Anexo_4[periodo],$Q$7)+SUMIFS(Anexo_4[base_no_grabada],Anexo_4[gastos_operativos_kpi],$E$22,Anexo_4[periodo],$Q$7) -> 0 | R22: =SUMIFS(Anexo_4[base_imponible_18],Anexo_4[gastos_operativos_kpi],$E$22,Anexo_4[periodo],$R$7)+SUMIFS(Anexo_4[base_imponible_10],Anexo_4[gastos_operativos_kpi],$E$22,Anexo_4[periodo],$R$7)+SUMIFS(Anexo_4[base_no_grabada],Anexo_4[gastos_operativos_kpi],$E$22,Anexo_4[periodo],$R$7) -> 0 | S22: =SUM(G22:R22) -> 4338.39 | T22: =AVERAGE(G22:R22) -> 361.5325
E23: Balanza - Servicios | F23: Moneda | G23: =SUMIFS(Anexo_4[base_imponible_18],Anexo_4[gastos_operativos_kpi],$E$23,Anexo_4[periodo],$G$7)+SUMIFS(Anexo_4[base_imponible_10],Anexo_4[gastos_operativos_kpi],$E$23,Anexo_4[periodo],$G$7)+SUMIFS(Anexo_4[base_no_grabada],Anexo_4[gastos_operativos_kpi],$E$23,Anexo_4[periodo],$G$7) -> 0 | H23: =SUMIFS(Anexo_4[base_imponible_18],Anexo_4[gastos_operativos_kpi],$E$23,Anexo_4[periodo],$H$7)+SUMIFS(Anexo_4[base_imponible_10],Anexo_4[gastos_operativos_kpi],$E$23,Anexo_4[periodo],$H$7)+SUMIFS(Anexo_4[base_no_grabada],Anexo_4[gastos_operativos_kpi],$E$23,Anexo_4[periodo],$H$7) -> 0 | I23: =SUMIFS(Anexo_4[base_imponible_18],Anexo_4[gastos_operativos_kpi],$E$23,Anexo_4[periodo],$I$7)+SUMIFS(Anexo_4[base_imponible_10],Anexo_4[gastos_operativos_kpi],$E$23,Anexo_4[periodo],$I$7)+SUMIFS(Anexo_4[base_no_grabada],Anexo_4[gastos_operativos_kpi],$E$23,Anexo_4[periodo],$I$7) -> 0 | J23: =SUMIFS(Anexo_4[base_imponible_18],Anexo_4[gastos_operativos_kpi],$E$23,Anexo_4[periodo],$J$7)+SUMIFS(Anexo_4[base_imponible_10],Anexo_4[gastos_operativos_kpi],$E$23,Anexo_4[periodo],$J$7)+SUMIFS(Anexo_4[base_no_grabada],Anexo_4[gastos_operativos_kpi],$E$23,Anexo_4[periodo],$J$7) -> 0 | K23: =SUMIFS(Anexo_4[base_imponible_18],Anexo_4[gastos_operativos_kpi],$E$23,Anexo_4[periodo],$K$7)+SUMIFS(Anexo_4[base_imponible_10],Anexo_4[gastos_operativos_kpi],$E$23,Anexo_4[periodo],$K$7)+SUMIFS(Anexo_4[base_no_grabada],Anexo_4[gastos_operativos_kpi],$E$23,Anexo_4[periodo],$K$7) -> 0 | L23: =SUMIFS(Anexo_4[base_imponible_18],Anexo_4[gastos_operativos_kpi],$E$23,Anexo_4[periodo],$L$7)+SUMIFS(Anexo_4[base_imponible_10],Anexo_4[gastos_operativos_kpi],$E$23,Anexo_4[periodo],$L$7)+SUMIFS(Anexo_4[base_no_grabada],Anexo_4[gastos_operativos_kpi],$E$23,Anexo_4[periodo],$L$7) -> 493.96 | M23: =SUMIFS(Anexo_4[base_imponible_18],Anexo_4[gastos_operativos_kpi],$E$23,Anexo_4[periodo],$M$7)+SUMIFS(Anexo_4[base_imponible_10],Anexo_4[gastos_operativos_kpi],$E$23,Anexo_4[periodo],$M$7)+SUMIFS(Anexo_4[base_no_grabada],Anexo_4[gastos_operativos_kpi],$E$23,Anexo_4[periodo],$M$7) -> 392.88 | N23: =SUMIFS(Anexo_4[base_imponible_18],Anexo_4[gastos_operativos_kpi],$E$23,Anexo_4[periodo],$N$7)+SUMIFS(Anexo_4[base_imponible_10],Anexo_4[gastos_operativos_kpi],$E$23,Anexo_4[periodo],$N$7)+SUMIFS(Anexo_4[base_no_grabada],Anexo_4[gastos_operativos_kpi],$E$23,Anexo_4[periodo],$N$7) -> 544.48 | O23: =SUMIFS(Anexo_4[base_imponible_18],Anexo_4[gastos_operativos_kpi],$E$23,Anexo_4[periodo],$O$7)+SUMIFS(Anexo_4[base_imponible_10],Anexo_4[gastos_operativos_kpi],$E$23,Anexo_4[periodo],$O$7)+SUMIFS(Anexo_4[base_no_grabada],Anexo_4[gastos_operativos_kpi],$E$23,Anexo_4[periodo],$O$7) -> 698.84 | P23: =SUMIFS(Anexo_4[base_imponible_18],Anexo_4[gastos_operativos_kpi],$E$23,Anexo_4[periodo],$P$7)+SUMIFS(Anexo_4[base_imponible_10],Anexo_4[gastos_operativos_kpi],$E$23,Anexo_4[periodo],$P$7)+SUMIFS(Anexo_4[base_no_grabada],Anexo_4[gastos_operativos_kpi],$E$23,Anexo_4[periodo],$P$7) -> 0 | Q23: =SUMIFS(Anexo_4[base_imponible_18],Anexo_4[gastos_operativos_kpi],$E$23,Anexo_4[periodo],$Q$7)+SUMIFS(Anexo_4[base_imponible_10],Anexo_4[gastos_operativos_kpi],$E$23,Anexo_4[periodo],$Q$7)+SUMIFS(Anexo_4[base_no_grabada],Anexo_4[gastos_operativos_kpi],$E$23,Anexo_4[periodo],$Q$7) -> 0 | R23: =SUMIFS(Anexo_4[base_imponible_18],Anexo_4[gastos_operativos_kpi],$E$23,Anexo_4[periodo],$R$7)+SUMIFS(Anexo_4[base_imponible_10],Anexo_4[gastos_operativos_kpi],$E$23,Anexo_4[periodo],$R$7)+SUMIFS(Anexo_4[base_no_grabada],Anexo_4[gastos_operativos_kpi],$E$23,Anexo_4[periodo],$R$7) -> 0 | S23: =SUM(G23:R23) -> 2130.16 | T23: =AVERAGE(G23:R23) -> 177.51333
E24: Montacarga - Servicios | F24: Moneda | G24: =SUMIFS(Anexo_4[base_imponible_18],Anexo_4[gastos_operativos_kpi],$E$24,Anexo_4[periodo],$G$7)+SUMIFS(Anexo_4[base_imponible_10],Anexo_4[gastos_operativos_kpi],$E$24,Anexo_4[periodo],$G$7)+SUMIFS(Anexo_4[base_no_grabada],Anexo_4[gastos_operativos_kpi],$E$24,Anexo_4[periodo],$G$7) -> 0 | H24: =SUMIFS(Anexo_4[base_imponible_18],Anexo_4[gastos_operativos_kpi],$E$24,Anexo_4[periodo],$H$7)+SUMIFS(Anexo_4[base_imponible_10],Anexo_4[gastos_operativos_kpi],$E$24,Anexo_4[periodo],$H$7)+SUMIFS(Anexo_4[base_no_grabada],Anexo_4[gastos_operativos_kpi],$E$24,Anexo_4[periodo],$H$7) -> 0 | I24: =SUMIFS(Anexo_4[base_imponible_18],Anexo_4[gastos_operativos_kpi],$E$24,Anexo_4[periodo],$I$7)+SUMIFS(Anexo_4[base_imponible_10],Anexo_4[gastos_operativos_kpi],$E$24,Anexo_4[periodo],$I$7)+SUMIFS(Anexo_4[base_no_grabada],Anexo_4[gastos_operativos_kpi],$E$24,Anexo_4[periodo],$I$7) -> 0 | J24: =SUMIFS(Anexo_4[base_imponible_18],Anexo_4[gastos_operativos_kpi],$E$24,Anexo_4[periodo],$J$7)+SUMIFS(Anexo_4[base_imponible_10],Anexo_4[gastos_operativos_kpi],$E$24,Anexo_4[periodo],$J$7)+SUMIFS(Anexo_4[base_no_grabada],Anexo_4[gastos_operativos_kpi],$E$24,Anexo_4[periodo],$J$7) -> 0 | K24: =SUMIFS(Anexo_4[base_imponible_18],Anexo_4[gastos_operativos_kpi],$E$24,Anexo_4[periodo],$K$7)+SUMIFS(Anexo_4[base_imponible_10],Anexo_4[gastos_operativos_kpi],$E$24,Anexo_4[periodo],$K$7)+SUMIFS(Anexo_4[base_no_grabada],Anexo_4[gastos_operativos_kpi],$E$24,Anexo_4[periodo],$K$7) -> 0 | L24: =SUMIFS(Anexo_4[base_imponible_18],Anexo_4[gastos_operativos_kpi],$E$24,Anexo_4[periodo],$L$7)+SUMIFS(Anexo_4[base_imponible_10],Anexo_4[gastos_operativos_kpi],$E$24,Anexo_4[periodo],$L$7)+SUMIFS(Anexo_4[base_no_grabada],Anexo_4[gastos_operativos_kpi],$E$24,Anexo_4[periodo],$L$7) -> 970 | M24: =SUMIFS(Anexo_4[base_imponible_18],Anexo_4[gastos_operativos_kpi],$E$24,Anexo_4[periodo],$M$7)+SUMIFS(Anexo_4[base_imponible_10],Anexo_4[gastos_operativos_kpi],$E$24,Anexo_4[periodo],$M$7)+SUMIFS(Anexo_4[base_no_grabada],Anexo_4[gastos_operativos_kpi],$E$24,Anexo_4[periodo],$M$7) -> 3589.25 | N24: =SUMIFS(Anexo_4[base_imponible_18],Anexo_4[gastos_operativos_kpi],$E$24,Anexo_4[periodo],$N$7)+SUMIFS(Anexo_4[base_imponible_10],Anexo_4[gastos_operativos_kpi],$E$24,Anexo_4[periodo],$N$7)+SUMIFS(Anexo_4[base_no_grabada],Anexo_4[gastos_operativos_kpi],$E$24,Anexo_4[periodo],$N$7) -> 4618.75 | O24: =SUMIFS(Anexo_4[base_imponible_18],Anexo_4[gastos_operativos_kpi],$E$24,Anexo_4[periodo],$O$7)+SUMIFS(Anexo_4[base_imponible_10],Anexo_4[gastos_operativos_kpi],$E$24,Anexo_4[periodo],$O$7)+SUMIFS(Anexo_4[base_no_grabada],Anexo_4[gastos_operativos_kpi],$E$24,Anexo_4[periodo],$O$7) -> 895 | P24: =SUMIFS(Anexo_4[base_imponible_18],Anexo_4[gastos_operativos_kpi],$E$24,Anexo_4[periodo],$P$7)+SUMIFS(Anexo_4[base_imponible_10],Anexo_4[gastos_operativos_kpi],$E$24,Anexo_4[periodo],$P$7)+SUMIFS(Anexo_4[base_no_grabada],Anexo_4[gastos_operativos_kpi],$E$24,Anexo_4[periodo],$P$7) -> 0 | Q24: =SUMIFS(Anexo_4[base_imponible_18],Anexo_4[gastos_operativos_kpi],$E$24,Anexo_4[periodo],$Q$7)+SUMIFS(Anexo_4[base_imponible_10],Anexo_4[gastos_operativos_kpi],$E$24,Anexo_4[periodo],$Q$7)+SUMIFS(Anexo_4[base_no_grabada],Anexo_4[gastos_operativos_kpi],$E$24,Anexo_4[periodo],$Q$7) -> 0 | R24: =SUMIFS(Anexo_4[base_imponible_18],Anexo_4[gastos_operativos_kpi],$E$24,Anexo_4[periodo],$R$7)+SUMIFS(Anexo_4[base_imponible_10],Anexo_4[gastos_operativos_kpi],$E$24,Anexo_4[periodo],$R$7)+SUMIFS(Anexo_4[base_no_grabada],Anexo_4[gastos_operativos_kpi],$E$24,Anexo_4[periodo],$R$7) -> 0 | S24: =SUM(G24:R24) -> 10073 | T24: =AVERAGE(G24:R24) -> 839.41667
E25: Maquinaria Pesada - Servicios | F25: Moneda | G25: =SUMIFS(Anexo_4[base_imponible_18],Anexo_4[gastos_operativos_kpi],$E$25,Anexo_4[periodo],$G$7)+SUMIFS(Anexo_4[base_imponible_10],Anexo_4[gastos_operativos_kpi],$E$25,Anexo_4[periodo],$G$7)+SUMIFS(Anexo_4[base_no_grabada],Anexo_4[gastos_operativos_kpi],$E$25,Anexo_4[periodo],$G$7) -> 0 | H25: =SUMIFS(Anexo_4[base_imponible_18],Anexo_4[gastos_operativos_kpi],$E$25,Anexo_4[periodo],$H$7)+SUMIFS(Anexo_4[base_imponible_10],Anexo_4[gastos_operativos_kpi],$E$25,Anexo_4[periodo],$H$7)+SUMIFS(Anexo_4[base_no_grabada],Anexo_4[gastos_operativos_kpi],$E$25,Anexo_4[periodo],$H$7) -> 0 | I25: =SUMIFS(Anexo_4[base_imponible_18],Anexo_4[gastos_operativos_kpi],$E$25,Anexo_4[periodo],$I$7)+SUMIFS(Anexo_4[base_imponible_10],Anexo_4[gastos_operativos_kpi],$E$25,Anexo_4[periodo],$I$7)+SUMIFS(Anexo_4[base_no_grabada],Anexo_4[gastos_operativos_kpi],$E$25,Anexo_4[periodo],$I$7) -> 0 | J25: =SUMIFS(Anexo_4[base_imponible_18],Anexo_4[gastos_operativos_kpi],$E$25,Anexo_4[periodo],$J$7)+SUMIFS(Anexo_4[base_imponible_10],Anexo_4[gastos_operativos_kpi],$E$25,Anexo_4[periodo],$J$7)+SUMIFS(Anexo_4[base_no_grabada],Anexo_4[gastos_operativos_kpi],$E$25,Anexo_4[periodo],$J$7) -> 0 | K25: =SUMIFS(Anexo_4[base_imponible_18],Anexo_4[gastos_operativos_kpi],$E$25,Anexo_4[periodo],$K$7)+SUMIFS(Anexo_4[base_imponible_10],Anexo_4[gastos_operativos_kpi],$E$25,Anexo_4[periodo],$K$7)+SUMIFS(Anexo_4[base_no_grabada],Anexo_4[gastos_operativos_kpi],$E$25,Anexo_4[periodo],$K$7) -> 0 | L25: =SUMIFS(Anexo_4[base_imponible_18],Anexo_4[gastos_operativos_kpi],$E$25,Anexo_4[periodo],$L$7)+SUMIFS(Anexo_4[base_imponible_10],Anexo_4[gastos_operativos_kpi],$E$25,Anexo_4[periodo],$L$7)+SUMIFS(Anexo_4[base_no_grabada],Anexo_4[gastos_operativos_kpi],$E$25,Anexo_4[periodo],$L$7) -> 0 | M25: =SUMIFS(Anexo_4[base_imponible_18],Anexo_4[gastos_operativos_kpi],$E$25,Anexo_4[periodo],$M$7)+SUMIFS(Anexo_4[base_imponible_10],Anexo_4[gastos_operativos_kpi],$E$25,Anexo_4[periodo],$M$7)+SUMIFS(Anexo_4[base_no_grabada],Anexo_4[gastos_operativos_kpi],$E$25,Anexo_4[periodo],$M$7) -> 0 | N25: =SUMIFS(Anexo_4[base_imponible_18],Anexo_4[gastos_operativos_kpi],$E$25,Anexo_4[periodo],$N$7)+SUMIFS(Anexo_4[base_imponible_10],Anexo_4[gastos_operativos_kpi],$E$25,Anexo_4[periodo],$N$7)+SUMIFS(Anexo_4[base_no_grabada],Anexo_4[gastos_operativos_kpi],$E$25,Anexo_4[periodo],$N$7) -> 0 | O25: =SUMIFS(Anexo_4[base_imponible_18],Anexo_4[gastos_operativos_kpi],$E$25,Anexo_4[periodo],$O$7)+SUMIFS(Anexo_4[base_imponible_10],Anexo_4[gastos_operativos_kpi],$E$25,Anexo_4[periodo],$O$7)+SUMIFS(Anexo_4[base_no_grabada],Anexo_4[gastos_operativos_kpi],$E$25,Anexo_4[periodo],$O$7) -> 0 | P25: =SUMIFS(Anexo_4[base_imponible_18],Anexo_4[gastos_operativos_kpi],$E$25,Anexo_4[periodo],$P$7)+SUMIFS(Anexo_4[base_imponible_10],Anexo_4[gastos_operativos_kpi],$E$25,Anexo_4[periodo],$P$7)+SUMIFS(Anexo_4[base_no_grabada],Anexo_4[gastos_operativos_kpi],$E$25,Anexo_4[periodo],$P$7) -> 0 | Q25: =SUMIFS(Anexo_4[base_imponible_18],Anexo_4[gastos_operativos_kpi],$E$25,Anexo_4[periodo],$Q$7)+SUMIFS(Anexo_4[base_imponible_10],Anexo_4[gastos_operativos_kpi],$E$25,Anexo_4[periodo],$Q$7)+SUMIFS(Anexo_4[base_no_grabada],Anexo_4[gastos_operativos_kpi],$E$25,Anexo_4[periodo],$Q$7) -> 0 | R25: =SUMIFS(Anexo_4[base_imponible_18],Anexo_4[gastos_operativos_kpi],$E$25,Anexo_4[periodo],$R$7)+SUMIFS(Anexo_4[base_imponible_10],Anexo_4[gastos_operativos_kpi],$E$25,Anexo_4[periodo],$R$7)+SUMIFS(Anexo_4[base_no_grabada],Anexo_4[gastos_operativos_kpi],$E$25,Anexo_4[periodo],$R$7) -> 0 | S25: =SUM(G25:R25) -> 0 | T25: =AVERAGE(G25:R25) -> 0
E26: Gastos Variables | F26: Moneda | G26: ='DETALLE GASTOS FIJOS Y VARIABLE'!$F$34*$G$60 -> #REF! | H26: =+'DETALLE GASTOS FIJOS Y VARIABLE'!$G$34*$H$60 -> #REF! | I26: =+'DETALLE GASTOS FIJOS Y VARIABLE'!$H$34*$I$60 -> #REF! | J26: =+'DETALLE GASTOS FIJOS Y VARIABLE'!$I$34*$J$60 -> #REF! | K26: =+'DETALLE GASTOS FIJOS Y VARIABLE'!$J$34*$K$60 -> #REF! | L26: =+'DETALLE GASTOS FIJOS Y VARIABLE'!$K$34*$L$60 -> #REF! | M26: =+'DETALLE GASTOS FIJOS Y VARIABLE'!$L$34*$M$60 -> #REF! | N26: =+'DETALLE GASTOS FIJOS Y VARIABLE'!$M$34*$N$60 -> #REF! | O26: =+'DETALLE GASTOS FIJOS Y VARIABLE'!$N$34*$O$60 -> #REF! | P26: =+'DETALLE GASTOS FIJOS Y VARIABLE'!$O$34*$P$60 -> #REF! | Q26: =+'DETALLE GASTOS FIJOS Y VARIABLE'!$P$34*$Q$60 -> #REF! | R26: =+'DETALLE GASTOS FIJOS Y VARIABLE'!$Q$34*$R$60 -> #REF! | S26: =+'DETALLE GASTOS FIJOS Y VARIABLE'!$R$34*$S$60 -> #REF! | T26: =+'DETALLE GASTOS FIJOS Y VARIABLE'!$S$34*$T$60 -> #REF!
E27: Gastos Operativos Fijos | F27: Moneda | G27: =+'DETALLE GASTOS FIJOS Y VARIABLE'!$F$38*$G$60 -> #REF! | H27: =+'DETALLE GASTOS FIJOS Y VARIABLE'!$G$38*$H$60 -> #REF! | I27: =+'DETALLE GASTOS FIJOS Y VARIABLE'!$H$38*$I$60 -> #REF! | J27: =+'DETALLE GASTOS FIJOS Y VARIABLE'!$I$38*$J$60 -> #REF! | K27: =+'DETALLE GASTOS FIJOS Y VARIABLE'!$J$38*$K$60 -> #REF! | L27: =+'DETALLE GASTOS FIJOS Y VARIABLE'!$K$38*$L$60 -> #REF! | M27: =+'DETALLE GASTOS FIJOS Y VARIABLE'!$L$38*$M$60 -> #REF! | N27: =+'DETALLE GASTOS FIJOS Y VARIABLE'!$M$38*$N$60 -> #REF! | O27: =+'DETALLE GASTOS FIJOS Y VARIABLE'!$N$38*$O$60 -> #REF! | P27: =+'DETALLE GASTOS FIJOS Y VARIABLE'!$O$38*$P$60 -> #REF! | Q27: =+'DETALLE GASTOS FIJOS Y VARIABLE'!$P$38*$Q$60 -> #REF! | R27: =+'DETALLE GASTOS FIJOS Y VARIABLE'!$Q$38*$R$60 -> #REF! | S27: =+'DETALLE GASTOS FIJOS Y VARIABLE'!$R$38*$S$60 -> #REF! | T27: =+'DETALLE GASTOS FIJOS Y VARIABLE'!$S$38*$T$60 -> #REF!
B29: TOTAL | G29: =SUM(G8:G28) -> #REF! | H29: =SUM(H8:H28) -> #REF! | I29: =SUM(I8:I28) -> #REF! | J29: =SUM(J8:J28) -> #REF! | K29: =SUM(K8:K28) -> #REF! | L29: =SUM(L8:L28) -> #REF! | M29: =SUM(M8:M28) -> #REF! | N29: =SUM(N8:N28) -> #REF! | ... T29: =SUM(T8:T28) -> #REF!
E31: FORMATO ADMINISTRATIVO DE GESTION | S31: COD: S/N
E32: INDICADORES DE GESTION - VENTAS | S32: VERSIÓN:01
S33: AREÁ: Gerencia
E34: CONTABILIDAD | S34: =TODAY() -> 45979
B36: KPI | C36: CONCEPTO | E36: DETALLE | F36: MEDIDA | G36: ENERO | H36: FEBRERO | I36: MARZO | J36: ABRIL | K36: MAYO | L36: JUNIO | M36: JULIO | N36: AGOSTO | O36: SETIEMBRE | P36: OCTUBRE | Q36: NOVIEMBRE | R36: DICIEMBRE | S36: TOTAL | T36: PROMEDIO
B37: I.3.2 (Det. Anexo 5) | C37: RESIDUOS FACTURADOS | E37: E001 | F37: Moneda | G37: =SUMIFS(Anexo_5[base_imponible_18],Anexo_5[serie],$E$37,Anexo_5[periodo],$G$36)+SUMIFS(#REF!,Anexo_5[serie],$E$37,Anexo_5[periodo],$G$36)+SUMIFS(Anexo_5[base_no_grabada],Anexo_5[serie],$E$37,Anexo_5[periodo],$G$36) -> #REF! | H37: =SUMIFS(Anexo_5[base_imponible_18],Anexo_5[serie],$E$37,Anexo_5[periodo],$H$36)+SUMIFS(#REF!,Anexo_5[serie],$E$37,Anexo_5[periodo],$H$36)+SUMIFS(Anexo_5[base_no_grabada],Anexo_5[serie],$E$37,Anexo_5[periodo],$H$36) -> #REF! | I37: =SUMIFS(Anexo_5[base_imponible_18],Anexo_5[serie],$E$37,Anexo_5[periodo],$I$36)+SUMIFS(#REF!,Anexo_5[serie],$E$37,Anexo_5[periodo],$I$36)+SUMIFS(Anexo_5[base_no_grabada],Anexo_5[serie],$E$37,Anexo_5[periodo],$I$36) -> #REF! | J37: =SUMIFS(Anexo_5[base_imponible_18],Anexo_5[serie],$E$37,Anexo_5[periodo],$J$36)+SUMIFS(#REF!,Anexo_5[serie],$E$37,Anexo_5[periodo],$J$36)+SUMIFS(Anexo_5[base_no_grabada],Anexo_5[serie],$E$37,Anexo_5[periodo],$J$36) -> #REF! | K37: =SUMIFS(Anexo_5[base_imponible_18],Anexo_5[serie],$E$37,Anexo_5[periodo],$K$36)+SUMIFS(#REF!,Anexo_5[serie],$E$37,Anexo_5[periodo],$K$36)+SUMIFS(Anexo_5[base_no_grabada],Anexo_5[serie],$E$37,Anexo_5[periodo],$K$36) -> #REF! | L37: =SUMIFS(Anexo_5[base_imponible_18],Anexo_5[serie],$E$37,Anexo_5[periodo],$L$36)+SUMIFS(#REF!,Anexo_5[serie],$E$37,Anexo_5[periodo],$L$36)+SUMIFS(Anexo_5[base_no_grabada],Anexo_5[serie],$E$37,Anexo_5[periodo],$L$36) -> #REF! | M37: =SUMIFS(Anexo_5[base_imponible_18],Anexo_5[serie],$E$37,Anexo_5[periodo],$M$36)+SUMIFS(#REF!,Anexo_5[serie],$E$37,Anexo_5[periodo],$M$36)+SUMIFS(Anexo_5[base_no_grabada],Anexo_5[serie],$E$37,Anexo_5[periodo],$M$36) -> #REF! | N37: =SUMIFS(Anexo_5[base_imponible_18],Anexo_5[serie],$E$37,Anexo_5[periodo],$N$36)+SUMIFS(#REF!,Anexo_5[serie],$E$37,Anexo_5[periodo],$N$36)+SUMIFS(Anexo_5[base_no_grabada],Anexo_5[serie],$E$37,Anexo_5[periodo],$N$36) -> #REF! | O37: =SUMIFS(Anexo_5[base_imponible_18],Anexo_5[serie],$E$37,Anexo_5[periodo],$O$36)+SUMIFS(#REF!,Anexo_5[serie],$E$37,Anexo_5[periodo],$O$36)+SUMIFS(Anexo_5[base_no_grabada],Anexo_5[serie],$E$37,Anexo_5[periodo],$O$36) -> #REF! | P37: =SUMIFS(Anexo_5[base_imponible_18],Anexo_5[serie],$E$37,Anexo_5[periodo],$P$36)+SUMIFS(#REF!,Anexo_5[serie],$E$37,Anexo_5[periodo],$P$36)+SUMIFS(Anexo_5[base_no_grabada],Anexo_5[serie],$E$37,Anexo_5[periodo],$P$36) -> #REF! | Q37: =SUMIFS(Anexo_5[base_imponible_18],Anexo_5[serie],$E$37,Anexo_5[periodo],$Q$36)+SUMIFS(#REF!,Anexo_5[serie],$E$37,Anexo_5[periodo],$Q$36)+SUMIFS(Anexo_5[base_no_grabada],Anexo_5[serie],$E$37,Anexo_5[periodo],$Q$36) -> #REF! | R37: =SUMIFS(Anexo_5[base_imponible_18],Anexo_5[serie],$E$37,Anexo_5[periodo],$R$36)+SUMIFS(#REF!,Anexo_5[serie],$E$37,Anexo_5[periodo],$R$36)+SUMIFS(Anexo_5[base_no_grabada],Anexo_5[serie],$E$37,Anexo_5[periodo],$R$36) -> #REF! | S37: =SUM(G37:R37) -> #REF! | T37: =AVERAGE(G37:R37) -> #REF!
E38: FE02 | F38: Moneda | G38: =SUMIFS(Anexo_5[base_imponible_18],Anexo_5[serie],$E$38,Anexo_5[periodo],$G$36)+SUMIFS(#REF!,Anexo_5[serie],$E$38,Anexo_5[periodo],$G$36)+SUMIFS(Anexo_5[base_no_grabada],Anexo_5[serie],$E$38,Anexo_5[periodo],$G$36) -> #REF! | H38: =SUMIFS(Anexo_5[base_imponible_18],Anexo_5[serie],$E$38,Anexo_5[periodo],$H$36)+SUMIFS(#REF!,Anexo_5[serie],$E$38,Anexo_5[periodo],$H$36)+SUMIFS(Anexo_5[base_no_grabada],Anexo_5[serie],$E$38,Anexo_5[periodo],$H$36) -> #REF! | I38: =SUMIFS(Anexo_5[base_imponible_18],Anexo_5[serie],$E$38,Anexo_5[periodo],$I$36)+SUMIFS(#REF!,Anexo_5[serie],$E$38,Anexo_5[periodo],$I$36)+SUMIFS(Anexo_5[base_no_grabada],Anexo_5[serie],$E$38,Anexo_5[periodo],$I$36) -> #REF! | J38: =SUMIFS(Anexo_5[base_imponible_18],Anexo_5[serie],$E$38,Anexo_5[periodo],$J$36)+SUMIFS(#REF!,Anexo_5[serie],$E$38,Anexo_5[periodo],$J$36)+SUMIFS(Anexo_5[base_no_grabada],Anexo_5[serie],$E$38,Anexo_5[periodo],$J$36) -> #REF! | K38: =SUMIFS(Anexo_5[base_imponible_18],Anexo_5[serie],$E$38,Anexo_5[periodo],$K$36)+SUMIFS(#REF!,Anexo_5[serie],$E$38,Anexo_5[periodo],$K$36)+SUMIFS(Anexo_5[base_no_grabada],Anexo_5[serie],$E$38,Anexo_5[periodo],$K$36) -> #REF! | L38: =SUMIFS(Anexo_5[base_imponible_18],Anexo_5[serie],$E$38,Anexo_5[periodo],$L$36)+SUMIFS(#REF!,Anexo_5[serie],$E$38,Anexo_5[periodo],$L$36)+SUMIFS(Anexo_5[base_no_grabada],Anexo_5[serie],$E$38,Anexo_5[periodo],$L$36) -> #REF! | M38: =SUMIFS(Anexo_5[base_imponible_18],Anexo_5[serie],$E$38,Anexo_5[periodo],$M$36)+SUMIFS(#REF!,Anexo_5[serie],$E$38,Anexo_5[periodo],$M$36)+SUMIFS(Anexo_5[base_no_grabada],Anexo_5[serie],$E$38,Anexo_5[periodo],$M$36) -> #REF! | N38: =SUMIFS(Anexo_5[base_imponible_18],Anexo_5[serie],$E$38,Anexo_5[periodo],$N$36)+SUMIFS(#REF!,Anexo_5[serie],$E$38,Anexo_5[periodo],$N$36)+SUMIFS(Anexo_5[base_no_grabada],Anexo_5[serie],$E$38,Anexo_5[periodo],$N$36) -> #REF! | O38: =SUMIFS(Anexo_5[base_imponible_18],Anexo_5[serie],$E$38,Anexo_5[periodo],$O$36)+SUMIFS(#REF!,Anexo_5[serie],$E$38,Anexo_5[periodo],$O$36)+SUMIFS(Anexo_5[base_no_grabada],Anexo_5[serie],$E$38,Anexo_5[periodo],$O$36) -> #REF! | P38: =SUMIFS(Anexo_5[base_imponible_18],Anexo_5[serie],$E$38,Anexo_5[periodo],$P$36)+SUMIFS(#REF!,Anexo_5[serie],$E$38,Anexo_5[periodo],$P$36)+SUMIFS(Anexo_5[base_no_grabada],Anexo_5[serie],$E$38,Anexo_5[periodo],$P$36) -> #REF! | Q38: =SUMIFS(Anexo_5[base_imponible_18],Anexo_5[serie],$E$38,Anexo_5[periodo],$Q$36)+SUMIFS(#REF!,Anexo_5[serie],$E$38,Anexo_5[periodo],$Q$36)+SUMIFS(Anexo_5[base_no_grabada],Anexo_5[serie],$E$38,Anexo_5[periodo],$Q$36) -> #REF! | R38: =SUMIFS(Anexo_5[base_imponible_18],Anexo_5[serie],$E$38,Anexo_5[periodo],$R$36)+SUMIFS(#REF!,Anexo_5[serie],$E$38,Anexo_5[periodo],$R$36)+SUMIFS(Anexo_5[base_no_grabada],Anexo_5[serie],$E$38,Anexo_5[periodo],$R$36) -> #REF! | S38: =SUM(G38:R38) -> #REF! | T38: =AVERAGE(G38:R38) -> #REF!
E39: FE05 | F39: Moneda | G39: =SUMIFS(Anexo_5[base_imponible_18],Anexo_5[serie],$E$39,Anexo_5[periodo],$G$36)+SUMIFS(#REF!,Anexo_5[serie],$E$39,Anexo_5[periodo],$G$36)+SUMIFS(Anexo_5[base_no_grabada],Anexo_5[serie],$E$39,Anexo_5[periodo],$G$36) -> #REF! | H39: =SUMIFS(Anexo_5[base_imponible_18],Anexo_5[serie],$E$39,Anexo_5[periodo],$H$36)+SUMIFS(#REF!,Anexo_5[serie],$E$39,Anexo_5[periodo],$H$36)+SUMIFS(Anexo_5[base_no_grabada],Anexo_5[serie],$E$39,Anexo_5[periodo],$H$36) -> #REF! | I39: =SUMIFS(Anexo_5[base_imponible_18],Anexo_5[serie],$E$39,Anexo_5[periodo],$I$36)+SUMIFS(#REF!,Anexo_5[serie],$E$39,Anexo_5[periodo],$I$36)+SUMIFS(Anexo_5[base_no_grabada],Anexo_5[serie],$E$39,Anexo_5[periodo],$I$36) -> #REF! | J39: =SUMIFS(Anexo_5[base_imponible_18],Anexo_5[serie],$E$39,Anexo_5[periodo],$J$36)+SUMIFS(#REF!,Anexo_5[serie],$E$39,Anexo_5[periodo],$J$36)+SUMIFS(Anexo_5[base_no_grabada],Anexo_5[serie],$E$39,Anexo_5[periodo],$J$36) -> #REF! | K39: =SUMIFS(Anexo_5[base_imponible_18],Anexo_5[serie],$E$39,Anexo_5[periodo],$K$36)+SUMIFS(#REF!,Anexo_5[serie],$E$39,Anexo_5[periodo],$K$36)+SUMIFS(Anexo_5[base_no_grabada],Anexo_5[serie],$E$39,Anexo_5[periodo],$K$36) -> #REF! | L39: =SUMIFS(Anexo_5[base_imponible_18],Anexo_5[serie],$E$39,Anexo_5[periodo],$L$36)+SUMIFS(#REF!,Anexo_5[serie],$E$39,Anexo_5[periodo],$L$36)+SUMIFS(Anexo_5[base_no_grabada],Anexo_5[serie],$E$39,Anexo_5[periodo],$L$36) -> #REF! | M39: =SUMIFS(Anexo_5[base_imponible_18],Anexo_5[serie],$E$39,Anexo_5[periodo],$M$36)+SUMIFS(#REF!,Anexo_5[serie],$E$39,Anexo_5[periodo],$M$36)+SUMIFS(Anexo_5[base_no_grabada],Anexo_5[serie],$E$39,Anexo_5[periodo],$M$36) -> #REF! | N39: =SUMIFS(Anexo_5[base_imponible_18],Anexo_5[serie],$E$39,Anexo_5[periodo],$N$36)+SUMIFS(#REF!,Anexo_5[serie],$E$39,Anexo_5[periodo],$N$36)+SUMIFS(Anexo_5[base_no_grabada],Anexo_5[serie],$E$39,Anexo_5[periodo],$N$36) -> #REF! | O39: =SUMIFS(Anexo_5[base_imponible_18],Anexo_5[serie],$E$39,Anexo_5[periodo],$O$36)+SUMIFS(#REF!,Anexo_5[serie],$E$39,Anexo_5[periodo],$O$36)+SUMIFS(Anexo_5[base_no_grabada],Anexo_5[serie],$E$39,Anexo_5[periodo],$O$36) -> #REF! | P39: =SUMIFS(Anexo_5[base_imponible_18],Anexo_5[serie],$E$39,Anexo_5[periodo],$P$36)+SUMIFS(#REF!,Anexo_5[serie],$E$39,Anexo_5[periodo],$P$36)+SUMIFS(Anexo_5[base_no_grabada],Anexo_5[serie],$E$39,Anexo_5[periodo],$P$36) -> #REF! | Q39: =SUMIFS(Anexo_5[base_imponible_18],Anexo_5[serie],$E$39,Anexo_5[periodo],$Q$36)+SUMIFS(#REF!,Anexo_5[serie],$E$39,Anexo_5[periodo],$Q$36)+SUMIFS(Anexo_5[base_no_grabada],Anexo_5[serie],$E$39,Anexo_5[periodo],$Q$36) -> #REF! | R39: =SUMIFS(Anexo_5[base_imponible_18],Anexo_5[serie],$E$39,Anexo_5[periodo],$R$36)+SUMIFS(#REF!,Anexo_5[serie],$E$39,Anexo_5[periodo],$R$36)+SUMIFS(Anexo_5[base_no_grabada],Anexo_5[serie],$E$39,Anexo_5[periodo],$R$36) -> #REF! | S39: =SUM(G39:R39) -> #REF! | T39: =AVERAGE(G39:R39) -> #REF!
E40: FF02 | F40: Moneda | G40: =SUMIFS(Anexo_5[base_imponible_18],Anexo_5[serie],$E$40,Anexo_5[periodo],$G$36)+SUMIFS(#REF!,Anexo_5[serie],$E$40,Anexo_5[periodo],$G$36)+SUMIFS(Anexo_5[base_no_grabada],Anexo_5[serie],$E$40,Anexo_5[periodo],$G$36) -> #REF! | H40: =SUMIFS(Anexo_5[base_imponible_18],Anexo_5[serie],$E$40,Anexo_5[periodo],$H$36)+SUMIFS(#REF!,Anexo_5[serie],$E$40,Anexo_5[periodo],$H$36)+SUMIFS(Anexo_5[base_no_grabada],Anexo_5[serie],$E$40,Anexo_5[periodo],$H$36) -> #REF! | I40: =SUMIFS(Anexo_5[base_imponible_18],Anexo_5[serie],$E$40,Anexo_5[periodo],$I$36)+SUMIFS(#REF!,Anexo_5[serie],$E$40,Anexo_5[periodo],$I$36)+SUMIFS(Anexo_5[base_no_grabada],Anexo_5[serie],$E$40,Anexo_5[periodo],$I$36) -> #REF! | J40: =SUMIFS(Anexo_5[base_imponible_18],Anexo_5[serie],$E$40,Anexo_5[periodo],$J$36)+SUMIFS(#REF!,Anexo_5[serie],$E$40,Anexo_5[periodo],$J$36)+SUMIFS(Anexo_5[base_no_grabada],Anexo_5[serie],$E$40,Anexo_5[periodo],$J$36) -> #REF! | K40: =SUMIFS(Anexo_5[base_imponible_18],Anexo_5[serie],$E$40,Anexo_5[periodo],$K$36)+SUMIFS(#REF!,Anexo_5[serie],$E$40,Anexo_5[periodo],$K$36)+SUMIFS(Anexo_5[base_no_grabada],Anexo_5[serie],$E$40,Anexo_5[periodo],$K$36) -> #REF! | L40: =SUMIFS(Anexo_5[base_imponible_18],Anexo_5[serie],$E$40,Anexo_5[periodo],$L$36)+SUMIFS(#REF!,Anexo_5[serie],$E$40,Anexo_5[periodo],$L$36)+SUMIFS(Anexo_5[base_no_grabada],Anexo_5[serie],$E$40,Anexo_5[periodo],$L$36) -> #REF! | M40: =SUMIFS(Anexo_5[base_imponible_18],Anexo_5[serie],$E$40,Anexo_5[periodo],$M$36)+SUMIFS(#REF!,Anexo_5[serie],$E$40,Anexo_5[periodo],$M$36)+SUMIFS(Anexo_5[base_no_grabada],Anexo_5[serie],$E$40,Anexo_5[periodo],$M$36) -> #REF! | N40: =SUMIFS(Anexo_5[base_imponible_18],Anexo_5[serie],$E$40,Anexo_5[periodo],$N$36)+SUMIFS(#REF!,Anexo_5[serie],$E$40,Anexo_5[periodo],$N$36)+SUMIFS(Anexo_5[base_no_grabada],Anexo_5[serie],$E$40,Anexo_5[periodo],$N$36) -> #REF! | O40: =SUMIFS(Anexo_5[base_imponible_18],Anexo_5[serie],$E$40,Anexo_5[periodo],$O$36)+SUMIFS(#REF!,Anexo_5[serie],$E$40,Anexo_5[periodo],$O$36)+SUMIFS(Anexo_5[base_no_grabada],Anexo_5[serie],$E$40,Anexo_5[periodo],$O$36) -> #REF! | P40: =SUMIFS(Anexo_5[base_imponible_18],Anexo_5[serie],$E$40,Anexo_5[periodo],$P$36)+SUMIFS(#REF!,Anexo_5[serie],$E$40,Anexo_5[periodo],$P$36)+SUMIFS(Anexo_5[base_no_grabada],Anexo_5[serie],$E$40,Anexo_5[periodo],$P$36) -> #REF! | Q40: =SUMIFS(Anexo_5[base_imponible_18],Anexo_5[serie],$E$40,Anexo_5[periodo],$Q$36)+SUMIFS(#REF!,Anexo_5[serie],$E$40,Anexo_5[periodo],$Q$36)+SUMIFS(Anexo_5[base_no_grabada],Anexo_5[serie],$E$40,Anexo_5[periodo],$Q$36) -> #REF! | R40: =SUMIFS(Anexo_5[base_imponible_18],Anexo_5[serie],$E$40,Anexo_5[periodo],$R$36)+SUMIFS(#REF!,Anexo_5[serie],$E$40,Anexo_5[periodo],$R$36)+SUMIFS(Anexo_5[base_no_grabada],Anexo_5[serie],$E$40,Anexo_5[periodo],$R$36) -> #REF! | S40: =SUM(G40:R40) -> #REF! | T40: =AVERAGE(G40:R40) -> #REF!
E41: FF04 | F41: Moneda | G41: =SUMIFS(Anexo_5[base_imponible_18],Anexo_5[serie],$E$41,Anexo_5[periodo],$G$36)+SUMIFS(#REF!,Anexo_5[serie],$E$41,Anexo_5[periodo],$G$36)+SUMIFS(Anexo_5[base_no_grabada],Anexo_5[serie],$E$41,Anexo_5[periodo],$G$36) -> #REF! | H41: =SUMIFS(Anexo_5[base_imponible_18],Anexo_5[serie],$E$41,Anexo_5[periodo],$H$36)+SUMIFS(#REF!,Anexo_5[serie],$E$41,Anexo_5[periodo],$H$36)+SUMIFS(Anexo_5[base_no_grabada],Anexo_5[serie],$E$41,Anexo_5[periodo],$H$36) -> #REF! | I41: =SUMIFS(Anexo_5[base_imponible_18],Anexo_5[serie],$E$41,Anexo_5[periodo],$I$36)+SUMIFS(#REF!,Anexo_5[serie],$E$41,Anexo_5[periodo],$I$36)+SUMIFS(Anexo_5[base_no_grabada],Anexo_5[serie],$E$41,Anexo_5[periodo],$I$36) -> #REF! | J41: =SUMIFS(Anexo_5[base_imponible_18],Anexo_5[serie],$E$41,Anexo_5[periodo],$J$36)+SUMIFS(#REF!,Anexo_5[serie],$E$41,Anexo_5[periodo],$J$36)+SUMIFS(Anexo_5[base_no_grabada],Anexo_5[serie],$E$41,Anexo_5[periodo],$J$36) -> #REF! | K41: =SUMIFS(Anexo_5[base_imponible_18],Anexo_5[serie],$E$41,Anexo_5[periodo],$K$36)+SUMIFS(#REF!,Anexo_5[serie],$E$41,Anexo_5[periodo],$K$36)+SUMIFS(Anexo_5[base_no_grabada],Anexo_5[serie],$E$41,Anexo_5[periodo],$K$36) -> #REF! | L41: =SUMIFS(Anexo_5[base_imponible_18],Anexo_5[serie],$E$41,Anexo_5[periodo],$L$36)+SUMIFS(#REF!,Anexo_5[serie],$E$41,Anexo_5[periodo],$L$36)+SUMIFS(Anexo_5[base_no_grabada],Anexo_5[serie],$E$41,Anexo_5[periodo],$L$36) -> #REF! | M41: =SUMIFS(Anexo_5[base_imponible_18],Anexo_5[serie],$E$41,Anexo_5[periodo],$M$36)+SUMIFS(#REF!,Anexo_5[serie],$E$41,Anexo_5[periodo],$M$36)+SUMIFS(Anexo_5[base_no_grabada],Anexo_5[serie],$E$41,Anexo_5[periodo],$M$36) -> #REF! | N41: =SUMIFS(Anexo_5[base_imponible_18],Anexo_5[serie],$E$41,Anexo_5[periodo],$N$36)+SUMIFS(#REF!,Anexo_5[serie],$E$41,Anexo_5[periodo],$N$36)+SUMIFS(Anexo_5[base_no_grabada],Anexo_5[serie],$E$41,Anexo_5[periodo],$N$36) -> #REF! | O41: =SUMIFS(Anexo_5[base_imponible_18],Anexo_5[serie],$E$41,Anexo_5[periodo],$O$36)+SUMIFS(#REF!,Anexo_5[serie],$E$41,Anexo_5[periodo],$O$36)+SUMIFS(Anexo_5[base_no_grabada],Anexo_5[serie],$E$41,Anexo_5[periodo],$O$36) -> #REF! | P41: =SUMIFS(Anexo_5[base_imponible_18],Anexo_5[serie],$E$41,Anexo_5[periodo],$P$36)+SUMIFS(#REF!,Anexo_5[serie],$E$41,Anexo_5[periodo],$P$36)+SUMIFS(Anexo_5[base_no_grabada],Anexo_5[serie],$E$41,Anexo_5[periodo],$P$36) -> #REF! | Q41: =SUMIFS(Anexo_5[base_imponible_18],Anexo_5[serie],$E$41,Anexo_5[periodo],$Q$36)+SUMIFS(#REF!,Anexo_5[serie],$E$41,Anexo_5[periodo],$Q$36)+SUMIFS(Anexo_5[base_no_grabada],Anexo_5[serie],$E$41,Anexo_5[periodo],$Q$36) -> #REF! | R41: =SUMIFS(Anexo_5[base_imponible_18],Anexo_5[serie],$E$41,Anexo_5[periodo],$R$36)+SUMIFS(#REF!,Anexo_5[serie],$E$41,Anexo_5[periodo],$R$36)+SUMIFS(Anexo_5[base_no_grabada],Anexo_5[serie],$E$41,Anexo_5[periodo],$R$36) -> #REF! | S41: =SUM(G41:R41) -> #REF! | T41: =AVERAGE(G41:R41) -> #REF!
E42: FF05 | F42: Moneda | G42: =SUMIFS(Anexo_5[base_imponible_18],Anexo_5[serie],$E$42,Anexo_5[periodo],$G$36)+SUMIFS(#REF!,Anexo_5[serie],$E$42,Anexo_5[periodo],$G$36)+SUMIFS(Anexo_5[base_no_grabada],Anexo_5[serie],$E$42,Anexo_5[periodo],$G$36) -> #REF! | H42: =SUMIFS(Anexo_5[base_imponible_18],Anexo_5[serie],$E$42,Anexo_5[periodo],$H$36)+SUMIFS(#REF!,Anexo_5[serie],$E$42,Anexo_5[periodo],$H$36)+SUMIFS(Anexo_5[base_no_grabada],Anexo_5[serie],$E$42,Anexo_5[periodo],$H$36) -> #REF! | I42: =SUMIFS(Anexo_5[base_imponible_18],Anexo_5[serie],$E$42,Anexo_5[periodo],$I$36)+SUMIFS(#REF!,Anexo_5[serie],$E$42,Anexo_5[periodo],$I$36)+SUMIFS(Anexo_5[base_no_grabada],Anexo_5[serie],$E$42,Anexo_5[periodo],$I$36) -> #REF! | J42: =SUMIFS(Anexo_5[base_imponible_18],Anexo_5[serie],$E$42,Anexo_5[periodo],$J$36)+SUMIFS(#REF!,Anexo_5[serie],$E$42,Anexo_5[periodo],$J$36)+SUMIFS(Anexo_5[base_no_grabada],Anexo_5[serie],$E$42,Anexo_5[periodo],$J$36) -> #REF! | K42: =SUMIFS(Anexo_5[base_imponible_18],Anexo_5[serie],$E$42,Anexo_5[periodo],$K$36)+SUMIFS(#REF!,Anexo_5[serie],$E$42,Anexo_5[periodo],$K$36)+SUMIFS(Anexo_5[base_no_grabada],Anexo_5[serie],$E$42,Anexo_5[periodo],$K$36) -> #REF! | L42: =SUMIFS(Anexo_5[base_imponible_18],Anexo_5[serie],$E$42,Anexo_5[periodo],$L$36)+SUMIFS(#REF!,Anexo_5[serie],$E$42,Anexo_5[periodo],$L$36)+SUMIFS(Anexo_5[base_no_grabada],Anexo_5[serie],$E$42,Anexo_5[periodo],$L$36) -> #REF! | M42: =SUMIFS(Anexo_5[base_imponible_18],Anexo_5[serie],$E$42,Anexo_5[periodo],$M$36)+SUMIFS(#REF!,Anexo_5[serie],$E$42,Anexo_5[periodo],$M$36)+SUMIFS(Anexo_5[base_no_grabada],Anexo_5[serie],$E$42,Anexo_5[periodo],$M$36) -> #REF! | N42: =SUMIFS(Anexo_5[base_imponible_18],Anexo_5[serie],$E$42,Anexo_5[periodo],$N$36)+SUMIFS(#REF!,Anexo_5[serie],$E$42,Anexo_5[periodo],$N$36)+SUMIFS(Anexo_5[base_no_grabada],Anexo_5[serie],$E$42,Anexo_5[periodo],$N$36) -> #REF! | O42: =SUMIFS(Anexo_5[base_imponible_18],Anexo_5[serie],$E$42,Anexo_5[periodo],$O$36)+SUMIFS(#REF!,Anexo_5[serie],$E$42,Anexo_5[periodo],$O$36)+SUMIFS(Anexo_5[base_no_grabada],Anexo_5[serie],$E$42,Anexo_5[periodo],$O$36) -> #REF! | P42: =SUMIFS(Anexo_5[base_imponible_18],Anexo_5[serie],$E$42,Anexo_5[periodo],$P$36)+SUMIFS(#REF!,Anexo_5[serie],$E$42,Anexo_5[periodo],$P$36)+SUMIFS(Anexo_5[base_no_grabada],Anexo_5[serie],$E$42,Anexo_5[periodo],$P$36) -> #REF! | Q42: =SUMIFS(Anexo_5[base_imponible_18],Anexo_5[serie],$E$42,Anexo_5[periodo],$Q$36)+SUMIFS(#REF!,Anexo_5[serie],$E$42,Anexo_5[periodo],$Q$36)+SUMIFS(Anexo_5[base_no_grabada],Anexo_5[serie],$E$42,Anexo_5[periodo],$Q$36) -> #REF! | R42: =SUMIFS(Anexo_5[base_imponible_18],Anexo_5[serie],$E$42,Anexo_5[periodo],$R$36)+SUMIFS(#REF!,Anexo_5[serie],$E$42,Anexo_5[periodo],$R$36)+SUMIFS(Anexo_5[base_no_grabada],Anexo_5[serie],$E$42,Anexo_5[periodo],$R$36) -> #REF! | S42: =SUM(G42:R42) -> #REF! | T42: =AVERAGE(G42:R42) -> #REF!
E43: FF07 | F43: Moneda | G43: =SUMIFS(Anexo_5[base_imponible_18],Anexo_5[serie],$E$43,Anexo_5[periodo],$G$36)+SUMIFS(#REF!,Anexo_5[serie],$E$43,Anexo_5[periodo],$G$36)+SUMIFS(Anexo_5[base_no_grabada],Anexo_5[serie],$E$43,Anexo_5[periodo],$G$36) -> #REF! | H43: =SUMIFS(Anexo_5[base_imponible_18],Anexo_5[serie],$E$43,Anexo_5[periodo],$H$36)+SUMIFS(#REF!,Anexo_5[serie],$E$43,Anexo_5[periodo],$H$36)+SUMIFS(Anexo_5[base_no_grabada],Anexo_5[serie],$E$43,Anexo_5[periodo],$H$36) -> #REF! | I43: =SUMIFS(Anexo_5[base_imponible_18],Anexo_5[serie],$E$43,Anexo_5[periodo],$I$36)+SUMIFS(#REF!,Anexo_5[serie],$E$43,Anexo_5[periodo],$I$36)+SUMIFS(Anexo_5[base_no_grabada],Anexo_5[serie],$E$43,Anexo_5[periodo],$I$36) -> #REF! | J43: =SUMIFS(Anexo_5[base_imponible_18],Anexo_5[serie],$E$43,Anexo_5[periodo],$J$36)+SUMIFS(#REF!,Anexo_5[serie],$E$43,Anexo_5[periodo],$J$36)+SUMIFS(Anexo_5[base_no_grabada],Anexo_5[serie],$E$43,Anexo_5[periodo],$J$36) -> #REF! | K43: =SUMIFS(Anexo_5[base_imponible_18],Anexo_5[serie],$E$43,Anexo_5[periodo],$K$36)+SUMIFS(#REF!,Anexo_5[serie],$E$43,Anexo_5[periodo],$K$36)+SUMIFS(Anexo_5[base_no_grabada],Anexo_5[serie],$E$43,Anexo_5[periodo],$K$36) -> #REF! | L43: =SUMIFS(Anexo_5[base_imponible_18],Anexo_5[serie],$E$43,Anexo_5[periodo],$L$36)+SUMIFS(#REF!,Anexo_5[serie],$E$43,Anexo_5[periodo],$L$36)+SUMIFS(Anexo_5[base_no_grabada],Anexo_5[serie],$E$43,Anexo_5[periodo],$L$36) -> #REF! | M43: =SUMIFS(Anexo_5[base_imponible_18],Anexo_5[serie],$E$43,Anexo_5[periodo],$M$36)+SUMIFS(#REF!,Anexo_5[serie],$E$43,Anexo_5[periodo],$M$36)+SUMIFS(Anexo_5[base_no_grabada],Anexo_5[serie],$E$43,Anexo_5[periodo],$M$36) -> #REF! | N43: =SUMIFS(Anexo_5[base_imponible_18],Anexo_5[serie],$E$43,Anexo_5[periodo],$N$36)+SUMIFS(#REF!,Anexo_5[serie],$E$43,Anexo_5[periodo],$N$36)+SUMIFS(Anexo_5[base_no_grabada],Anexo_5[serie],$E$43,Anexo_5[periodo],$N$36) -> #REF! | O43: =SUMIFS(Anexo_5[base_imponible_18],Anexo_5[serie],$E$43,Anexo_5[periodo],$O$36)+SUMIFS(#REF!,Anexo_5[serie],$E$43,Anexo_5[periodo],$O$36)+SUMIFS(Anexo_5[base_no_grabada],Anexo_5[serie],$E$43,Anexo_5[periodo],$O$36) -> #REF! | P43: =SUMIFS(Anexo_5[base_imponible_18],Anexo_5[serie],$E$43,Anexo_5[periodo],$P$36)+SUMIFS(#REF!,Anexo_5[serie],$E$43,Anexo_5[periodo],$P$36)+SUMIFS(Anexo_5[base_no_grabada],Anexo_5[serie],$E$43,Anexo_5[periodo],$P$36) -> #REF! | Q43: =SUMIFS(Anexo_5[base_imponible_18],Anexo_5[serie],$E$43,Anexo_5[periodo],$Q$36)+SUMIFS(#REF!,Anexo_5[serie],$E$43,Anexo_5[periodo],$Q$36)+SUMIFS(Anexo_5[base_no_grabada],Anexo_5[serie],$E$43,Anexo_5[periodo],$Q$36) -> #REF! | R43: =SUMIFS(Anexo_5[base_imponible_18],Anexo_5[serie],$E$43,Anexo_5[periodo],$R$36)+SUMIFS(#REF!,Anexo_5[serie],$E$43,Anexo_5[periodo],$R$36)+SUMIFS(Anexo_5[base_no_grabada],Anexo_5[serie],$E$43,Anexo_5[periodo],$R$36) -> #REF! | S43: =SUM(G43:R43) -> #REF! | T43: =AVERAGE(G43:R43) -> #REF!
E44: FFN5 | F44: Moneda | G44: =SUMIFS(Anexo_5[base_imponible_18],Anexo_5[serie],$E$44,Anexo_5[periodo],$G$36)+SUMIFS(#REF!,Anexo_5[serie],$E$44,Anexo_5[periodo],$G$36)+SUMIFS(Anexo_5[base_no_grabada],Anexo_5[serie],$E$44,Anexo_5[periodo],$G$36) -> #REF! | H44: =SUMIFS(Anexo_5[base_imponible_18],Anexo_5[serie],$E$44,Anexo_5[periodo],$H$36)+SUMIFS(#REF!,Anexo_5[serie],$E$44,Anexo_5[periodo],$H$36)+SUMIFS(Anexo_5[base_no_grabada],Anexo_5[serie],$E$44,Anexo_5[periodo],$H$36) -> #REF! | I44: =SUMIFS(Anexo_5[base_imponible_18],Anexo_5[serie],$E$44,Anexo_5[periodo],$I$36)+SUMIFS(#REF!,Anexo_5[serie],$E$44,Anexo_5[periodo],$I$36)+SUMIFS(Anexo_5[base_no_grabada],Anexo_5[serie],$E$44,Anexo_5[periodo],$I$36) -> #REF! | J44: =SUMIFS(Anexo_5[base_imponible_18],Anexo_5[serie],$E$44,Anexo_5[periodo],$J$36)+SUMIFS(#REF!,Anexo_5[serie],$E$44,Anexo_5[periodo],$J$36)+SUMIFS(Anexo_5[base_no_grabada],Anexo_5[serie],$E$44,Anexo_5[periodo],$J$36) -> #REF! | K44: =SUMIFS(Anexo_5[base_imponible_18],Anexo_5[serie],$E$44,Anexo_5[periodo],$K$36)+SUMIFS(#REF!,Anexo_5[serie],$E$44,Anexo_5[periodo],$K$36)+SUMIFS(Anexo_5[base_no_grabada],Anexo_5[serie],$E$44,Anexo_5[periodo],$K$36) -> #REF! | L44: =SUMIFS(Anexo_5[base_imponible_18],Anexo_5[serie],$E$44,Anexo_5[periodo],$L$36)+SUMIFS(#REF!,Anexo_5[serie],$E$44,Anexo_5[periodo],$L$36)+SUMIFS(Anexo_5[base_no_grabada],Anexo_5[serie],$E$44,Anexo_5[periodo],$L$36) -> #REF! | M44: =SUMIFS(Anexo_5[base_imponible_18],Anexo_5[serie],$E$44,Anexo_5[periodo],$M$36)+SUMIFS(#REF!,Anexo_5[serie],$E$44,Anexo_5[periodo],$M$36)+SUMIFS(Anexo_5[base_no_grabada],Anexo_5[serie],$E$44,Anexo_5[periodo],$M$36) -> #REF! | N44: =SUMIFS(Anexo_5[base_imponible_18],Anexo_5[serie],$E$44,Anexo_5[periodo],$N$36)+SUMIFS(#REF!,Anexo_5[serie],$E$44,Anexo_5[periodo],$N$36)+SUMIFS(Anexo_5[base_no_grabada],Anexo_5[serie],$E$44,Anexo_5[periodo],$N$36) -> #REF! | O44: =SUMIFS(Anexo_5[base_imponible_18],Anexo_5[serie],$E$44,Anexo_5[periodo],$O$36)+SUMIFS(#REF!,Anexo_5[serie],$E$44,Anexo_5[periodo],$O$36)+SUMIFS(Anexo_5[base_no_grabada],Anexo_5[serie],$E$44,Anexo_5[periodo],$O$36) -> #REF! | P44: =SUMIFS(Anexo_5[base_imponible_18],Anexo_5[serie],$E$44,Anexo_5[periodo],$P$36)+SUMIFS(#REF!,Anexo_5[serie],$E$44,Anexo_5[periodo],$P$36)+SUMIFS(Anexo_5[base_no_grabada],Anexo_5[serie],$E$44,Anexo_5[periodo],$P$36) -> #REF! | Q44: =SUMIFS(Anexo_5[base_imponible_18],Anexo_5[serie],$E$44,Anexo_5[periodo],$Q$36)+SUMIFS(#REF!,Anexo_5[serie],$E$44,Anexo_5[periodo],$Q$36)+SUMIFS(Anexo_5[base_no_grabada],Anexo_5[serie],$E$44,Anexo_5[periodo],$Q$36) -> #REF! | R44: =SUMIFS(Anexo_5[base_imponible_18],Anexo_5[serie],$E$44,Anexo_5[periodo],$R$36)+SUMIFS(#REF!,Anexo_5[serie],$E$44,Anexo_5[periodo],$R$36)+SUMIFS(Anexo_5[base_no_grabada],Anexo_5[serie],$E$44,Anexo_5[periodo],$R$36) -> #REF! | S44: =SUM(G44:R44) -> #REF! | T44: =AVERAGE(G44:R44) -> #REF!
E45: Descuentos y Rebajas | F45: Moneda | G45: =SUMIFS(Anexo_5[base_imponible_18],Anexo_5[serie],$E$45,Anexo_5[periodo],$G$36)+SUMIFS(#REF!,Anexo_5[serie],$E$45,Anexo_5[periodo],$G$36)+SUMIFS(Anexo_5[base_no_grabada],Anexo_5[serie],$E$45,Anexo_5[periodo],$G$36) -> #REF! | H45: =SUMIFS(Anexo_5[base_imponible_18],Anexo_5[serie],$E$45,Anexo_5[periodo],$H$36)+SUMIFS(#REF!,Anexo_5[serie],$E$45,Anexo_5[periodo],$H$36)+SUMIFS(Anexo_5[base_no_grabada],Anexo_5[serie],$E$45,Anexo_5[periodo],$H$36) -> #REF! | I45: =SUMIFS(Anexo_5[base_imponible_18],Anexo_5[serie],$E$45,Anexo_5[periodo],$I$36)+SUMIFS(#REF!,Anexo_5[serie],$E$45,Anexo_5[periodo],$I$36)+SUMIFS(Anexo_5[base_no_grabada],Anexo_5[serie],$E$45,Anexo_5[periodo],$I$36) -> #REF! | J45: =SUMIFS(Anexo_5[base_imponible_18],Anexo_5[serie],$E$45,Anexo_5[periodo],$J$36)+SUMIFS(#REF!,Anexo_5[serie],$E$45,Anexo_5[periodo],$J$36)+SUMIFS(Anexo_5[base_no_grabada],Anexo_5[serie],$E$45,Anexo_5[periodo],$J$36) -> #REF! | K45: =SUMIFS(Anexo_5[base_imponible_18],Anexo_5[serie],$E$45,Anexo_5[periodo],$K$36)+SUMIFS(#REF!,Anexo_5[serie],$E$45,Anexo_5[periodo],$K$36)+SUMIFS(Anexo_5[base_no_grabada],Anexo_5[serie],$E$45,Anexo_5[periodo],$K$36) -> #REF! | L45: =SUMIFS(Anexo_5[base_imponible_18],Anexo_5[serie],$E$45,Anexo_5[periodo],$L$36)+SUMIFS(#REF!,Anexo_5[serie],$E$45,Anexo_5[periodo],$L$36)+SUMIFS(Anexo_5[base_no_grabada],Anexo_5[serie],$E$45,Anexo_5[periodo],$L$36) -> #REF! | M45: =SUMIFS(Anexo_5[base_imponible_18],Anexo_5[serie],$E$45,Anexo_5[periodo],$M$36)+SUMIFS(#REF!,Anexo_5[serie],$E$45,Anexo_5[periodo],$M$36)+SUMIFS(Anexo_5[base_no_grabada],Anexo_5[serie],$E$45,Anexo_5[periodo],$M$36) -> #REF! | N45: =SUMIFS(Anexo_5[base_imponible_18],Anexo_5[serie],$E$45,Anexo_5[periodo],$N$36)+SUMIFS(#REF!,Anexo_5[serie],$E$45,Anexo_5[periodo],$N$36)+SUMIFS(Anexo_5[base_no_grabada],Anexo_5[serie],$E$45,Anexo_5[periodo],$N$36) -> #REF! | O45: =SUMIFS(Anexo_5[base_imponible_18],Anexo_5[serie],$E$45,Anexo_5[periodo],$O$36)+SUMIFS(#REF!,Anexo_5[serie],$E$45,Anexo_5[periodo],$O$36)+SUMIFS(Anexo_5[base_no_grabada],Anexo_5[serie],$E$45,Anexo_5[periodo],$O$36) -> #REF! | P45: =SUMIFS(Anexo_5[base_imponible_18],Anexo_5[serie],$E$45,Anexo_5[periodo],$P$36)+SUMIFS(#REF!,Anexo_5[serie],$E$45,Anexo_5[periodo],$P$36)+SUMIFS(Anexo_5[base_no_grabada],Anexo_5[serie],$E$45,Anexo_5[periodo],$P$36) -> #REF! | Q45: =SUMIFS(Anexo_5[base_imponible_18],Anexo_5[serie],$E$45,Anexo_5[periodo],$Q$36)+SUMIFS(#REF!,Anexo_5[serie],$E$45,Anexo_5[periodo],$Q$36)+SUMIFS(Anexo_5[base_no_grabada],Anexo_5[serie],$E$45,Anexo_5[periodo],$Q$36) -> #REF! | R45: =SUMIFS(Anexo_5[base_imponible_18],Anexo_5[serie],$E$45,Anexo_5[periodo],$R$36)+SUMIFS(#REF!,Anexo_5[serie],$E$45,Anexo_5[periodo],$R$36)+SUMIFS(Anexo_5[base_no_grabada],Anexo_5[serie],$E$45,Anexo_5[periodo],$R$36) -> #REF! | S45: =SUM(G45:R45) -> #REF! | T45: =AVERAGE(G45:R45) -> #REF!
E46: TOTAL RESIDUOS FACTURADOS | F46: Moneda | G46: =SUM(G37:G45) -> #REF! | H46: =SUM(H37:H45) -> #REF! | I46: =SUM(I37:I45) -> #REF! | J46: =SUM(J37:J45) -> #REF! | K46: =SUM(K37:K45) -> #REF! | L46: =SUM(L37:L45) -> #REF! | M46: =SUM(M37:M45) -> #REF! | N46: =SUM(N37:N45) -> #REF! | ... T46: =SUM(T37:T45) -> #REF!
E47: % SOBRE LA VENTA TOTAL | F47: % | G47: =IFERROR(((G46*100)/G61)*0.01,0) -> 0 | H47: =IFERROR(((H46*100)/H61)*0.01,0) -> 0 | I47: =IFERROR(((I46*100)/I61)*0.01,0) -> 0 | J47: =IFERROR(((J46*100)/J61)*0.01,0) -> 0 | K47: =IFERROR(((K46*100)/K61)*0.01,0) -> 0 | L47: =IFERROR(((L46*100)/L61)*0.01,0) -> 0 | M47: =IFERROR(((M46*100)/M61)*0.01,0) -> 0 | N47: =IFERROR(((N46*100)/N61)*0.01,0) -> 0 | ... T47: =IFERROR(((T46*100)/T61)*0.01,0) -> 0
C49: SERVICIOS FACTURADOS | E49: Residuos Peligrosos | F49: Moneda | G49: =SUMIFS(Anexo_5[base_imponible_18],Anexo_5[VENTAS KPI],$E$49,Anexo_5[periodo],$G$36)+SUMIFS(#REF!,Anexo_5[VENTAS KPI],$E$49,Anexo_5[periodo],$G$36)+SUMIFS(Anexo_5[base_no_grabada],Anexo_5[VENTAS KPI],$E$49,Anexo_5[periodo],$G$36) -> #REF! | H49: =SUMIFS(Anexo_5[base_imponible_18],Anexo_5[VENTAS KPI],$E$49,Anexo_5[periodo],$H$36)+SUMIFS(#REF!,Anexo_5[VENTAS KPI],$E$49,Anexo_5[periodo],$H$36)+SUMIFS(Anexo_5[base_no_grabada],Anexo_5[VENTAS KPI],$E$49,Anexo_5[periodo],$H$36) -> #REF! | I49: =SUMIFS(Anexo_5[base_imponible_18],Anexo_5[VENTAS KPI],$E$49,Anexo_5[periodo],$I$36)+SUMIFS(#REF!,Anexo_5[VENTAS KPI],$E$49,Anexo_5[periodo],$I$36)+SUMIFS(Anexo_5[base_no_grabada],Anexo_5[VENTAS KPI],$E$49,Anexo_5[periodo],$I$36) -> #REF! | J49: =SUMIFS(Anexo_5[base_imponible_18],Anexo_5[VENTAS KPI],$E$49,Anexo_5[periodo],$J$36)+SUMIFS(#REF!,Anexo_5[VENTAS KPI],$E$49,Anexo_5[periodo],$J$36)+SUMIFS(Anexo_5[base_no_grabada],Anexo_5[VENTAS KPI],$E$49,Anexo_5[periodo],$J$36) -> #REF! | K49: =SUMIFS(Anexo_5[base_imponible_18],Anexo_5[VENTAS KPI],$E$49,Anexo_5[periodo],$K$36)+SUMIFS(#REF!,Anexo_5[VENTAS KPI],$E$49,Anexo_5[periodo],$K$36)+SUMIFS(Anexo_5[base_no_grabada],Anexo_5[VENTAS KPI],$E$49,Anexo_5[periodo],$K$36) -> #REF! | L49: =SUMIFS(Anexo_5[base_imponible_18],Anexo_5[VENTAS KPI],$E$49,Anexo_5[periodo],$L$36)+SUMIFS(#REF!,Anexo_5[VENTAS KPI],$E$49,Anexo_5[periodo],$L$36)+SUMIFS(Anexo_5[base_no_grabada],Anexo_5[VENTAS KPI],$E$49,Anexo_5[periodo],$L$36) -> #REF! | M49: =SUMIFS(Anexo_5[base_imponible_18],Anexo_5[VENTAS KPI],$E$49,Anexo_5[periodo],$M$36)+SUMIFS(#REF!,Anexo_5[VENTAS KPI],$E$49,Anexo_5[periodo],$M$36)+SUMIFS(Anexo_5[base_no_grabada],Anexo_5[VENTAS KPI],$E$49,Anexo_5[periodo],$M$36) -> #REF! | N49: =SUMIFS(Anexo_5[base_imponible_18],Anexo_5[VENTAS KPI],$E$49,Anexo_5[periodo],$N$36)+SUMIFS(#REF!,Anexo_5[VENTAS KPI],$E$49,Anexo_5[periodo],$N$36)+SUMIFS(Anexo_5[base_no_grabada],Anexo_5[VENTAS KPI],$E$49,Anexo_5[periodo],$N$36) -> #REF! | O49: =SUMIFS(Anexo_5[base_imponible_18],Anexo_5[VENTAS KPI],$E$49,Anexo_5[periodo],$O$36)+SUMIFS(#REF!,Anexo_5[VENTAS KPI],$E$49,Anexo_5[periodo],$O$36)+SUMIFS(Anexo_5[base_no_grabada],Anexo_5[VENTAS KPI],$E$49,Anexo_5[periodo],$O$36) -> #REF! | P49: =SUMIFS(Anexo_5[base_imponible_18],Anexo_5[VENTAS KPI],$E$49,Anexo_5[periodo],$P$36)+SUMIFS(#REF!,Anexo_5[VENTAS KPI],$E$49,Anexo_5[periodo],$P$36)+SUMIFS(Anexo_5[base_no_grabada],Anexo_5[VENTAS KPI],$E$49,Anexo_5[periodo],$P$36) -> #REF! | Q49: =SUMIFS(Anexo_5[base_imponible_18],Anexo_5[VENTAS KPI],$E$49,Anexo_5[periodo],$Q$36)+SUMIFS(#REF!,Anexo_5[VENTAS KPI],$E$49,Anexo_5[periodo],$Q$36)+SUMIFS(Anexo_5[base_no_grabada],Anexo_5[VENTAS KPI],$E$49,Anexo_5[periodo],$Q$36) -> #REF! | R49: =SUMIFS(Anexo_5[base_imponible_18],Anexo_5[VENTAS KPI],$E$49,Anexo_5[periodo],$R$36)+SUMIFS(#REF!,Anexo_5[VENTAS KPI],$E$49,Anexo_5[periodo],$R$36)+SUMIFS(Anexo_5[base_no_grabada],Anexo_5[VENTAS KPI],$E$49,Anexo_5[periodo],$R$36) -> #REF! | S49: =SUM(G49:R49) -> #REF! | T49: =AVERAGE(G49:R49) -> #REF!
E50: Residuos No Peligrosos | F50: Moneda | G50: =SUMIFS(Anexo_5[base_imponible_18],Anexo_5[VENTAS KPI],$E$50,Anexo_5[periodo],$G$36)+SUMIFS(#REF!,Anexo_5[VENTAS KPI],$E$50,Anexo_5[periodo],$G$36)+SUMIFS(Anexo_5[base_no_grabada],Anexo_5[VENTAS KPI],$E$50,Anexo_5[periodo],$G$36) -> #REF! | H50: =SUMIFS(Anexo_5[base_imponible_18],Anexo_5[VENTAS KPI],$E$50,Anexo_5[periodo],$H$36)+SUMIFS(#REF!,Anexo_5[VENTAS KPI],$E$50,Anexo_5[periodo],$H$36)+SUMIFS(Anexo_5[base_no_grabada],Anexo_5[VENTAS KPI],$E$50,Anexo_5[periodo],$H$36) -> #REF! | I50: =SUMIFS(Anexo_5[base_imponible_18],Anexo_5[VENTAS KPI],$E$50,Anexo_5[periodo],$I$36)+SUMIFS(#REF!,Anexo_5[VENTAS KPI],$E$50,Anexo_5[periodo],$I$36)+SUMIFS(Anexo_5[base_no_grabada],Anexo_5[VENTAS KPI],$E$50,Anexo_5[periodo],$I$36) -> #REF! | J50: =SUMIFS(Anexo_5[base_imponible_18],Anexo_5[VENTAS KPI],$E$50,Anexo_5[periodo],$J$36)+SUMIFS(#REF!,Anexo_5[VENTAS KPI],$E$50,Anexo_5[periodo],$J$36)+SUMIFS(Anexo_5[base_no_grabada],Anexo_5[VENTAS KPI],$E$50,Anexo_5[periodo],$J$36) -> #REF! | K50: =SUMIFS(Anexo_5[base_imponible_18],Anexo_5[VENTAS KPI],$E$50,Anexo_5[periodo],$K$36)+SUMIFS(#REF!,Anexo_5[VENTAS KPI],$E$50,Anexo_5[periodo],$K$36)+SUMIFS(Anexo_5[base_no_grabada],Anexo_5[VENTAS KPI],$E$50,Anexo_5[periodo],$K$36) -> #REF! | L50: =SUMIFS(Anexo_5[base_imponible_18],Anexo_5[VENTAS KPI],$E$50,Anexo_5[periodo],$L$36)+SUMIFS(#REF!,Anexo_5[VENTAS KPI],$E$50,Anexo_5[periodo],$L$36)+SUMIFS(Anexo_5[base_no_grabada],Anexo_5[VENTAS KPI],$E$50,Anexo_5[periodo],$L$36) -> #REF! | M50: =SUMIFS(Anexo_5[base_imponible_18],Anexo_5[VENTAS KPI],$E$50,Anexo_5[periodo],$M$36)+SUMIFS(#REF!,Anexo_5[VENTAS KPI],$E$50,Anexo_5[periodo],$M$36)+SUMIFS(Anexo_5[base_no_grabada],Anexo_5[VENTAS KPI],$E$50,Anexo_5[periodo],$M$36) -> #REF! | N50: =SUMIFS(Anexo_5[base_imponible_18],Anexo_5[VENTAS KPI],$E$50,Anexo_5[periodo],$N$36)+SUMIFS(#REF!,Anexo_5[VENTAS KPI],$E$50,Anexo_5[periodo],$N$36)+SUMIFS(Anexo_5[base_no_grabada],Anexo_5[VENTAS KPI],$E$50,Anexo_5[periodo],$N$36) -> #REF! | O50: =SUMIFS(Anexo_5[base_imponible_18],Anexo_5[VENTAS KPI],$E$50,Anexo_5[periodo],$O$36)+SUMIFS(#REF!,Anexo_5[VENTAS KPI],$E$50,Anexo_5[periodo],$O$36)+SUMIFS(Anexo_5[base_no_grabada],Anexo_5[VENTAS KPI],$E$50,Anexo_5[periodo],$O$36) -> #REF! | P50: =SUMIFS(Anexo_5[base_imponible_18],Anexo_5[VENTAS KPI],$E$50,Anexo_5[periodo],$P$36)+SUMIFS(#REF!,Anexo_5[VENTAS KPI],$E$50,Anexo_5[periodo],$P$36)+SUMIFS(Anexo_5[base_no_grabada],Anexo_5[VENTAS KPI],$E$50,Anexo_5[periodo],$P$36) -> #REF! | Q50: =SUMIFS(Anexo_5[base_imponible_18],Anexo_5[VENTAS KPI],$E$50,Anexo_5[periodo],$Q$36)+SUMIFS(#REF!,Anexo_5[VENTAS KPI],$E$50,Anexo_5[periodo],$Q$36)+SUMIFS(Anexo_5[base_no_grabada],Anexo_5[VENTAS KPI],$E$50,Anexo_5[periodo],$Q$36) -> #REF! | R50: =SUMIFS(Anexo_5[base_imponible_18],Anexo_5[VENTAS KPI],$E$50,Anexo_5[periodo],$R$36)+SUMIFS(#REF!,Anexo_5[VENTAS KPI],$E$50,Anexo_5[periodo],$R$36)+SUMIFS(Anexo_5[base_no_grabada],Anexo_5[VENTAS KPI],$E$50,Anexo_5[periodo],$R$36) -> #REF! | S50: =SUM(G50:R50) -> #REF! | T50: =AVERAGE(G50:R50) -> #REF!
E51: Residuos Biocontaminados | F51: Moneda | G51: =SUMIFS(Anexo_5[base_imponible_18],Anexo_5[VENTAS KPI],$E$51,Anexo_5[periodo],$G$36)+SUMIFS(#REF!,Anexo_5[VENTAS KPI],$E$51,Anexo_5[periodo],$G$36)+SUMIFS(Anexo_5[base_no_grabada],Anexo_5[VENTAS KPI],$E$51,Anexo_5[periodo],$G$36) -> #REF! | H51: =SUMIFS(Anexo_5[base_imponible_18],Anexo_5[VENTAS KPI],$E$51,Anexo_5[periodo],$H$36)+SUMIFS(#REF!,Anexo_5[VENTAS KPI],$E$51,Anexo_5[periodo],$H$36)+SUMIFS(Anexo_5[base_no_grabada],Anexo_5[VENTAS KPI],$E$51,Anexo_5[periodo],$H$36) -> #REF! | I51: =SUMIFS(Anexo_5[base_imponible_18],Anexo_5[VENTAS KPI],$E$51,Anexo_5[periodo],$I$36)+SUMIFS(#REF!,Anexo_5[VENTAS KPI],$E$51,Anexo_5[periodo],$I$36)+SUMIFS(Anexo_5[base_no_grabada],Anexo_5[VENTAS KPI],$E$51,Anexo_5[periodo],$I$36) -> #REF! | J51: =SUMIFS(Anexo_5[base_imponible_18],Anexo_5[VENTAS KPI],$E$51,Anexo_5[periodo],$J$36)+SUMIFS(#REF!,Anexo_5[VENTAS KPI],$E$51,Anexo_5[periodo],$J$36)+SUMIFS(Anexo_5[base_no_grabada],Anexo_5[VENTAS KPI],$E$51,Anexo_5[periodo],$J$36) -> #REF! | K51: =SUMIFS(Anexo_5[base_imponible_18],Anexo_5[VENTAS KPI],$E$51,Anexo_5[periodo],$K$36)+SUMIFS(#REF!,Anexo_5[VENTAS KPI],$E$51,Anexo_5[periodo],$K$36)+SUMIFS(Anexo_5[base_no_grabada],Anexo_5[VENTAS KPI],$E$51,Anexo_5[periodo],$K$36) -> #REF! | L51: =SUMIFS(Anexo_5[base_imponible_18],Anexo_5[VENTAS KPI],$E$51,Anexo_5[periodo],$L$36)+SUMIFS(#REF!,Anexo_5[VENTAS KPI],$E$51,Anexo_5[periodo],$L$36)+SUMIFS(Anexo_5[base_no_grabada],Anexo_5[VENTAS KPI],$E$51,Anexo_5[periodo],$L$36) -> #REF! | M51: =SUMIFS(Anexo_5[base_imponible_18],Anexo_5[VENTAS KPI],$E$51,Anexo_5[periodo],$M$36)+SUMIFS(#REF!,Anexo_5[VENTAS KPI],$E$51,Anexo_5[periodo],$M$36)+SUMIFS(Anexo_5[base_no_grabada],Anexo_5[VENTAS KPI],$E$51,Anexo_5[periodo],$M$36) -> #REF! | N51: =SUMIFS(Anexo_5[base_imponible_18],Anexo_5[VENTAS KPI],$E$51,Anexo_5[periodo],$N$36)+SUMIFS(#REF!,Anexo_5[VENTAS KPI],$E$51,Anexo_5[periodo],$N$36)+SUMIFS(Anexo_5[base_no_grabada],Anexo_5[VENTAS KPI],$E$51,Anexo_5[periodo],$N$36) -> #REF! | O51: =SUMIFS(Anexo_5[base_imponible_18],Anexo_5[VENTAS KPI],$E$51,Anexo_5[periodo],$O$36)+SUMIFS(#REF!,Anexo_5[VENTAS KPI],$E$51,Anexo_5[periodo],$O$36)+SUMIFS(Anexo_5[base_no_grabada],Anexo_5[VENTAS KPI],$E$51,Anexo_5[periodo],$O$36) -> #REF! | P51: =SUMIFS(Anexo_5[base_imponible_18],Anexo_5[VENTAS KPI],$E$51,Anexo_5[periodo],$P$36)+SUMIFS(#REF!,Anexo_5[VENTAS KPI],$E$51,Anexo_5[periodo],$P$36)+SUMIFS(Anexo_5[base_no_grabada],Anexo_5[VENTAS KPI],$E$51,Anexo_5[periodo],$P$36) -> #REF! | Q51: =SUMIFS(Anexo_5[base_imponible_18],Anexo_5[VENTAS KPI],$E$51,Anexo_5[periodo],$Q$36)+SUMIFS(#REF!,Anexo_5[VENTAS KPI],$E$51,Anexo_5[periodo],$Q$36)+SUMIFS(Anexo_5[base_no_grabada],Anexo_5[VENTAS KPI],$E$51,Anexo_5[periodo],$Q$36) -> #REF! | R51: =SUMIFS(Anexo_5[base_imponible_18],Anexo_5[VENTAS KPI],$E$51,Anexo_5[periodo],$R$36)+SUMIFS(#REF!,Anexo_5[VENTAS KPI],$E$51,Anexo_5[periodo],$R$36)+SUMIFS(Anexo_5[base_no_grabada],Anexo_5[VENTAS KPI],$E$51,Anexo_5[periodo],$R$36) -> #REF! | S51: =SUM(G51:R51) -> #REF! | T51: =AVERAGE(G51:R51) -> #REF!
E52: RAEE | F52: Moneda | G52: =SUMIFS(Anexo_5[base_imponible_18],Anexo_5[VENTAS KPI],$E$52,Anexo_5[periodo],$G$36)+SUMIFS(#REF!,Anexo_5[VENTAS KPI],$E$52,Anexo_5[periodo],$G$36)+SUMIFS(Anexo_5[base_no_grabada],Anexo_5[VENTAS KPI],$E$52,Anexo_5[periodo],$G$36) -> #REF! | H52: =SUMIFS(Anexo_5[base_imponible_18],Anexo_5[VENTAS KPI],$E$52,Anexo_5[periodo],$H$36)+SUMIFS(#REF!,Anexo_5[VENTAS KPI],$E$52,Anexo_5[periodo],$H$36)+SUMIFS(Anexo_5[base_no_grabada],Anexo_5[VENTAS KPI],$E$52,Anexo_5[periodo],$H$36) -> #REF! | I52: =SUMIFS(Anexo_5[base_imponible_18],Anexo_5[VENTAS KPI],$E$52,Anexo_5[periodo],$I$36)+SUMIFS(#REF!,Anexo_5[VENTAS KPI],$E$52,Anexo_5[periodo],$I$36)+SUMIFS(Anexo_5[base_no_grabada],Anexo_5[VENTAS KPI],$E$52,Anexo_5[periodo],$I$36) -> #REF! | J52: =SUMIFS(Anexo_5[base_imponible_18],Anexo_5[VENTAS KPI],$E$52,Anexo_5[periodo],$J$36)+SUMIFS(#REF!,Anexo_5[VENTAS KPI],$E$52,Anexo_5[periodo],$J$36)+SUMIFS(Anexo_5[base_no_grabada],Anexo_5[VENTAS KPI],$E$52,Anexo_5[periodo],$J$36) -> #REF! | K52: =SUMIFS(Anexo_5[base_imponible_18],Anexo_5[VENTAS KPI],$E$52,Anexo_5[periodo],$K$36)+SUMIFS(#REF!,Anexo_5[VENTAS KPI],$E$52,Anexo_5[periodo],$K$36)+SUMIFS(Anexo_5[base_no_grabada],Anexo_5[VENTAS KPI],$E$52,Anexo_5[periodo],$K$36) -> #REF! | L52: =SUMIFS(Anexo_5[base_imponible_18],Anexo_5[VENTAS KPI],$E$52,Anexo_5[periodo],$L$36)+SUMIFS(#REF!,Anexo_5[VENTAS KPI],$E$52,Anexo_5[periodo],$L$36)+SUMIFS(Anexo_5[base_no_grabada],Anexo_5[VENTAS KPI],$E$52,Anexo_5[periodo],$L$36) -> #REF! | M52: =SUMIFS(Anexo_5[base_imponible_18],Anexo_5[VENTAS KPI],$E$52,Anexo_5[periodo],$M$36)+SUMIFS(#REF!,Anexo_5[VENTAS KPI],$E$52,Anexo_5[periodo],$M$36)+SUMIFS(Anexo_5[base_no_grabada],Anexo_5[VENTAS KPI],$E$52,Anexo_5[periodo],$M$36) -> #REF! | N52: =SUMIFS(Anexo_5[base_imponible_18],Anexo_5[VENTAS KPI],$E$52,Anexo_5[periodo],$N$36)+SUMIFS(#REF!,Anexo_5[VENTAS KPI],$E$52,Anexo_5[periodo],$N$36)+SUMIFS(Anexo_5[base_no_grabada],Anexo_5[VENTAS KPI],$E$52,Anexo_5[periodo],$N$36) -> #REF! | O52: =SUMIFS(Anexo_5[base_imponible_18],Anexo_5[VENTAS KPI],$E$52,Anexo_5[periodo],$O$36)+SUMIFS(#REF!,Anexo_5[VENTAS KPI],$E$52,Anexo_5[periodo],$O$36)+SUMIFS(Anexo_5[base_no_grabada],Anexo_5[VENTAS KPI],$E$52,Anexo_5[periodo],$O$36) -> #REF! | P52: =SUMIFS(Anexo_5[base_imponible_18],Anexo_5[VENTAS KPI],$E$52,Anexo_5[periodo],$P$36)+SUMIFS(#REF!,Anexo_5[VENTAS KPI],$E$52,Anexo_5[periodo],$P$36)+SUMIFS(Anexo_5[base_no_grabada],Anexo_5[VENTAS KPI],$E$52,Anexo_5[periodo],$P$36) -> #REF! | Q52: =SUMIFS(Anexo_5[base_imponible_18],Anexo_5[VENTAS KPI],$E$52,Anexo_5[periodo],$Q$36)+SUMIFS(#REF!,Anexo_5[VENTAS KPI],$E$52,Anexo_5[periodo],$Q$36)+SUMIFS(Anexo_5[base_no_grabada],Anexo_5[VENTAS KPI],$E$52,Anexo_5[periodo],$Q$36) -> #REF! | R52: =SUMIFS(Anexo_5[base_imponible_18],Anexo_5[VENTAS KPI],$E$52,Anexo_5[periodo],$R$36)+SUMIFS(#REF!,Anexo_5[VENTAS KPI],$E$52,Anexo_5[periodo],$R$36)+SUMIFS(Anexo_5[base_no_grabada],Anexo_5[VENTAS KPI],$E$52,Anexo_5[periodo],$R$36) -> #REF! | S52: =SUM(G52:R52) -> #REF! | T52: =AVERAGE(G52:R52) -> #REF!
E53: RCD | F53: Moneda | G53: =SUMIFS(Anexo_5[base_imponible_18],Anexo_5[VENTAS KPI],$E$53,Anexo_5[periodo],$G$36)+SUMIFS(#REF!,Anexo_5[VENTAS KPI],$E$53,Anexo_5[periodo],$G$36)+SUMIFS(Anexo_5[base_no_grabada],Anexo_5[VENTAS KPI],$E$53,Anexo_5[periodo],$G$36) -> #REF! | H53: =SUMIFS(Anexo_5[base_imponible_18],Anexo_5[VENTAS KPI],$E$53,Anexo_5[periodo],$H$36)+SUMIFS(#REF!,Anexo_5[VENTAS KPI],$E$53,Anexo_5[periodo],$H$36)+SUMIFS(Anexo_5[base_no_grabada],Anexo_5[VENTAS KPI],$E$53,Anexo_5[periodo],$H$36) -> #REF! | I53: =SUMIFS(Anexo_5[base_imponible_18],Anexo_5[VENTAS KPI],$E$53,Anexo_5[periodo],$I$36)+SUMIFS(#REF!,Anexo_5[VENTAS KPI],$E$53,Anexo_5[periodo],$I$36)+SUMIFS(Anexo_5[base_no_grabada],Anexo_5[VENTAS KPI],$E$53,Anexo_5[periodo],$I$36) -> #REF! | J53: =SUMIFS(Anexo_5[base_imponible_18],Anexo_5[VENTAS KPI],$E$53,Anexo_5[periodo],$J$36)+SUMIFS(#REF!,Anexo_5[VENTAS KPI],$E$53,Anexo_5[periodo],$J$36)+SUMIFS(Anexo_5[base_no_grabada],Anexo_5[VENTAS KPI],$E$53,Anexo_5[periodo],$J$36) -> #REF! | K53: =SUMIFS(Anexo_5[base_imponible_18],Anexo_5[VENTAS KPI],$E$53,Anexo_5[periodo],$K$36)+SUMIFS(#REF!,Anexo_5[VENTAS KPI],$E$53,Anexo_5[periodo],$K$36)+SUMIFS(Anexo_5[base_no_grabada],Anexo_5[VENTAS KPI],$E$53,Anexo_5[periodo],$K$36) -> #REF! | L53: =SUMIFS(Anexo_5[base_imponible_18],Anexo_5[VENTAS KPI],$E$53,Anexo_5[periodo],$L$36)+SUMIFS(#REF!,Anexo_5[VENTAS KPI],$E$53,Anexo_5[periodo],$L$36)+SUMIFS(Anexo_5[base_no_grabada],Anexo_5[VENTAS KPI],$E$53,Anexo_5[periodo],$L$36) -> #REF! | M53: =SUMIFS(Anexo_5[base_imponible_18],Anexo_5[VENTAS KPI],$E$53,Anexo_5[periodo],$M$36)+SUMIFS(#REF!,Anexo_5[VENTAS KPI],$E$53,Anexo_5[periodo],$M$36)+SUMIFS(Anexo_5[base_no_grabada],Anexo_5[VENTAS KPI],$E$53,Anexo_5[periodo],$M$36) -> #REF! | N53: =SUMIFS(Anexo_5[base_imponible_18],Anexo_5[VENTAS KPI],$E$53,Anexo_5[periodo],$N$36)+SUMIFS(#REF!,Anexo_5[VENTAS KPI],$E$53,Anexo_5[periodo],$N$36)+SUMIFS(Anexo_5[base_no_grabada],Anexo_5[VENTAS KPI],$E$53,Anexo_5[periodo],$N$36) -> #REF! | O53: =SUMIFS(Anexo_5[base_imponible_18],Anexo_5[VENTAS KPI],$E$53,Anexo_5[periodo],$O$36)+SUMIFS(#REF!,Anexo_5[VENTAS KPI],$E$53,Anexo_5[periodo],$O$36)+SUMIFS(Anexo_5[base_no_grabada],Anexo_5[VENTAS KPI],$E$53,Anexo_5[periodo],$O$36) -> #REF! | P53: =SUMIFS(Anexo_5[base_imponible_18],Anexo_5[VENTAS KPI],$E$53,Anexo_5[periodo],$P$36)+SUMIFS(#REF!,Anexo_5[VENTAS KPI],$E$53,Anexo_5[periodo],$P$36)+SUMIFS(Anexo_5[base_no_grabada],Anexo_5[VENTAS KPI],$E$53,Anexo_5[periodo],$P$36) -> #REF! | Q53: =SUMIFS(Anexo_5[base_imponible_18],Anexo_5[VENTAS KPI],$E$53,Anexo_5[periodo],$Q$36)+SUMIFS(#REF!,Anexo_5[VENTAS KPI],$E$53,Anexo_5[periodo],$Q$36)+SUMIFS(Anexo_5[base_no_grabada],Anexo_5[VENTAS KPI],$E$53,Anexo_5[periodo],$Q$36) -> #REF! | R53: =SUMIFS(Anexo_5[base_imponible_18],Anexo_5[VENTAS KPI],$E$53,Anexo_5[periodo],$R$36)+SUMIFS(#REF!,Anexo_5[VENTAS KPI],$E$53,Anexo_5[periodo],$R$36)+SUMIFS(Anexo_5[base_no_grabada],Anexo_5[VENTAS KPI],$E$53,Anexo_5[periodo],$R$36) -> #REF! | S53: =SUM(G53:R53) -> #REF! | T53: =AVERAGE(G53:R53) -> #REF!
E54: Limpieza de Caja Trampa | F54: Moneda | G54: =SUMIFS(Anexo_5[base_imponible_18],Anexo_5[VENTAS KPI],$E$54,Anexo_5[periodo],$G$36)+SUMIFS(#REF!,Anexo_5[VENTAS KPI],$E$54,Anexo_5[periodo],$G$36)+SUMIFS(Anexo_5[base_no_grabada],Anexo_5[VENTAS KPI],$E$54,Anexo_5[periodo],$G$36) -> #REF! | H54: =SUMIFS(Anexo_5[base_imponible_18],Anexo_5[VENTAS KPI],$E$54,Anexo_5[periodo],$H$36)+SUMIFS(#REF!,Anexo_5[VENTAS KPI],$E$54,Anexo_5[periodo],$H$36)+SUMIFS(Anexo_5[base_no_grabada],Anexo_5[VENTAS KPI],$E$54,Anexo_5[periodo],$H$36) -> #REF! | I54: =SUMIFS(Anexo_5[base_imponible_18],Anexo_5[VENTAS KPI],$E$54,Anexo_5[periodo],$I$36)+SUMIFS(#REF!,Anexo_5[VENTAS KPI],$E$54,Anexo_5[periodo],$I$36)+SUMIFS(Anexo_5[base_no_grabada],Anexo_5[VENTAS KPI],$E$54,Anexo_5[periodo],$I$36) -> #REF! | J54: =SUMIFS(Anexo_5[base_imponible_18],Anexo_5[VENTAS KPI],$E$54,Anexo_5[periodo],$J$36)+SUMIFS(#REF!,Anexo_5[VENTAS KPI],$E$54,Anexo_5[periodo],$J$36)+SUMIFS(Anexo_5[base_no_grabada],Anexo_5[VENTAS KPI],$E$54,Anexo_5[periodo],$J$36) -> #REF! | K54: =SUMIFS(Anexo_5[base_imponible_18],Anexo_5[VENTAS KPI],$E$54,Anexo_5[periodo],$K$36)+SUMIFS(#REF!,Anexo_5[VENTAS KPI],$E$54,Anexo_5[periodo],$K$36)+SUMIFS(Anexo_5[base_no_grabada],Anexo_5[VENTAS KPI],$E$54,Anexo_5[periodo],$K$36) -> #REF! | L54: =SUMIFS(Anexo_5[base_imponible_18],Anexo_5[VENTAS KPI],$E$54,Anexo_5[periodo],$L$36)+SUMIFS(#REF!,Anexo_5[VENTAS KPI],$E$54,Anexo_5[periodo],$L$36)+SUMIFS(Anexo_5[base_no_grabada],Anexo_5[VENTAS KPI],$E$54,Anexo_5[periodo],$L$36) -> #REF! | M54: =SUMIFS(Anexo_5[base_imponible_18],Anexo_5[VENTAS KPI],$E$54,Anexo_5[periodo],$M$36)+SUMIFS(#REF!,Anexo_5[VENTAS KPI],$E$54,Anexo_5[periodo],$M$36)+SUMIFS(Anexo_5[base_no_grabada],Anexo_5[VENTAS KPI],$E$54,Anexo_5[periodo],$M$36) -> #REF! | N54: =SUMIFS(Anexo_5[base_imponible_18],Anexo_5[VENTAS KPI],$E$54,Anexo_5[periodo],$N$36)+SUMIFS(#REF!,Anexo_5[VENTAS KPI],$E$54,Anexo_5[periodo],$N$36)+SUMIFS(Anexo_5[base_no_grabada],Anexo_5[VENTAS KPI],$E$54,Anexo_5[periodo],$N$36) -> #REF! | O54: =SUMIFS(Anexo_5[base_imponible_18],Anexo_5[VENTAS KPI],$E$54,Anexo_5[periodo],$O$36)+SUMIFS(#REF!,Anexo_5[VENTAS KPI],$E$54,Anexo_5[periodo],$O$36)+SUMIFS(Anexo_5[base_no_grabada],Anexo_5[VENTAS KPI],$E$54,Anexo_5[periodo],$O$36) -> #REF! | P54: =SUMIFS(Anexo_5[base_imponible_18],Anexo_5[VENTAS KPI],$E$54,Anexo_5[periodo],$P$36)+SUMIFS(#REF!,Anexo_5[VENTAS KPI],$E$54,Anexo_5[periodo],$P$36)+SUMIFS(Anexo_5[base_no_grabada],Anexo_5[VENTAS KPI],$E$54,Anexo_5[periodo],$P$36) -> #REF! | Q54: =SUMIFS(Anexo_5[base_imponible_18],Anexo_5[VENTAS KPI],$E$54,Anexo_5[periodo],$Q$36)+SUMIFS(#REF!,Anexo_5[VENTAS KPI],$E$54,Anexo_5[periodo],$Q$36)+SUMIFS(Anexo_5[base_no_grabada],Anexo_5[VENTAS KPI],$E$54,Anexo_5[periodo],$Q$36) -> #REF! | R54: =SUMIFS(Anexo_5[base_imponible_18],Anexo_5[VENTAS KPI],$E$54,Anexo_5[periodo],$R$36)+SUMIFS(#REF!,Anexo_5[VENTAS KPI],$E$54,Anexo_5[periodo],$R$36)+SUMIFS(Anexo_5[base_no_grabada],Anexo_5[VENTAS KPI],$E$54,Anexo_5[periodo],$R$36) -> #REF! | S54: =SUM(G54:R54) -> #REF! | T54: =AVERAGE(G54:R54) -> #REF!
E55: Limpieza de Biodigestores | F55: Moneda | G55: =SUMIFS(Anexo_5[base_imponible_18],Anexo_5[VENTAS KPI],$E$55,Anexo_5[periodo],$G$36)+SUMIFS(#REF!,Anexo_5[VENTAS KPI],$E$55,Anexo_5[periodo],$G$36)+SUMIFS(Anexo_5[base_no_grabada],Anexo_5[VENTAS KPI],$E$55,Anexo_5[periodo],$G$36) -> #REF! | H55: =SUMIFS(Anexo_5[base_imponible_18],Anexo_5[VENTAS KPI],$E$55,Anexo_5[periodo],$H$36)+SUMIFS(#REF!,Anexo_5[VENTAS KPI],$E$55,Anexo_5[periodo],$H$36)+SUMIFS(Anexo_5[base_no_grabada],Anexo_5[VENTAS KPI],$E$55,Anexo_5[periodo],$H$36) -> #REF! | I55: =SUMIFS(Anexo_5[base_imponible_18],Anexo_5[VENTAS KPI],$E$55,Anexo_5[periodo],$I$36)+SUMIFS(#REF!,Anexo_5[VENTAS KPI],$E$55,Anexo_5[periodo],$I$36)+SUMIFS(Anexo_5[base_no_grabada],Anexo_5[VENTAS KPI],$E$55,Anexo_5[periodo],$I$36) -> #REF! | J55: =SUMIFS(Anexo_5[base_imponible_18],Anexo_5[VENTAS KPI],$E$55,Anexo_5[periodo],$J$36)+SUMIFS(#REF!,Anexo_5[VENTAS KPI],$E$55,Anexo_5[periodo],$J$36)+SUMIFS(Anexo_5[base_no_grabada],Anexo_5[VENTAS KPI],$E$55,Anexo_5[periodo],$J$36) -> #REF! | K55: =SUMIFS(Anexo_5[base_imponible_18],Anexo_5[VENTAS KPI],$E$55,Anexo_5[periodo],$K$36)+SUMIFS(#REF!,Anexo_5[VENTAS KPI],$E$55,Anexo_5[periodo],$K$36)+SUMIFS(Anexo_5[base_no_grabada],Anexo_5[VENTAS KPI],$E$55,Anexo_5[periodo],$K$36) -> #REF! | L55: =SUMIFS(Anexo_5[base_imponible_18],Anexo_5[VENTAS KPI],$E$55,Anexo_5[periodo],$L$36)+SUMIFS(#REF!,Anexo_5[VENTAS KPI],$E$55,Anexo_5[periodo],$L$36)+SUMIFS(Anexo_5[base_no_grabada],Anexo_5[VENTAS KPI],$E$55,Anexo_5[periodo],$L$36) -> #REF! | M55: =SUMIFS(Anexo_5[base_imponible_18],Anexo_5[VENTAS KPI],$E$55,Anexo_5[periodo],$M$36)+SUMIFS(#REF!,Anexo_5[VENTAS KPI],$E$55,Anexo_5[periodo],$M$36)+SUMIFS(Anexo_5[base_no_grabada],Anexo_5[VENTAS KPI],$E$55,Anexo_5[periodo],$M$36) -> #REF! | N55: =SUMIFS(Anexo_5[base_imponible_18],Anexo_5[VENTAS KPI],$E$55,Anexo_5[periodo],$N$36)+SUMIFS(#REF!,Anexo_5[VENTAS KPI],$E$55,Anexo_5[periodo],$N$36)+SUMIFS(Anexo_5[base_no_grabada],Anexo_5[VENTAS KPI],$E$55,Anexo_5[periodo],$N$36) -> #REF! | O55: =SUMIFS(Anexo_5[base_imponible_18],Anexo_5[VENTAS KPI],$E$55,Anexo_5[periodo],$O$36)+SUMIFS(#REF!,Anexo_5[VENTAS KPI],$E$55,Anexo_5[periodo],$O$36)+SUMIFS(Anexo_5[base_no_grabada],Anexo_5[VENTAS KPI],$E$55,Anexo_5[periodo],$O$36) -> #REF! | P55: =SUMIFS(Anexo_5[base_imponible_18],Anexo_5[VENTAS KPI],$E$55,Anexo_5[periodo],$P$36)+SUMIFS(#REF!,Anexo_5[VENTAS KPI],$E$55,Anexo_5[periodo],$P$36)+SUMIFS(Anexo_5[base_no_grabada],Anexo_5[VENTAS KPI],$E$55,Anexo_5[periodo],$P$36) -> #REF! | Q55: =SUMIFS(Anexo_5[base_imponible_18],Anexo_5[VENTAS KPI],$E$55,Anexo_5[periodo],$Q$36)+SUMIFS(#REF!,Anexo_5[VENTAS KPI],$E$55,Anexo_5[periodo],$Q$36)+SUMIFS(Anexo_5[base_no_grabada],Anexo_5[VENTAS KPI],$E$55,Anexo_5[periodo],$Q$36) -> #REF! | R55: =SUMIFS(Anexo_5[base_imponible_18],Anexo_5[VENTAS KPI],$E$55,Anexo_5[periodo],$R$36)+SUMIFS(#REF!,Anexo_5[VENTAS KPI],$E$55,Anexo_5[periodo],$R$36)+SUMIFS(Anexo_5[base_no_grabada],Anexo_5[VENTAS KPI],$E$55,Anexo_5[periodo],$R$36) -> #REF! | S55: =SUM(G55:R55) -> #REF! | T55: =AVERAGE(G55:R55) -> #REF!
E56: Destrucción de merma y desmedro | F56: Moneda | G56: =SUMIFS(Anexo_5[base_imponible_18],Anexo_5[VENTAS KPI],$E$56,Anexo_5[periodo],$G$36)+SUMIFS(#REF!,Anexo_5[VENTAS KPI],$E$56,Anexo_5[periodo],$G$36)+SUMIFS(Anexo_5[base_no_grabada],Anexo_5[VENTAS KPI],$E$56,Anexo_5[periodo],$G$36) -> #REF! | H56: =SUMIFS(Anexo_5[base_imponible_18],Anexo_5[VENTAS KPI],$E$56,Anexo_5[periodo],$H$36)+SUMIFS(#REF!,Anexo_5[VENTAS KPI],$E$56,Anexo_5[periodo],$H$36)+SUMIFS(Anexo_5[base_no_grabada],Anexo_5[VENTAS KPI],$E$56,Anexo_5[periodo],$H$36) -> #REF! | I56: =SUMIFS(Anexo_5[base_imponible_18],Anexo_5[VENTAS KPI],$E$56,Anexo_5[periodo],$I$36)+SUMIFS(#REF!,Anexo_5[VENTAS KPI],$E$56,Anexo_5[periodo],$I$36)+SUMIFS(Anexo_5[base_no_grabada],Anexo_5[VENTAS KPI],$E$56,Anexo_5[periodo],$I$36) -> #REF! | J56: =SUMIFS(Anexo_5[base_imponible_18],Anexo_5[VENTAS KPI],$E$56,Anexo_5[periodo],$J$36)+SUMIFS(#REF!,Anexo_5[VENTAS KPI],$E$56,Anexo_5[periodo],$J$36)+SUMIFS(Anexo_5[base_no_grabada],Anexo_5[VENTAS KPI],$E$56,Anexo_5[periodo],$J$36) -> #REF! | K56: =SUMIFS(Anexo_5[base_imponible_18],Anexo_5[VENTAS KPI],$E$56,Anexo_5[periodo],$K$36)+SUMIFS(#REF!,Anexo_5[VENTAS KPI],$E$56,Anexo_5[periodo],$K$36)+SUMIFS(Anexo_5[base_no_grabada],Anexo_5[VENTAS KPI],$E$56,Anexo_5[periodo],$K$36) -> #REF! | L56: =SUMIFS(Anexo_5[base_imponible_18],Anexo_5[VENTAS KPI],$E$56,Anexo_5[periodo],$L$36)+SUMIFS(#REF!,Anexo_5[VENTAS KPI],$E$56,Anexo_5[periodo],$L$36)+SUMIFS(Anexo_5[base_no_grabada],Anexo_5[VENTAS KPI],$E$56,Anexo_5[periodo],$L$36) -> #REF! | M56: =SUMIFS(Anexo_5[base_imponible_18],Anexo_5[VENTAS KPI],$E$56,Anexo_5[periodo],$M$36)+SUMIFS(#REF!,Anexo_5[VENTAS KPI],$E$56,Anexo_5[periodo],$M$36)+SUMIFS(Anexo_5[base_no_grabada],Anexo_5[VENTAS KPI],$E$56,Anexo_5[periodo],$M$36) -> #REF! | N56: =SUMIFS(Anexo_5[base_imponible_18],Anexo_5[VENTAS KPI],$E$56,Anexo_5[periodo],$N$36)+SUMIFS(#REF!,Anexo_5[VENTAS KPI],$E$56,Anexo_5[periodo],$N$36)+SUMIFS(Anexo_5[base_no_grabada],Anexo_5[VENTAS KPI],$E$56,Anexo_5[periodo],$N$36) -> #REF! | O56: =SUMIFS(Anexo_5[base_imponible_18],Anexo_5[VENTAS KPI],$E$56,Anexo_5[periodo],$O$36)+SUMIFS(#REF!,Anexo_5[VENTAS KPI],$E$56,Anexo_5[periodo],$O$36)+SUMIFS(Anexo_5[base_no_grabada],Anexo_5[VENTAS KPI],$E$56,Anexo_5[periodo],$O$36) -> #REF! | P56: =SUMIFS(Anexo_5[base_imponible_18],Anexo_5[VENTAS KPI],$E$56,Anexo_5[periodo],$P$36)+SUMIFS(#REF!,Anexo_5[VENTAS KPI],$E$56,Anexo_5[periodo],$P$36)+SUMIFS(Anexo_5[base_no_grabada],Anexo_5[VENTAS KPI],$E$56,Anexo_5[periodo],$P$36) -> #REF! | Q56: =SUMIFS(Anexo_5[base_imponible_18],Anexo_5[VENTAS KPI],$E$56,Anexo_5[periodo],$Q$36)+SUMIFS(#REF!,Anexo_5[VENTAS KPI],$E$56,Anexo_5[periodo],$Q$36)+SUMIFS(Anexo_5[base_no_grabada],Anexo_5[VENTAS KPI],$E$56,Anexo_5[periodo],$Q$36) -> #REF! | R56: =SUMIFS(Anexo_5[base_imponible_18],Anexo_5[VENTAS KPI],$E$56,Anexo_5[periodo],$R$36)+SUMIFS(#REF!,Anexo_5[VENTAS KPI],$E$56,Anexo_5[periodo],$R$36)+SUMIFS(Anexo_5[base_no_grabada],Anexo_5[VENTAS KPI],$E$56,Anexo_5[periodo],$R$36) -> #REF! | S56: =SUM(G56:R56) -> #REF! | T56: =AVERAGE(G56:R56) -> #REF!
E57: Transporte de Carga - Local | F57: Moneda | G57: =SUMIFS(Anexo_5[base_imponible_18],Anexo_5[VENTAS KPI],$E$57,Anexo_5[periodo],$G$36)+SUMIFS(#REF!,Anexo_5[VENTAS KPI],$E$57,Anexo_5[periodo],$G$36)+SUMIFS(Anexo_5[base_no_grabada],Anexo_5[VENTAS KPI],$E$57,Anexo_5[periodo],$G$36) -> #REF! | H57: =SUMIFS(Anexo_5[base_imponible_18],Anexo_5[VENTAS KPI],$E$57,Anexo_5[periodo],$H$36)+SUMIFS(#REF!,Anexo_5[VENTAS KPI],$E$57,Anexo_5[periodo],$H$36)+SUMIFS(Anexo_5[base_no_grabada],Anexo_5[VENTAS KPI],$E$57,Anexo_5[periodo],$H$36) -> #REF! | I57: =SUMIFS(Anexo_5[base_imponible_18],Anexo_5[VENTAS KPI],$E$57,Anexo_5[periodo],$I$36)+SUMIFS(#REF!,Anexo_5[VENTAS KPI],$E$57,Anexo_5[periodo],$I$36)+SUMIFS(Anexo_5[base_no_grabada],Anexo_5[VENTAS KPI],$E$57,Anexo_5[periodo],$I$36) -> #REF! | J57: =SUMIFS(Anexo_5[base_imponible_18],Anexo_5[VENTAS KPI],$E$57,Anexo_5[periodo],$J$36)+SUMIFS(#REF!,Anexo_5[VENTAS KPI],$E$57,Anexo_5[periodo],$J$36)+SUMIFS(Anexo_5[base_no_grabada],Anexo_5[VENTAS KPI],$E$57,Anexo_5[periodo],$J$36) -> #REF! | K57: =SUMIFS(Anexo_5[base_imponible_18],Anexo_5[VENTAS KPI],$E$57,Anexo_5[periodo],$K$36)+SUMIFS(#REF!,Anexo_5[VENTAS KPI],$E$57,Anexo_5[periodo],$K$36)+SUMIFS(Anexo_5[base_no_grabada],Anexo_5[VENTAS KPI],$E$57,Anexo_5[periodo],$K$36) -> #REF! | L57: =SUMIFS(Anexo_5[base_imponible_18],Anexo_5[VENTAS KPI],$E$57,Anexo_5[periodo],$L$36)+SUMIFS(#REF!,Anexo_5[VENTAS KPI],$E$57,Anexo_5[periodo],$L$36)+SUMIFS(Anexo_5[base_no_grabada],Anexo_5[VENTAS KPI],$E$57,Anexo_5[periodo],$L$36) -> #REF! | M57: =SUMIFS(Anexo_5[base_imponible_18],Anexo_5[VENTAS KPI],$E$57,Anexo_5[periodo],$M$36)+SUMIFS(#REF!,Anexo_5[VENTAS KPI],$E$57,Anexo_5[periodo],$M$36)+SUMIFS(Anexo_5[base_no_grabada],Anexo_5[VENTAS KPI],$E$57,Anexo_5[periodo],$M$36) -> #REF! | N57: =SUMIFS(Anexo_5[base_imponible_18],Anexo_5[VENTAS KPI],$E$57,Anexo_5[periodo],$N$36)+SUMIFS(#REF!,Anexo_5[VENTAS KPI],$E$57,Anexo_5[periodo],$N$36)+SUMIFS(Anexo_5[base_no_grabada],Anexo_5[VENTAS KPI],$E$57,Anexo_5[periodo],$N$36) -> #REF! | O57: =SUMIFS(Anexo_5[base_imponible_18],Anexo_5[VENTAS KPI],$E$57,Anexo_5[periodo],$O$36)+SUMIFS(#REF!,Anexo_5[VENTAS KPI],$E$57,Anexo_5[periodo],$O$36)+SUMIFS(Anexo_5[base_no_grabada],Anexo_5[VENTAS KPI],$E$57,Anexo_5[periodo],$O$36) -> #REF! | P57: =SUMIFS(Anexo_5[base_imponible_18],Anexo_5[VENTAS KPI],$E$57,Anexo_5[periodo],$P$36)+SUMIFS(#REF!,Anexo_5[VENTAS KPI],$E$57,Anexo_5[periodo],$P$36)+SUMIFS(Anexo_5[base_no_grabada],Anexo_5[VENTAS KPI],$E$57,Anexo_5[periodo],$P$36) -> #REF! | Q57: =SUMIFS(Anexo_5[base_imponible_18],Anexo_5[VENTAS KPI],$E$57,Anexo_5[periodo],$Q$36)+SUMIFS(#REF!,Anexo_5[VENTAS KPI],$E$57,Anexo_5[periodo],$Q$36)+SUMIFS(Anexo_5[base_no_grabada],Anexo_5[VENTAS KPI],$E$57,Anexo_5[periodo],$Q$36) -> #REF! | R57: =SUMIFS(Anexo_5[base_imponible_18],Anexo_5[VENTAS KPI],$E$57,Anexo_5[periodo],$R$36)+SUMIFS(#REF!,Anexo_5[VENTAS KPI],$E$57,Anexo_5[periodo],$R$36)+SUMIFS(Anexo_5[base_no_grabada],Anexo_5[VENTAS KPI],$E$57,Anexo_5[periodo],$R$36) -> #REF! | S57: =SUM(G57:R57) -> #REF! | T57: =AVERAGE(G57:R57) -> #REF!
E58: Transporte de Carga - Nacional | F58: Moneda | G58: =SUMIFS(Anexo_5[base_imponible_18],Anexo_5[VENTAS KPI],$E$58,Anexo_5[periodo],$G$36)+SUMIFS(#REF!,Anexo_5[VENTAS KPI],$E$58,Anexo_5[periodo],$G$36)+SUMIFS(Anexo_5[base_no_grabada],Anexo_5[VENTAS KPI],$E$58,Anexo_5[periodo],$G$36) -> #REF! | H58: =SUMIFS(Anexo_5[base_imponible_18],Anexo_5[VENTAS KPI],$E$58,Anexo_5[periodo],$H$36)+SUMIFS(#REF!,Anexo_5[VENTAS KPI],$E$58,Anexo_5[periodo],$H$36)+SUMIFS(Anexo_5[base_no_grabada],Anexo_5[VENTAS KPI],$E$58,Anexo_5[periodo],$H$36) -> #REF! | I58: =SUMIFS(Anexo_5[base_imponible_18],Anexo_5[VENTAS KPI],$E$58,Anexo_5[periodo],$I$36)+SUMIFS(#REF!,Anexo_5[VENTAS KPI],$E$58,Anexo_5[periodo],$I$36)+SUMIFS(Anexo_5[base_no_grabada],Anexo_5[VENTAS KPI],$E$58,Anexo_5[periodo],$I$36) -> #REF! | J58: =SUMIFS(Anexo_5[base_imponible_18],Anexo_5[VENTAS KPI],$E$58,Anexo_5[periodo],$J$36)+SUMIFS(#REF!,Anexo_5[VENTAS KPI],$E$58,Anexo_5[periodo],$J$36)+SUMIFS(Anexo_5[base_no_grabada],Anexo_5[VENTAS KPI],$E$58,Anexo_5[periodo],$J$36) -> #REF! | K58: =SUMIFS(Anexo_5[base_imponible_18],Anexo_5[VENTAS KPI],$E$58,Anexo_5[periodo],$K$36)+SUMIFS(#REF!,Anexo_5[VENTAS KPI],$E$58,Anexo_5[periodo],$K$36)+SUMIFS(Anexo_5[base_no_grabada],Anexo_5[VENTAS KPI],$E$58,Anexo_5[periodo],$K$36) -> #REF! | L58: =SUMIFS(Anexo_5[base_imponible_18],Anexo_5[VENTAS KPI],$E$58,Anexo_5[periodo],$L$36)+SUMIFS(#REF!,Anexo_5[VENTAS KPI],$E$58,Anexo_5[periodo],$L$36)+SUMIFS(Anexo_5[base_no_grabada],Anexo_5[VENTAS KPI],$E$58,Anexo_5[periodo],$L$36) -> #REF! | M58: =SUMIFS(Anexo_5[base_imponible_18],Anexo_5[VENTAS KPI],$E$58,Anexo_5[periodo],$M$36)+SUMIFS(#REF!,Anexo_5[VENTAS KPI],$E$58,Anexo_5[periodo],$M$36)+SUMIFS(Anexo_5[base_no_grabada],Anexo_5[VENTAS KPI],$E$58,Anexo_5[periodo],$M$36) -> #REF! | N58: =SUMIFS(Anexo_5[base_imponible_18],Anexo_5[VENTAS KPI],$E$58,Anexo_5[periodo],$N$36)+SUMIFS(#REF!,Anexo_5[VENTAS KPI],$E$58,Anexo_5[periodo],$N$36)+SUMIFS(Anexo_5[base_no_grabada],Anexo_5[VENTAS KPI],$E$58,Anexo_5[periodo],$N$36) -> #REF! | O58: =SUMIFS(Anexo_5[base_imponible_18],Anexo_5[VENTAS KPI],$E$58,Anexo_5[periodo],$O$36)+SUMIFS(#REF!,Anexo_5[VENTAS KPI],$E$58,Anexo_5[periodo],$O$36)+SUMIFS(Anexo_5[base_no_grabada],Anexo_5[VENTAS KPI],$E$58,Anexo_5[periodo],$O$36) -> #REF! | P58: =SUMIFS(Anexo_5[base_imponible_18],Anexo_5[VENTAS KPI],$E$58,Anexo_5[periodo],$P$36)+SUMIFS(#REF!,Anexo_5[VENTAS KPI],$E$58,Anexo_5[periodo],$P$36)+SUMIFS(Anexo_5[base_no_grabada],Anexo_5[VENTAS KPI],$E$58,Anexo_5[periodo],$P$36) -> #REF! | Q58: =SUMIFS(Anexo_5[base_imponible_18],Anexo_5[VENTAS KPI],$E$58,Anexo_5[periodo],$Q$36)+SUMIFS(#REF!,Anexo_5[VENTAS KPI],$E$58,Anexo_5[periodo],$Q$36)+SUMIFS(Anexo_5[base_no_grabada],Anexo_5[VENTAS KPI],$E$58,Anexo_5[periodo],$Q$36) -> #REF! | R58: =SUMIFS(Anexo_5[base_imponible_18],Anexo_5[VENTAS KPI],$E$58,Anexo_5[periodo],$R$36)+SUMIFS(#REF!,Anexo_5[VENTAS KPI],$E$58,Anexo_5[periodo],$R$36)+SUMIFS(Anexo_5[base_no_grabada],Anexo_5[VENTAS KPI],$E$58,Anexo_5[periodo],$R$36) -> #REF! | S58: =SUM(G58:R58) -> #REF! | T58: =AVERAGE(G58:R58) -> #REF!
E59: TOTAL SERVICIOS FACTURADOS | F59: Moneda | G59: =SUM(G49:G58) -> #REF! | H59: =SUM(H49:H58) -> #REF! | I59: =SUM(I49:I58) -> #REF! | J59: =SUM(J49:J58) -> #REF! | K59: =SUM(K49:K58) -> #REF! | L59: =SUM(L49:L58) -> #REF! | M59: =SUM(M49:M58) -> #REF! | N59: =SUM(N49:N58) -> #REF! | ... T59: =SUM(T49:T58) -> #REF!
E60: % SOBRE LA VENTA TOTAL | F60: % | G60: =IF(G61=0,0,((100%-G47))) -> #REF! | H60: =IF(H61=0,0,((100%-H47))) -> #REF! | I60: =IF(I61=0,0,((100%-I47))) -> #REF! | J60: =IF(J61=0,0,((100%-J47))) -> #REF! | K60: =IF(K61=0,0,((100%-K47))) -> #REF! | L60: =IF(L61=0,0,((100%-L47))) -> #REF! | M60: =IF(M61=0,0,((100%-M47))) -> #REF! | N60: =IF(N61=0,0,((100%-N47))) -> #REF! | ... T60: =IF(T61=0,0,((100%-T47))) -> #REF!
B61: TOTAL | G61: =G46+G59 -> #REF! | H61: =H46+H59 -> #REF! | I61: =I46+I59 -> #REF! | J61: =J46+J59 -> #REF! | K61: =K46+K59 -> #REF! | L61: =L46+L59 -> #REF! | M61: =M46+M59 -> #REF! | N61: =N46+N59 -> #REF! | ... T61: =T46+T59 -> #REF!

Sheet DETALLE GASTOS FIJOS Y VARIABLE
D2: FORMATO ADMINISTRATIVO DE GESTION | R2: COD: S/N
D3: INDICADORES DE GESTION - GASTOS VARIABLES Y GASTOS OPERATIVOS FIJOS | R3: VERSIÓN:01
R4: AREÁ: Gerencia
D5: CONTABILIDAD | R5: =TODAY() -> 45979
B7: KPI | C7: CONCEPTO | D7: DETALLE | E7: MEDIDA | F7: ENERO | G7: FEBRERO | H7: MARZO | I7: ABRIL | J7: MAYO | K7: JUNIO | L7: JULIO | M7: AGOSTO | N7: SETIEMBRE | O7: OCTUBRE | P7: NOVIEMBRE | Q7: DICIEMBRE | R7: TOTAL | S7: PROMEDIO
C8: GASTOS VARIABLES | D8: Transporte de Personal | E8: Moneda | F8: =SUMIFS(Anexo_4[base_imponible_18],Anexo_4[gastos_operativos_kpi],$D$8,Anexo_4[periodo],$F$7)+SUMIFS(Anexo_4[base_imponible_10],Anexo_4[gastos_operativos_kpi],$D$8,Anexo_4[periodo],$F$7) -> 0 | G8: =SUMIFS(Anexo_4[base_imponible_18],Anexo_4[gastos_operativos_kpi],$D$8,Anexo_4[periodo],$G$7)+SUMIFS(Anexo_4[base_imponible_10],Anexo_4[gastos_operativos_kpi],$D$8,Anexo_4[periodo],$G$7) -> 0 | H8: =SUMIFS(Anexo_4[base_imponible_18],Anexo_4[gastos_operativos_kpi],$D$8,Anexo_4[periodo],$H$7)+SUMIFS(Anexo_4[base_imponible_10],Anexo_4[gastos_operativos_kpi],$D$8,Anexo_4[periodo],$H$7) -> 0 | I8: =SUMIFS(Anexo_4[base_imponible_18],Anexo_4[gastos_operativos_kpi],$D$8,Anexo_4[periodo],$I$7)+SUMIFS(Anexo_4[base_imponible_10],Anexo_4[gastos_operativos_kpi],$D$8,Anexo_4[periodo],$I$7) -> 0 | J8: =SUMIFS(Anexo_4[base_imponible_18],Anexo_4[gastos_operativos_kpi],$D$8,Anexo_4[periodo],$J$7)+SUMIFS(Anexo_4[base_imponible_10],Anexo_4[gastos_operativos_kpi],$D$8,Anexo_4[periodo],$J$7) -> 0 | K8: =SUMIFS(Anexo_4[base_imponible_18],Anexo_4[gastos_operativos_kpi],$D$8,Anexo_4[periodo],$K$7)+SUMIFS(Anexo_4[base_imponible_10],Anexo_4[gastos_operativos_kpi],$D$8,Anexo_4[periodo],$K$7) -> 33.9 | L8: =SUMIFS(Anexo_4[base_imponible_18],Anexo_4[gastos_operativos_kpi],$D$8,Anexo_4[periodo],$L$7)+SUMIFS(Anexo_4[base_imponible_10],Anexo_4[gastos_operativos_kpi],$D$8,Anexo_4[periodo],$L$7) -> 0 | M8: =SUMIFS(Anexo_4[base_imponible_18],Anexo_4[gastos_operativos_kpi],$D$8,Anexo_4[periodo],$M$7)+SUMIFS(Anexo_4[base_imponible_10],Anexo_4[gastos_operativos_kpi],$D$8,Anexo_4[periodo],$M$7) -> 0 | N8: =SUMIFS(Anexo_4[base_imponible_18],Anexo_4[gastos_operativos_kpi],$D$8,Anexo_4[periodo],$N$7)+SUMIFS(Anexo_4[base_imponible_10],Anexo_4[gastos_operativos_kpi],$D$8,Anexo_4[periodo],$N$7) -> 0 | O8: =SUMIFS(Anexo_4[base_imponible_18],Anexo_4[gastos_operativos_kpi],$D$8,Anexo_4[periodo],$O$7)+SUMIFS(Anexo_4[base_imponible_10],Anexo_4[gastos_operativos_kpi],$D$8,Anexo_4[periodo],$O$7) -> 0 | P8: =SUMIFS(Anexo_4[base_imponible_18],Anexo_4[gastos_operativos_kpi],$D$8,Anexo_4[periodo],$P$7)+SUMIFS(Anexo_4[base_imponible_10],Anexo_4[gastos_operativos_kpi],$D$8,Anexo_4[periodo],$P$7) -> 0 | Q8: =SUMIFS(Anexo_4[base_imponible_18],Anexo_4[gastos_operativos_kpi],$D$8,Anexo_4[periodo],$Q$7)+SUMIFS(Anexo_4[base_imponible_10],Anexo_4[gastos_operativos_kpi],$D$8,Anexo_4[periodo],$Q$7) -> 0 | R8: =SUM(F8:Q8) -> 33.9 | S8: =AVERAGE(F8:Q8) -> 2.825
D9: Transporte de Personal (Viajes) | E9: Moneda | F9: =SUMIFS(Anexo_4[base_imponible_18],Anexo_4[gastos_operativos_kpi],$D$9,Anexo_4[periodo],$F$7)+SUMIFS(Anexo_4[base_imponible_10],Anexo_4[gastos_operativos_kpi],$D$9,Anexo_4[periodo],$F$7) -> 0 | G9: =SUMIFS(Anexo_4[base_imponible_18],Anexo_4[gastos_operativos_kpi],$D$9,Anexo_4[periodo],$G$7)+SUMIFS(Anexo_4[base_imponible_10],Anexo_4[gastos_operativos_kpi],$D$9,Anexo_4[periodo],$G$7) -> 0 | H9: =SUMIFS(Anexo_4[base_imponible_18],Anexo_4[gastos_operativos_kpi],$D$9,Anexo_4[periodo],$H$7)+SUMIFS(Anexo_4[base_imponible_10],Anexo_4[gastos_operativos_kpi],$D$9,Anexo_4[periodo],$H$7) -> 0 | I9: =SUMIFS(Anexo_4[base_imponible_18],Anexo_4[gastos_operativos_kpi],$D$9,Anexo_4[periodo],$I$7)+SUMIFS(Anexo_4[base_imponible_10],Anexo_4[gastos_operativos_kpi],$D$9,Anexo_4[periodo],$I$7) -> 0 | J9: =SUMIFS(Anexo_4[base_imponible_18],Anexo_4[gastos_operativos_kpi],$D$9,Anexo_4[periodo],$J$7)+SUMIFS(Anexo_4[base_imponible_10],Anexo_4[gastos_operativos_kpi],$D$9,Anexo_4[periodo],$J$7) -> 0 | K9: =SUMIFS(Anexo_4[base_imponible_18],Anexo_4[gastos_operativos_kpi],$D$9,Anexo_4[periodo],$K$7)+SUMIFS(Anexo_4[base_imponible_10],Anexo_4[gastos_operativos_kpi],$D$9,Anexo_4[periodo],$K$7) -> 0 | L9: =SUMIFS(Anexo_4[base_imponible_18],Anexo_4[gastos_operativos_kpi],$D$9,Anexo_4[periodo],$L$7)+SUMIFS(Anexo_4[base_imponible_10],Anexo_4[gastos_operativos_kpi],$D$9,Anexo_4[periodo],$L$7) -> 0 | M9: =SUMIFS(Anexo_4[base_imponible_18],Anexo_4[gastos_operativos_kpi],$D$9,Anexo_4[periodo],$M$7)+SUMIFS(Anexo_4[base_imponible_10],Anexo_4[gastos_operativos_kpi],$D$9,Anexo_4[periodo],$M$7) -> 0 | N9: =SUMIFS(Anexo_4[base_imponible_18],Anexo_4[gastos_operativos_kpi],$D$9,Anexo_4[periodo],$N$7)+SUMIFS(Anexo_4[base_imponible_10],Anexo_4[gastos_operativos_kpi],$D$9,Anexo_4[periodo],$N$7) -> 0 | O9: =SUMIFS(Anexo_4[base_imponible_18],Anexo_4[gastos_operativos_kpi],$D$9,Anexo_4[periodo],$O$7)+SUMIFS(Anexo_4[base_imponible_10],Anexo_4[gastos_operativos_kpi],$D$9,Anexo_4[periodo],$O$7) -> 0 | P9: =SUMIFS(Anexo_4[base_imponible_18],Anexo_4[gastos_operativos_kpi],$D$9,Anexo_4[periodo],$P$7)+SUMIFS(Anexo_4[base_imponible_10],Anexo_4[gastos_operativos_kpi],$D$9,Anexo_4[periodo],$P$7) -> 0 | Q9: =SUMIFS(Anexo_4[base_imponible_18],Anexo_4[gastos_operativos_kpi],$D$9,Anexo_4[periodo],$Q$7)+SUMIFS(Anexo_4[base_imponible_10],Anexo_4[gastos_operativos_kpi],$D$9,Anexo_4[periodo],$Q$7) -> 0 | R9: =SUM(F9:Q9) -> 0 | S9: =AVERAGE(F9:Q9) -> 0
D10: Transporte parqueo (Cochera) | E10: Moneda | F10: =SUMIFS(Anexo_4[base_imponible_18],Anexo_4[gastos_operativos_kpi],$D$10,Anexo_4[periodo],$F$7)+SUMIFS(Anexo_4[base_imponible_10],Anexo_4[gastos_operativos_kpi],$D$10,Anexo_4[periodo],$F$7) -> 0 | G10: =SUMIFS(Anexo_4[base_imponible_18],Anexo_4[gastos_operativos_kpi],$D$10,Anexo_4[periodo],$G$7)+SUMIFS(Anexo_4[base_imponible_10],Anexo_4[gastos_operativos_kpi],$D$10,Anexo_4[periodo],$G$7) -> 0 | H10: =SUMIFS(Anexo_4[base_imponible_18],Anexo_4[gastos_operativos_kpi],$D$10,Anexo_4[periodo],$H$7)+SUMIFS(Anexo_4[base_imponible_10],Anexo_4[gastos_operativos_kpi],$D$10,Anexo_4[periodo],$H$7) -> 0 | I10: =SUMIFS(Anexo_4[base_imponible_18],Anexo_4[gastos_operativos_kpi],$D$10,Anexo_4[periodo],$I$7)+SUMIFS(Anexo_4[base_imponible_10],Anexo_4[gastos_operativos_kpi],$D$10,Anexo_4[periodo],$I$7) -> 0 | J10: =SUMIFS(Anexo_4[base_imponible_18],Anexo_4[gastos_operativos_kpi],$D$10,Anexo_4[periodo],$J$7)+SUMIFS(Anexo_4[base_imponible_10],Anexo_4[gastos_operativos_kpi],$D$10,Anexo_4[periodo],$J$7) -> 0 | K10: =SUMIFS(Anexo_4[base_imponible_18],Anexo_4[gastos_operativos_kpi],$D$10,Anexo_4[periodo],$K$7)+SUMIFS(Anexo_4[base_imponible_10],Anexo_4[gastos_operativos_kpi],$D$10,Anexo_4[periodo],$K$7) -> 0 | L10: =SUMIFS(Anexo_4[base_imponible_18],Anexo_4[gastos_operativos_kpi],$D$10,Anexo_4[periodo],$L$7)+SUMIFS(Anexo_4[base_imponible_10],Anexo_4[gastos_operativos_kpi],$D$10,Anexo_4[periodo],$L$7) -> 55.93 | M10: =SUMIFS(Anexo_4[base_imponible_18],Anexo_4[gastos_operativos_kpi],$D$10,Anexo_4[periodo],$M$7)+SUMIFS(Anexo_4[base_imponible_10],Anexo_4[gastos_operativos_kpi],$D$10,Anexo_4[periodo],$M$7) -> 0 | N10: =SUMIFS(Anexo_4[base_imponible_18],Anexo_4[gastos_operativos_kpi],$D$10,Anexo_4[periodo],$N$7)+SUMIFS(Anexo_4[base_imponible_10],Anexo_4[gastos_operativos_kpi],$D$10,Anexo_4[periodo],$N$7) -> 30.59 | O10: =SUMIFS(Anexo_4[base_imponible_18],Anexo_4[gastos_operativos_kpi],$D$10,Anexo_4[periodo],$O$7)+SUMIFS(Anexo_4[base_imponible_10],Anexo_4[gastos_operativos_kpi],$D$10,Anexo_4[periodo],$O$7) -> 0 | P10: =SUMIFS(Anexo_4[base_imponible_18],Anexo_4[gastos_operativos_kpi],$D$10,Anexo_4[periodo],$P$7)+SUMIFS(Anexo_4[base_imponible_10],Anexo_4[gastos_operativos_kpi],$D$10,Anexo_4[periodo],$P$7) -> 0 | Q10: =SUMIFS(Anexo_4[base_imponible_18],Anexo_4[gastos_operativos_kpi],$D$10,Anexo_4[periodo],$Q$7)+SUMIFS(Anexo_4[base_imponible_10],Anexo_4[gastos_operativos_kpi],$D$10,Anexo_4[periodo],$Q$7) -> 0 | R10: =SUM(F10:Q10) -> 86.52 | S10: =AVERAGE(F10:Q10) -> 7.21
D11: Transporte lavado (Higienización) | E11: Moneda | F11: =SUMIFS(Anexo_4[base_imponible_18],Anexo_4[gastos_operativos_kpi],$D$11,Anexo_4[periodo],$F$7)+SUMIFS(Anexo_4[base_imponible_10],Anexo_4[gastos_operativos_kpi],$D$11,Anexo_4[periodo],$F$7) -> 0 | G11: =SUMIFS(Anexo_4[base_imponible_18],Anexo_4[gastos_operativos_kpi],$D$11,Anexo_4[periodo],$G$7)+SUMIFS(Anexo_4[base_imponible_10],Anexo_4[gastos_operativos_kpi],$D$11,Anexo_4[periodo],$G$7) -> 0 | H11: =SUMIFS(Anexo_4[base_imponible_18],Anexo_4[gastos_operativos_kpi],$D$11,Anexo_4[periodo],$H$7)+SUMIFS(Anexo_4[base_imponible_10],Anexo_4[gastos_operativos_kpi],$D$11,Anexo_4[periodo],$H$7) -> 0 | I11: =SUMIFS(Anexo_4[base_imponible_18],Anexo_4[gastos_operativos_kpi],$D$11,Anexo_4[periodo],$I$7)+SUMIFS(Anexo_4[base_imponible_10],Anexo_4[gastos_operativos_kpi],$D$11,Anexo_4[periodo],$I$7) -> 0 | J11: =SUMIFS(Anexo_4[base_imponible_18],Anexo_4[gastos_operativos_kpi],$D$11,Anexo_4[periodo],$J$7)+SUMIFS(Anexo_4[base_imponible_10],Anexo_4[gastos_operativos_kpi],$D$11,Anexo_4[periodo],$J$7) -> 0 | K11: =SUMIFS(Anexo_4[base_imponible_18],Anexo_4[gastos_operativos_kpi],$D$11,Anexo_4[periodo],$K$7)+SUMIFS(Anexo_4[base_imponible_10],Anexo_4[gastos_operativos_kpi],$D$11,Anexo_4[periodo],$K$7) -> 451.7 | L11: =SUMIFS(Anexo_4[base_imponible_18],Anexo_4[gastos_operativos_kpi],$D$11,Anexo_4[periodo],$L$7)+SUMIFS(Anexo_4[base_imponible_10],Anexo_4[gastos_operativos_kpi],$D$11,Anexo_4[periodo],$L$7) -> 470.34 | M11: =SUMIFS(Anexo_4[base_imponible_18],Anexo_4[gastos_operativos_kpi],$D$11,Anexo_4[periodo],$M$7)+SUMIFS(Anexo_4[base_imponible_10],Anexo_4[gastos_operativos_kpi],$D$11,Anexo_4[periodo],$M$7) -> 242.48 | N11: =SUMIFS(Anexo_4[base_imponible_18],Anexo_4[gastos_operativos_kpi],$D$11,Anexo_4[periodo],$N$7)+SUMIFS(Anexo_4[base_imponible_10],Anexo_4[gastos_operativos_kpi],$D$11,Anexo_4[periodo],$N$7) -> 415.26 | O11: =SUMIFS(Anexo_4[base_imponible_18],Anexo_4[gastos_operativos_kpi],$D$11,Anexo_4[periodo],$O$7)+SUMIFS(Anexo_4[base_imponible_10],Anexo_4[gastos_operativos_kpi],$D$11,Anexo_4[periodo],$O$7) -> 0 | P11: =SUMIFS(Anexo_4[base_imponible_18],Anexo_4[gastos_operativos_kpi],$D$11,Anexo_4[periodo],$P$7)+SUMIFS(Anexo_4[base_imponible_10],Anexo_4[gastos_operativos_kpi],$D$11,Anexo_4[periodo],$P$7) -> 0 | Q11: =SUMIFS(Anexo_4[base_imponible_18],Anexo_4[gastos_operativos_kpi],$D$11,Anexo_4[periodo],$Q$7)+SUMIFS(Anexo_4[base_imponible_10],Anexo_4[gastos_operativos_kpi],$D$11,Anexo_4[periodo],$Q$7) -> 0 | R11: =SUM(F11:Q11) -> 1579.78 | S11: =AVERAGE(F11:Q11) -> 131.64833
D12: Encomienda (Envío de documentación) | E12: Moneda | F12: =SUMIFS(Anexo_4[base_imponible_18],Anexo_4[gastos_operativos_kpi],$D$12,Anexo_4[periodo],$F$7)+SUMIFS(Anexo_4[base_imponible_10],Anexo_4[gastos_operativos_kpi],$D$12,Anexo_4[periodo],$F$7) -> 0 | G12: =SUMIFS(Anexo_4[base_imponible_18],Anexo_4[gastos_operativos_kpi],$D$12,Anexo_4[periodo],$G$7)+SUMIFS(Anexo_4[base_imponible_10],Anexo_4[gastos_operativos_kpi],$D$12,Anexo_4[periodo],$G$7) -> 0 | H12: =SUMIFS(Anexo_4[base_imponible_18],Anexo_4[gastos_operativos_kpi],$D$12,Anexo_4[periodo],$H$7)+SUMIFS(Anexo_4[base_imponible_10],Anexo_4[gastos_operativos_kpi],$D$12,Anexo_4[periodo],$H$7) -> 0 | I12: =SUMIFS(Anexo_4[base_imponible_18],Anexo_4[gastos_operativos_kpi],$D$12,Anexo_4[periodo],$I$7)+SUMIFS(Anexo_4[base_imponible_10],Anexo_4[gastos_operativos_kpi],$D$12,Anexo_4[periodo],$I$7) -> 0 | J12: =SUMIFS(Anexo_4[base_imponible_18],Anexo_4[gastos_operativos_kpi],$D$12,Anexo_4[periodo],$J$7)+SUMIFS(Anexo_4[base_imponible_10],Anexo_4[gastos_operativos_kpi],$D$12,Anexo_4[periodo],$J$7) -> 0 | K12: =SUMIFS(Anexo_4[base_imponible_18],Anexo_4[gastos_operativos_kpi],$D$12,Anexo_4[periodo],$K$7)+SUMIFS(Anexo_4[base_imponible_10],Anexo_4[gastos_operativos_kpi],$D$12,Anexo_4[periodo],$K$7) -> 140.67 | L12: =SUMIFS(Anexo_4[base_imponible_18],Anexo_4[gastos_operativos_kpi],$D$12,Anexo_4[periodo],$L$7)+SUMIFS(Anexo_4[base_imponible_10],Anexo_4[gastos_operativos_kpi],$D$12,Anexo_4[periodo],$L$7) -> 194.23 | M12: =SUMIFS(Anexo_4[base_imponible_18],Anexo_4[gastos_operativos_kpi],$D$12,Anexo_4[periodo],$M$7)+SUMIFS(Anexo_4[base_imponible_10],Anexo_4[gastos_operativos_kpi],$D$12,Anexo_4[periodo],$M$7) -> 74.57 | N12: =SUMIFS(Anexo_4[base_imponible_18],Anexo_4[gastos_operativos_kpi],$D$12,Anexo_4[periodo],$N$7)+SUMIFS(Anexo_4[base_imponible_10],Anexo_4[gastos_operativos_kpi],$D$12,Anexo_4[periodo],$N$7) -> 34.74 | O12: =SUMIFS(Anexo_4[base_imponible_18],Anexo_4[gastos_operativos_kpi],$D$12,Anexo_4[periodo],$O$7)+SUMIFS(Anexo_4[base_imponible_10],Anexo_4[gastos_operativos_kpi],$D$12,Anexo_4[periodo],$O$7) -> 0 | P12: =SUMIFS(Anexo_4[base_imponible_18],Anexo_4[gastos_operativos_kpi],$D$12,Anexo_4[periodo],$P$7)+SUMIFS(Anexo_4[base_imponible_10],Anexo_4[gastos_operativos_kpi],$D$12,Anexo_4[periodo],$P$7) -> 0 | Q12: =SUMIFS(Anexo_4[base_imponible_18],Anexo_4[gastos_operativos_kpi],$D$12,Anexo_4[periodo],$Q$7)+SUMIFS(Anexo_4[base_imponible_10],Anexo_4[gastos_operativos_kpi],$D$12,Anexo_4[periodo],$Q$7) -> 0 | R12: =SUM(F12:Q12) -> 444.21 | S12: =AVERAGE(F12:Q12) -> 37.0175
D13: Alojamiento (Operativo) | E13: Moneda | F13: =SUMIFS(Anexo_4[base_imponible_18],Anexo_4[gastos_operativos_kpi],$D$13,Anexo_4[periodo],$F$7)+SUMIFS(Anexo_4[base_imponible_10],Anexo_4[gastos_operativos_kpi],$D$13,Anexo_4[periodo],$F$7) -> 0 | G13: =SUMIFS(Anexo_4[base_imponible_18],Anexo_4[gastos_operativos_kpi],$D$13,Anexo_4[periodo],$G$7)+SUMIFS(Anexo_4[base_imponible_10],Anexo_4[gastos_operativos_kpi],$D$13,Anexo_4[periodo],$G$7) -> 0 | H13: =SUMIFS(Anexo_4[base_imponible_18],Anexo_4[gastos_operativos_kpi],$D$13,Anexo_4[periodo],$H$7)+SUMIFS(Anexo_4[base_imponible_10],Anexo_4[gastos_operativos_kpi],$D$13,Anexo_4[periodo],$H$7) -> 0 | I13: =SUMIFS(Anexo_4[base_imponible_18],Anexo_4[gastos_operativos_kpi],$D$13,Anexo_4[periodo],$I$7)+SUMIFS(Anexo_4[base_imponible_10],Anexo_4[gastos_operativos_kpi],$D$13,Anexo_4[periodo],$I$7) -> 0 | J13: =SUMIFS(Anexo_4[base_imponible_18],Anexo_4[gastos_operativos_kpi],$D$13,Anexo_4[periodo],$J$7)+SUMIFS(Anexo_4[base_imponible_10],Anexo_4[gastos_operativos_kpi],$D$13,Anexo_4[periodo],$J$7) -> 0 | K13: =SUMIFS(Anexo_4[base_imponible_18],Anexo_4[gastos_operativos_kpi],$D$13,Anexo_4[periodo],$K$7)+SUMIFS(Anexo_4[base_imponible_10],Anexo_4[gastos_operativos_kpi],$D$13,Anexo_4[periodo],$K$7) -> 150.23 | L13: =SUMIFS(Anexo_4[base_imponible_18],Anexo_4[gastos_operativos_kpi],$D$13,Anexo_4[periodo],$L$7)+SUMIFS(Anexo_4[base_imponible_10],Anexo_4[gastos_operativos_kpi],$D$13,Anexo_4[periodo],$L$7) -> 0 | M13: =SUMIFS(Anexo_4[base_imponible_18],Anexo_4[gastos_operativos_kpi],$D$13,Anexo_4[periodo],$M$7)+SUMIFS(Anexo_4[base_imponible_10],Anexo_4[gastos_operativos_kpi],$D$13,Anexo_4[periodo],$M$7) -> 84.75 | N13: =SUMIFS(Anexo_4[base_imponible_18],Anexo_4[gastos_operativos_kpi],$D$13,Anexo_4[periodo],$N$7)+SUMIFS(Anexo_4[base_imponible_10],Anexo_4[gastos_operativos_kpi],$D$13,Anexo_4[periodo],$N$7) -> 765.95 | O13: =SUMIFS(Anexo_4[base_imponible_18],Anexo_4[gastos_operativos_kpi],$D$13,Anexo_4[periodo],$O$7)+SUMIFS(Anexo_4[base_imponible_10],Anexo_4[gastos_operativos_kpi],$D$13,Anexo_4[periodo],$O$7) -> 0 | P13: =SUMIFS(Anexo_4[base_imponible_18],Anexo_4[gastos_operativos_kpi],$D$13,Anexo_4[periodo],$P$7)+SUMIFS(Anexo_4[base_imponible_10],Anexo_4[gastos_operativos_kpi],$D$13,Anexo_4[periodo],$P$7) -> 0 | Q13: =SUMIFS(Anexo_4[base_imponible_18],Anexo_4[gastos_operativos_kpi],$D$13,Anexo_4[periodo],$Q$7)+SUMIFS(Anexo_4[base_imponible_10],Anexo_4[gastos_operativos_kpi],$D$13,Anexo_4[periodo],$Q$7) -> 0 | R13: =SUM(F13:Q13) -> 1000.93 | S13: =AVERAGE(F13:Q13) -> 83.410833
D14: Alimentacion (Operativo) | E14: Moneda | F14: =SUMIFS(Anexo_4[base_imponible_18],Anexo_4[gastos_operativos_kpi],$D$14,Anexo_4[periodo],$F$7)+SUMIFS(Anexo_4[base_imponible_10],Anexo_4[gastos_operativos_kpi],$D$14,Anexo_4[periodo],$F$7) -> 0 | G14: =SUMIFS(Anexo_4[base_imponible_18],Anexo_4[gastos_operativos_kpi],$D$14,Anexo_4[periodo],$G$7)+SUMIFS(Anexo_4[base_imponible_10],Anexo_4[gastos_operativos_kpi],$D$14,Anexo_4[periodo],$G$7) -> 0 | H14: =SUMIFS(Anexo_4[base_imponible_18],Anexo_4[gastos_operativos_kpi],$D$14,Anexo_4[periodo],$H$7)+SUMIFS(Anexo_4[base_imponible_10],Anexo_4[gastos_operativos_kpi],$D$14,Anexo_4[periodo],$H$7) -> 0 | I14: =SUMIFS(Anexo_4[base_imponible_18],Anexo_4[gastos_operativos_kpi],$D$14,Anexo_4[periodo],$I$7)+SUMIFS(Anexo_4[base_imponible_10],Anexo_4[gastos_operativos_kpi],$D$14,Anexo_4[periodo],$I$7) -> 0 | J14: =SUMIFS(Anexo_4[base_imponible_18],Anexo_4[gastos_operativos_kpi],$D$14,Anexo_4[periodo],$J$7)+SUMIFS(Anexo_4[base_imponible_10],Anexo_4[gastos_operativos_kpi],$D$14,Anexo_4[periodo],$J$7) -> 0 | K14: =SUMIFS(Anexo_4[base_imponible_18],Anexo_4[gastos_operativos_kpi],$D$14,Anexo_4[periodo],$K$7)+SUMIFS(Anexo_4[base_imponible_10],Anexo_4[gastos_operativos_kpi],$D$14,Anexo_4[periodo],$K$7) -> 55.08 | L14: =SUMIFS(Anexo_4[base_imponible_18],Anexo_4[gastos_operativos_kpi],$D$14,Anexo_4[periodo],$L$7)+SUMIFS(Anexo_4[base_imponible_10],Anexo_4[gastos_operativos_kpi],$D$14,Anexo_4[periodo],$L$7) -> 33.3 | M14: =SUMIFS(Anexo_4[base_imponible_18],Anexo_4[gastos_operativos_kpi],$D$14,Anexo_4[periodo],$M$7)+SUMIFS(Anexo_4[base_imponible_10],Anexo_4[gastos_operativos_kpi],$D$14,Anexo_4[periodo],$M$7) -> 44.92 | N14: =SUMIFS(Anexo_4[base_imponible_18],Anexo_4[gastos_operativos_kpi],$D$14,Anexo_4[periodo],$N$7)+SUMIFS(Anexo_4[base_imponible_10],Anexo_4[gastos_operativos_kpi],$D$14,Anexo_4[periodo],$N$7) -> 149.15 | O14: =SUMIFS(Anexo_4[base_imponible_18],Anexo_4[gastos_operativos_kpi],$D$14,Anexo_4[periodo],$O$7)+SUMIFS(Anexo_4[base_imponible_10],Anexo_4[gastos_operativos_kpi],$D$14,Anexo_4[periodo],$O$7) -> 0 | P14: =SUMIFS(Anexo_4[base_imponible_18],Anexo_4[gastos_operativos_kpi],$D$14,Anexo_4[periodo],$P$7)+SUMIFS(Anexo_4[base_imponible_10],Anexo_4[gastos_operativos_kpi],$D$14,Anexo_4[periodo],$P$7) -> 0 | Q14: =SUMIFS(Anexo_4[base_imponible_18],Anexo_4[gastos_operativos_kpi],$D$14,Anexo_4[periodo],$Q$7)+SUMIFS(Anexo_4[base_imponible_10],Anexo_4[gastos_operativos_kpi],$D$14,Anexo_4[periodo],$Q$7) -> 0 | R14: =SUM(F14:Q14) -> 282.45 | S14: =AVERAGE(F14:Q14) -> 23.5375
D15: GPS | E15: Moneda | F15: =SUMIFS(Anexo_4[base_imponible_18],Anexo_4[gastos_operativos_kpi],$D$15,Anexo_4[periodo],$F$7)+SUMIFS(Anexo_4[base_imponible_10],Anexo_4[gastos_operativos_kpi],$D$15,Anexo_4[periodo],$F$7) -> 0 | G15: =SUMIFS(Anexo_4[base_imponible_18],Anexo_4[gastos_operativos_kpi],$D$15,Anexo_4[periodo],$G$7)+SUMIFS(Anexo_4[base_imponible_10],Anexo_4[gastos_operativos_kpi],$D$15,Anexo_4[periodo],$G$7) -> 0 | H15: =SUMIFS(Anexo_4[base_imponible_18],Anexo_4[gastos_operativos_kpi],$D$15,Anexo_4[periodo],$H$7)+SUMIFS(Anexo_4[base_imponible_10],Anexo_4[gastos_operativos_kpi],$D$15,Anexo_4[periodo],$H$7) -> 0 | I15: =SUMIFS(Anexo_4[base_imponible_18],Anexo_4[gastos_operativos_kpi],$D$15,Anexo_4[periodo],$I$7)+SUMIFS(Anexo_4[base_imponible_10],Anexo_4[gastos_operativos_kpi],$D$15,Anexo_4[periodo],$I$7) -> 0 | J15: =SUMIFS(Anexo_4[base_imponible_18],Anexo_4[gastos_operativos_kpi],$D$15,Anexo_4[periodo],$J$7)+SUMIFS(Anexo_4[base_imponible_10],Anexo_4[gastos_operativos_kpi],$D$15,Anexo_4[periodo],$J$7) -> 0 | K15: =SUMIFS(Anexo_4[base_imponible_18],Anexo_4[gastos_operativos_kpi],$D$15,Anexo_4[periodo],$K$7)+SUMIFS(Anexo_4[base_imponible_10],Anexo_4[gastos_operativos_kpi],$D$15,Anexo_4[periodo],$K$7) -> 0 | L15: =SUMIFS(Anexo_4[base_imponible_18],Anexo_4[gastos_operativos_kpi],$D$15,Anexo_4[periodo],$L$7)+SUMIFS(Anexo_4[base_imponible_10],Anexo_4[gastos_operativos_kpi],$D$15,Anexo_4[periodo],$L$7) -> 1108.98 | M15: =SUMIFS(Anexo_4[base_imponible_18],Anexo_4[gastos_operativos_kpi],$D$15,Anexo_4[periodo],$M$7)+SUMIFS(Anexo_4[base_imponible_10],Anexo_4[gastos_operativos_kpi],$D$15,Anexo_4[periodo],$M$7) -> 0 | N15: =SUMIFS(Anexo_4[base_imponible_18],Anexo_4[gastos_operativos_kpi],$D$15,Anexo_4[periodo],$N$7)+SUMIFS(Anexo_4[base_imponible_10],Anexo_4[gastos_operativos_kpi],$D$15,Anexo_4[periodo],$N$7) -> 667.73 | O15: =SUMIFS(Anexo_4[base_imponible_18],Anexo_4[gastos_operativos_kpi],$D$15,Anexo_4[periodo],$O$7)+SUMIFS(Anexo_4[base_imponible_10],Anexo_4[gastos_operativos_kpi],$D$15,Anexo_4[periodo],$O$7) -> 0 | P15: =SUMIFS(Anexo_4[base_imponible_18],Anexo_4[gastos_operativos_kpi],$D$15,Anexo_4[periodo],$P$7)+SUMIFS(Anexo_4[base_imponible_10],Anexo_4[gastos_operativos_kpi],$D$15,Anexo_4[periodo],$P$7) -> 0 | Q15: =SUMIFS(Anexo_4[base_imponible_18],Anexo_4[gastos_operativos_kpi],$D$15,Anexo_4[periodo],$Q$7)+SUMIFS(Anexo_4[base_imponible_10],Anexo_4[gastos_operativos_kpi],$D$15,Anexo_4[periodo],$Q$7) -> 0 | R15: =SUM(F15:Q15) -> 1776.71 | S15: =AVERAGE(F15:Q15) -> 148.05917
D16: Fabricación de Contenedores | E16: Moneda | F16: =SUMIFS(Anexo_4[base_imponible_18],Anexo_4[gastos_operativos_kpi],$D$16,Anexo_4[periodo],$F$7)+SUMIFS(Anexo_4[base_imponible_10],Anexo_4[gastos_operativos_kpi],$D$16,Anexo_4[periodo],$F$7) -> 0 | G16: =SUMIFS(Anexo_4[base_imponible_18],Anexo_4[gastos_operativos_kpi],$D$16,Anexo_4[periodo],$G$7)+SUMIFS(Anexo_4[base_imponible_10],Anexo_4[gastos_operativos_kpi],$D$16,Anexo_4[periodo],$G$7) -> 0 | H16: =SUMIFS(Anexo_4[base_imponible_18],Anexo_4[gastos_operativos_kpi],$D$16,Anexo_4[periodo],$H$7)+SUMIFS(Anexo_4[base_imponible_10],Anexo_4[gastos_operativos_kpi],$D$16,Anexo_4[periodo],$H$7) -> 0 | I16: =SUMIFS(Anexo_4[base_imponible_18],Anexo_4[gastos_operativos_kpi],$D$16,Anexo_4[periodo],$I$7)+SUMIFS(Anexo_4[base_imponible_10],Anexo_4[gastos_operativos_kpi],$D$16,Anexo_4[periodo],$I$7) -> 0 | J16: =SUMIFS(Anexo_4[base_imponible_18],Anexo_4[gastos_operativos_kpi],$D$16,Anexo_4[periodo],$J$7)+SUMIFS(Anexo_4[base_imponible_10],Anexo_4[gastos_operativos_kpi],$D$16,Anexo_4[periodo],$J$7) -> 0 | K16: =SUMIFS(Anexo_4[base_imponible_18],Anexo_4[gastos_operativos_kpi],$D$16,Anexo_4[periodo],$K$7)+SUMIFS(Anexo_4[base_imponible_10],Anexo_4[gastos_operativos_kpi],$D$16,Anexo_4[periodo],$K$7) -> 0 | L16: =SUMIFS(Anexo_4[base_imponible_18],Anexo_4[gastos_operativos_kpi],$D$16,Anexo_4[periodo],$L$7)+SUMIFS(Anexo_4[base_imponible_10],Anexo_4[gastos_operativos_kpi],$D$16,Anexo_4[periodo],$L$7) -> 2000 | M16: =SUMIFS(Anexo_4[base_imponible_18],Anexo_4[gastos_operativos_kpi],$D$16,Anexo_4[periodo],$M$7)+SUMIFS(Anexo_4[base_imponible_10],Anexo_4[gastos_operativos_kpi],$D$16,Anexo_4[periodo],$M$7) -> 0 | N16: =SUMIFS(Anexo_4[base_imponible_18],Anexo_4[gastos_operativos_kpi],$D$16,Anexo_4[periodo],$N$7)+SUMIFS(Anexo_4[base_imponible_10],Anexo_4[gastos_operativos_kpi],$D$16,Anexo_4[periodo],$N$7) -> 513.45 | O16: =SUMIFS(Anexo_4[base_imponible_18],Anexo_4[gastos_operativos_kpi],$D$16,Anexo_4[periodo],$O$7)+SUMIFS(Anexo_4[base_imponible_10],Anexo_4[gastos_operativos_kpi],$D$16,Anexo_4[periodo],$O$7) -> 0 | P16: =SUMIFS(Anexo_4[base_imponible_18],Anexo_4[gastos_operativos_kpi],$D$16,Anexo_4[periodo],$P$7)+SUMIFS(Anexo_4[base_imponible_10],Anexo_4[gastos_operativos_kpi],$D$16,Anexo_4[periodo],$P$7) -> 0 | Q16: =SUMIFS(Anexo_4[base_imponible_18],Anexo_4[gastos_operativos_kpi],$D$16,Anexo_4[periodo],$Q$7)+SUMIFS(Anexo_4[base_imponible_10],Anexo_4[gastos_operativos_kpi],$D$16,Anexo_4[periodo],$Q$7) -> 0 | R16: =SUM(F16:Q16) -> 2513.45 | S16: =AVERAGE(F16:Q16) -> 209.45417
D17: Revisión Técnica Vehicular | E17: Moneda | F17: =SUMIFS(Anexo_4[base_imponible_18],Anexo_4[gastos_operativos_kpi],$D$17,Anexo_4[periodo],$F$7)+SUMIFS(Anexo_4[base_imponible_10],Anexo_4[gastos_operativos_kpi],$D$17,Anexo_4[periodo],$F$7) -> 0 | G17: =SUMIFS(Anexo_4[base_imponible_18],Anexo_4[gastos_operativos_kpi],$D$17,Anexo_4[periodo],$G$7)+SUMIFS(Anexo_4[base_imponible_10],Anexo_4[gastos_operativos_kpi],$D$17,Anexo_4[periodo],$G$7) -> 0 | H17: =SUMIFS(Anexo_4[base_imponible_18],Anexo_4[gastos_operativos_kpi],$D$17,Anexo_4[periodo],$H$7)+SUMIFS(Anexo_4[base_imponible_10],Anexo_4[gastos_operativos_kpi],$D$17,Anexo_4[periodo],$H$7) -> 0 | I17: =SUMIFS(Anexo_4[base_imponible_18],Anexo_4[gastos_operativos_kpi],$D$17,Anexo_4[periodo],$I$7)+SUMIFS(Anexo_4[base_imponible_10],Anexo_4[gastos_operativos_kpi],$D$17,Anexo_4[periodo],$I$7) -> 0 | J17: =SUMIFS(Anexo_4[base_imponible_18],Anexo_4[gastos_operativos_kpi],$D$17,Anexo_4[periodo],$J$7)+SUMIFS(Anexo_4[base_imponible_10],Anexo_4[gastos_operativos_kpi],$D$17,Anexo_4[periodo],$J$7) -> 0 | K17: =SUMIFS(Anexo_4[base_imponible_18],Anexo_4[gastos_operativos_kpi],$D$17,Anexo_4[periodo],$K$7)+SUMIFS(Anexo_4[base_imponible_10],Anexo_4[gastos_operativos_kpi],$D$17,Anexo_4[periodo],$K$7) -> 355.93 | L17: =SUMIFS(Anexo_4[base_imponible_18],Anexo_4[gastos_operativos_kpi],$D$17,Anexo_4[periodo],$L$7)+SUMIFS(Anexo_4[base_imponible_10],Anexo_4[gastos_operativos_kpi],$D$17,Anexo_4[periodo],$L$7) -> 0 | M17: =SUMIFS(Anexo_4[base_imponible_18],Anexo_4[gastos_operativos_kpi],$D$17,Anexo_4[periodo],$M$7)+SUMIFS(Anexo_4[base_imponible_10],Anexo_4[gastos_operativos_kpi],$D$17,Anexo_4[periodo],$M$7) -> 186.44 | N17: =SUMIFS(Anexo_4[base_imponible_18],Anexo_4[gastos_operativos_kpi],$D$17,Anexo_4[periodo],$N$7)+SUMIFS(Anexo_4[base_imponible_10],Anexo_4[gastos_operativos_kpi],$D$17,Anexo_4[periodo],$N$7) -> 59.32 | O17: =SUMIFS(Anexo_4[base_imponible_18],Anexo_4[gastos_operativos_kpi],$D$17,Anexo_4[periodo],$O$7)+SUMIFS(Anexo_4[base_imponible_10],Anexo_4[gastos_operativos_kpi],$D$17,Anexo_4[periodo],$O$7) -> 0 | P17: =SUMIFS(Anexo_4[base_imponible_18],Anexo_4[gastos_operativos_kpi],$D$17,Anexo_4[periodo],$P$7)+SUMIFS(Anexo_4[base_imponible_10],Anexo_4[gastos_operativos_kpi],$D$17,Anexo_4[periodo],$P$7) -> 0 | Q17: =SUMIFS(Anexo_4[base_imponible_18],Anexo_4[gastos_operativos_kpi],$D$17,Anexo_4[periodo],$Q$7)+SUMIFS(Anexo_4[base_imponible_10],Anexo_4[gastos_operativos_kpi],$D$17,Anexo_4[periodo],$Q$7) -> 0 | R17: =SUM(F17:Q17) -> 601.69 | S17: =AVERAGE(F17:Q17) -> 50.140833
D18: Mantenimiento Vehicular (Correctivo) | E18: Moneda | F18: =SUMIFS(Anexo_4[base_imponible_18],Anexo_4[gastos_operativos_kpi],$D$18,Anexo_4[periodo],$F$7)+SUMIFS(Anexo_4[base_imponible_10],Anexo_4[gastos_operativos_kpi],$D$18,Anexo_4[periodo],$F$7) -> 0 | G18: =SUMIFS(Anexo_4[base_imponible_18],Anexo_4[gastos_operativos_kpi],$D$18,Anexo_4[periodo],$G$7)+SUMIFS(Anexo_4[base_imponible_10],Anexo_4[gastos_operativos_kpi],$D$18,Anexo_4[periodo],$G$7) -> 0 | H18: =SUMIFS(Anexo_4[base_imponible_18],Anexo_4[gastos_operativos_kpi],$D$18,Anexo_4[periodo],$H$7)+SUMIFS(Anexo_4[base_imponible_10],Anexo_4[gastos_operativos_kpi],$D$18,Anexo_4[periodo],$H$7) -> 0 | I18: =SUMIFS(Anexo_4[base_imponible_18],Anexo_4[gastos_operativos_kpi],$D$18,Anexo_4[periodo],$I$7)+SUMIFS(Anexo_4[base_imponible_10],Anexo_4[gastos_operativos_kpi],$D$18,Anexo_4[periodo],$I$7) -> 0 | J18: =SUMIFS(Anexo_4[base_imponible_18],Anexo_4[gastos_operativos_kpi],$D$18,Anexo_4[periodo],$J$7)+SUMIFS(Anexo_4[base_imponible_10],Anexo_4[gastos_operativos_kpi],$D$18,Anexo_4[periodo],$J$7) -> 0 | K18: =SUMIFS(Anexo_4[base_imponible_18],Anexo_4[gastos_operativos_kpi],$D$18,Anexo_4[periodo],$K$7)+SUMIFS(Anexo_4[base_imponible_10],Anexo_4[gastos_operativos_kpi],$D$18,Anexo_4[periodo],$K$7) -> 214.41 | L18: =SUMIFS(Anexo_4[base_imponible_18],Anexo_4[gastos_operativos_kpi],$D$18,Anexo_4[periodo],$L$7)+SUMIFS(Anexo_4[base_imponible_10],Anexo_4[gastos_operativos_kpi],$D$18,Anexo_4[periodo],$L$7) -> 254.24 | M18: =SUMIFS(Anexo_4[base_imponible_18],Anexo_4[gastos_operativos_kpi],$D$18,Anexo_4[periodo],$M$7)+SUMIFS(Anexo_4[base_imponible_10],Anexo_4[gastos_operativos_kpi],$D$18,Anexo_4[periodo],$M$7) -> 36.02 | N18: =SUMIFS(Anexo_4[base_imponible_18],Anexo_4[gastos_operativos_kpi],$D$18,Anexo_4[periodo],$N$7)+SUMIFS(Anexo_4[base_imponible_10],Anexo_4[gastos_operativos_kpi],$D$18,Anexo_4[periodo],$N$7) -> 780 | O18: =SUMIFS(Anexo_4[base_imponible_18],Anexo_4[gastos_operativos_kpi],$D$18,Anexo_4[periodo],$O$7)+SUMIFS(Anexo_4[base_imponible_10],Anexo_4[gastos_operativos_kpi],$D$18,Anexo_4[periodo],$O$7) -> 0 | P18: =SUMIFS(Anexo_4[base_imponible_18],Anexo_4[gastos_operativos_kpi],$D$18,Anexo_4[periodo],$P$7)+SUMIFS(Anexo_4[base_imponible_10],Anexo_4[gastos_operativos_kpi],$D$18,Anexo_4[periodo],$P$7) -> 0 | Q18: =SUMIFS(Anexo_4[base_imponible_18],Anexo_4[gastos_operativos_kpi],$D$18,Anexo_4[periodo],$Q$7)+SUMIFS(Anexo_4[base_imponible_10],Anexo_4[gastos_operativos_kpi],$D$18,Anexo_4[periodo],$Q$7) -> 0 | R18: =SUM(F18:Q18) -> 1284.67 | S18: =AVERAGE(F18:Q18) -> 107.05583
D19: Mantenimiento Vehicular (Preventivo) | E19: Moneda | F19: =SUMIFS(Anexo_4[base_imponible_18],Anexo_4[gastos_operativos_kpi],$D$19,Anexo_4[periodo],$F$7)+SUMIFS(Anexo_4[base_imponible_10],Anexo_4[gastos_operativos_kpi],$D$19,Anexo_4[periodo],$F$7) -> 0 | G19: =SUMIFS(Anexo_4[base_imponible_18],Anexo_4[gastos_operativos_kpi],$D$19,Anexo_4[periodo],$G$7)+SUMIFS(Anexo_4[base_imponible_10],Anexo_4[gastos_operativos_kpi],$D$19,Anexo_4[periodo],$G$7) -> 0 | H19: =SUMIFS(Anexo_4[base_imponible_18],Anexo_4[gastos_operativos_kpi],$D$19,Anexo_4[periodo],$H$7)+SUMIFS(Anexo_4[base_imponible_10],Anexo_4[gastos_operativos_kpi],$D$19,Anexo_4[periodo],$H$7) -> 0 | I19: =SUMIFS(Anexo_4[base_imponible_18],Anexo_4[gastos_operativos_kpi],$D$19,Anexo_4[periodo],$I$7)+SUMIFS(Anexo_4[base_imponible_10],Anexo_4[gastos_operativos_kpi],$D$19,Anexo_4[periodo],$I$7) -> 0 | J19: =SUMIFS(Anexo_4[base_imponible_18],Anexo_4[gastos_operativos_kpi],$D$19,Anexo_4[periodo],$J$7)+SUMIFS(Anexo_4[base_imponible_10],Anexo_4[gastos_operativos_kpi],$D$19,Anexo_4[periodo],$J$7) -> 0 | K19: =SUMIFS(Anexo_4[base_imponible_18],Anexo_4[gastos_operativos_kpi],$D$19,Anexo_4[periodo],$K$7)+SUMIFS(Anexo_4[base_imponible_10],Anexo_4[gastos_operativos_kpi],$D$19,Anexo_4[periodo],$K$7) -> 6847.93 | L19: =SUMIFS(Anexo_4[base_imponible_18],Anexo_4[gastos_operativos_kpi],$D$19,Anexo_4[periodo],$L$7)+SUMIFS(Anexo_4[base_imponible_10],Anexo_4[gastos_operativos_kpi],$D$19,Anexo_4[periodo],$L$7) -> 7402.85 | M19: =SUMIFS(Anexo_4[base_imponible_18],Anexo_4[gastos_operativos_kpi],$D$19,Anexo_4[periodo],$M$7)+SUMIFS(Anexo_4[base_imponible_10],Anexo_4[gastos_operativos_kpi],$D$19,Anexo_4[periodo],$M$7) -> 3420.86 | N19: =SUMIFS(Anexo_4[base_imponible_18],Anexo_4[gastos_operativos_kpi],$D$19,Anexo_4[periodo],$N$7)+SUMIFS(Anexo_4[base_imponible_10],Anexo_4[gastos_operativos_kpi],$D$19,Anexo_4[periodo],$N$7) -> 2879.8 | O19: =SUMIFS(Anexo_4[base_imponible_18],Anexo_4[gastos_operativos_kpi],$D$19,Anexo_4[periodo],$O$7)+SUMIFS(Anexo_4[base_imponible_10],Anexo_4[gastos_operativos_kpi],$D$19,Anexo_4[periodo],$O$7) -> 0 | P19: =SUMIFS(Anexo_4[base_imponible_18],Anexo_4[gastos_operativos_kpi],$D$19,Anexo_4[periodo],$P$7)+SUMIFS(Anexo_4[base_imponible_10],Anexo_4[gastos_operativos_kpi],$D$19,Anexo_4[periodo],$P$7) -> 0 | Q19: =SUMIFS(Anexo_4[base_imponible_18],Anexo_4[gastos_operativos_kpi],$D$19,Anexo_4[periodo],$Q$7)+SUMIFS(Anexo_4[base_imponible_10],Anexo_4[gastos_operativos_kpi],$D$19,Anexo_4[periodo],$Q$7) -> 0 | R19: =SUM(F19:Q19) -> 20551.44 | S19: =AVERAGE(F19:Q19) -> 1712.62
D20: Accesorios Vehiculares | E20: Moneda | F20: =SUMIFS(Anexo_4[base_imponible_18],Anexo_4[gastos_operativos_kpi],$D$20,Anexo_4[periodo],$F$7)+SUMIFS(Anexo_4[base_imponible_10],Anexo_4[gastos_operativos_kpi],$D$20,Anexo_4[periodo],$F$7) -> 0 | G20: =SUMIFS(Anexo_4[base_imponible_18],Anexo_4[gastos_operativos_kpi],$D$20,Anexo_4[periodo],$G$7)+SUMIFS(Anexo_4[base_imponible_10],Anexo_4[gastos_operativos_kpi],$D$20,Anexo_4[periodo],$G$7) -> 0 | H20: =SUMIFS(Anexo_4[base_imponible_18],Anexo_4[gastos_operativos_kpi],$D$20,Anexo_4[periodo],$H$7)+SUMIFS(Anexo_4[base_imponible_10],Anexo_4[gastos_operativos_kpi],$D$20,Anexo_4[periodo],$H$7) -> 0 | I20: =SUMIFS(Anexo_4[base_imponible_18],Anexo_4[gastos_operativos_kpi],$D$20,Anexo_4[periodo],$I$7)+SUMIFS(Anexo_4[base_imponible_10],Anexo_4[gastos_operativos_kpi],$D$20,Anexo_4[periodo],$I$7) -> 0 | J20: =SUMIFS(Anexo_4[base_imponible_18],Anexo_4[gastos_operativos_kpi],$D$20,Anexo_4[periodo],$J$7)+SUMIFS(Anexo_4[base_imponible_10],Anexo_4[gastos_operativos_kpi],$D$20,Anexo_4[periodo],$J$7) -> 0 | K20: =SUMIFS(Anexo_4[base_imponible_18],Anexo_4[gastos_operativos_kpi],$D$20,Anexo_4[periodo],$K$7)+SUMIFS(Anexo_4[base_imponible_10],Anexo_4[gastos_operativos_kpi],$D$20,Anexo_4[periodo],$K$7) -> 1119.22 | L20: =SUMIFS(Anexo_4[base_imponible_18],Anexo_4[gastos_operativos_kpi],$D$20,Anexo_4[periodo],$L$7)+SUMIFS(Anexo_4[base_imponible_10],Anexo_4[gastos_operativos_kpi],$D$20,Anexo_4[periodo],$L$7) -> 1571.17 | M20: =SUMIFS(Anexo_4[base_imponible_18],Anexo_4[gastos_operativos_kpi],$D$20,Anexo_4[periodo],$M$7)+SUMIFS(Anexo_4[base_imponible_10],Anexo_4[gastos_operativos_kpi],$D$20,Anexo_4[periodo],$M$7) -> 2384.97 | N20: =SUMIFS(Anexo_4[base_imponible_18],Anexo_4[gastos_operativos_kpi],$D$20,Anexo_4[periodo],$N$7)+SUMIFS(Anexo_4[base_imponible_10],Anexo_4[gastos_operativos_kpi],$D$20,Anexo_4[periodo],$N$7) -> 1865.16 | O20: =SUMIFS(Anexo_4[base_imponible_18],Anexo_4[gastos_operativos_kpi],$D$20,Anexo_4[periodo],$O$7)+SUMIFS(Anexo_4[base_imponible_10],Anexo_4[gastos_operativos_kpi],$D$20,Anexo_4[periodo],$O$7) -> 0 | P20: =SUMIFS(Anexo_4[base_imponible_18],Anexo_4[gastos_operativos_kpi],$D$20,Anexo_4[periodo],$P$7)+SUMIFS(Anexo_4[base_imponible_10],Anexo_4[gastos_operativos_kpi],$D$20,Anexo_4[periodo],$P$7) -> 0 | Q20: =SUMIFS(Anexo_4[base_imponible_18],Anexo_4[gastos_operativos_kpi],$D$20,Anexo_4[periodo],$Q$7)+SUMIFS(Anexo_4[base_imponible_10],Anexo_4[gastos_operativos_kpi],$D$20,Anexo_4[periodo],$Q$7) -> 0 | R20: =SUM(F20:Q20) -> 6940.52 | S20: =AVERAGE(F20:Q20) -> 578.37667
D21: Mantenimiento Correctivo (Montacarga) | E21: Moneda | F21: =SUMIFS(Anexo_4[base_imponible_18],Anexo_4[gastos_operativos_kpi],$D$21,Anexo_4[periodo],$F$7)+SUMIFS(Anexo_4[base_imponible_10],Anexo_4[gastos_operativos_kpi],$D$21,Anexo_4[periodo],$F$7) -> 0 | G21: =SUMIFS(Anexo_4[base_imponible_18],Anexo_4[gastos_operativos_kpi],$D$21,Anexo_4[periodo],$G$7)+SUMIFS(Anexo_4[base_imponible_10],Anexo_4[gastos_operativos_kpi],$D$21,Anexo_4[periodo],$G$7) -> 0 | H21: =SUMIFS(Anexo_4[base_imponible_18],Anexo_4[gastos_operativos_kpi],$D$21,Anexo_4[periodo],$H$7)+SUMIFS(Anexo_4[base_imponible_10],Anexo_4[gastos_operativos_kpi],$D$21,Anexo_4[periodo],$H$7) -> 0 | I21: =SUMIFS(Anexo_4[base_imponible_18],Anexo_4[gastos_operativos_kpi],$D$21,Anexo_4[periodo],$I$7)+SUMIFS(Anexo_4[base_imponible_10],Anexo_4[gastos_operativos_kpi],$D$21,Anexo_4[periodo],$I$7) -> 0 | J21: =SUMIFS(Anexo_4[base_imponible_18],Anexo_4[gastos_operativos_kpi],$D$21,Anexo_4[periodo],$J$7)+SUMIFS(Anexo_4[base_imponible_10],Anexo_4[gastos_operativos_kpi],$D$21,Anexo_4[periodo],$J$7) -> 0 | K21: =SUMIFS(Anexo_4[base_imponible_18],Anexo_4[gastos_operativos_kpi],$D$21,Anexo_4[periodo],$K$7)+SUMIFS(Anexo_4[base_imponible_10],Anexo_4[gastos_operativos_kpi],$D$21,Anexo_4[periodo],$K$7) -> 0 | L21: =SUMIFS(Anexo_4[base_imponible_18],Anexo_4[gastos_operativos_kpi],$D$21,Anexo_4[periodo],$L$7)+SUMIFS(Anexo_4[base_imponible_10],Anexo_4[gastos_operativos_kpi],$D$21,Anexo_4[periodo],$L$7) -> 0 | M21: =SUMIFS(Anexo_4[base_imponible_18],Anexo_4[gastos_operativos_kpi],$D$21,Anexo_4[periodo],$M$7)+SUMIFS(Anexo_4[base_imponible_10],Anexo_4[gastos_operativos_kpi],$D$21,Anexo_4[periodo],$M$7) -> 0 | N21: =SUMIFS(Anexo_4[base_imponible_18],Anexo_4[gastos_operativos_kpi],$D$21,Anexo_4[periodo],$N$7)+SUMIFS(Anexo_4[base_imponible_10],Anexo_4[gastos_operativos_kpi],$D$21,Anexo_4[periodo],$N$7) -> 0 | O21: =SUMIFS(Anexo_4[base_imponible_18],Anexo_4[gastos_operativos_kpi],$D$21,Anexo_4[periodo],$O$7)+SUMIFS(Anexo_4[base_imponible_10],Anexo_4[gastos_operativos_kpi],$D$21,Anexo_4[periodo],$O$7) -> 0 | P21: =SUMIFS(Anexo_4[base_imponible_18],Anexo_4[gastos_operativos_kpi],$D$21,Anexo_4[periodo],$P$7)+SUMIFS(Anexo_4[base_imponible_10],Anexo_4[gastos_operativos_kpi],$D$21,Anexo_4[periodo],$P$7) -> 0 | Q21: =SUMIFS(Anexo_4[base_imponible_18],Anexo_4[gastos_operativos_kpi],$D$21,Anexo_4[periodo],$Q$7)+SUMIFS(Anexo_4[base_imponible_10],Anexo_4[gastos_operativos_kpi],$D$21,Anexo_4[periodo],$Q$7) -> 0 | R21: =SUM(F21:Q21) -> 0 | S21: =AVERAGE(F21:Q21) -> 0
D22: Mantenimiento Preventivo (Montacarga) | E22: Moneda | F22: =SUMIFS(Anexo_4[base_imponible_18],Anexo_4[gastos_operativos_kpi],$D$22,Anexo_4[periodo],$F$7)+SUMIFS(Anexo_4[base_imponible_10],Anexo_4[gastos_operativos_kpi],$D$22,Anexo_4[periodo],$F$7) -> 0 | G22: =SUMIFS(Anexo_4[base_imponible_18],Anexo_4[gastos_operativos_kpi],$D$22,Anexo_4[periodo],$G$7)+SUMIFS(Anexo_4[base_imponible_10],Anexo_4[gastos_operativos_kpi],$D$22,Anexo_4[periodo],$G$7) -> 0 | H22: =SUMIFS(Anexo_4[base_imponible_18],Anexo_4[gastos_operativos_kpi],$D$22,Anexo_4[periodo],$H$7)+SUMIFS(Anexo_4[base_imponible_10],Anexo_4[gastos_operativos_kpi],$D$22,Anexo_4[periodo],$H$7) -> 0 | I22: =SUMIFS(Anexo_4[base_imponible_18],Anexo_4[gastos_operativos_kpi],$D$22,Anexo_4[periodo],$I$7)+SUMIFS(Anexo_4[base_imponible_10],Anexo_4[gastos_operativos_kpi],$D$22,Anexo_4[periodo],$I$7) -> 0 | J22: =SUMIFS(Anexo_4[base_imponible_18],Anexo_4[gastos_operativos_kpi],$D$22,Anexo_4[periodo],$J$7)+SUMIFS(Anexo_4[base_imponible_10],Anexo_4[gastos_operativos_kpi],$D$22,Anexo_4[periodo],$J$7) -> 0 | K22: =SUMIFS(Anexo_4[base_imponible_18],Anexo_4[gastos_operativos_kpi],$D$22,Anexo_4[periodo],$K$7)+SUMIFS(Anexo_4[base_imponible_10],Anexo_4[gastos_operativos_kpi],$D$22,Anexo_4[periodo],$K$7) -> 76.27 | L22: =SUMIFS(Anexo_4[base_imponible_18],Anexo_4[gastos_operativos_kpi],$D$22,Anexo_4[periodo],$L$7)+SUMIFS(Anexo_4[base_imponible_10],Anexo_4[gastos_operativos_kpi],$D$22,Anexo_4[periodo],$L$7) -> 152.54 | M22: =SUMIFS(Anexo_4[base_imponible_18],Anexo_4[gastos_operativos_kpi],$D$22,Anexo_4[periodo],$M$7)+SUMIFS(Anexo_4[base_imponible_10],Anexo_4[gastos_operativos_kpi],$D$22,Anexo_4[periodo],$M$7) -> 0 | N22: =SUMIFS(Anexo_4[base_imponible_18],Anexo_4[gastos_operativos_kpi],$D$22,Anexo_4[periodo],$N$7)+SUMIFS(Anexo_4[base_imponible_10],Anexo_4[gastos_operativos_kpi],$D$22,Anexo_4[periodo],$N$7) -> 381.36 | O22: =SUMIFS(Anexo_4[base_imponible_18],Anexo_4[gastos_operativos_kpi],$D$22,Anexo_4[periodo],$O$7)+SUMIFS(Anexo_4[base_imponible_10],Anexo_4[gastos_operativos_kpi],$D$22,Anexo_4[periodo],$O$7) -> 0 | P22: =SUMIFS(Anexo_4[base_imponible_18],Anexo_4[gastos_operativos_kpi],$D$22,Anexo_4[periodo],$P$7)+SUMIFS(Anexo_4[base_imponible_10],Anexo_4[gastos_operativos_kpi],$D$22,Anexo_4[periodo],$P$7) -> 0 | Q22: =SUMIFS(Anexo_4[base_imponible_18],Anexo_4[gastos_operativos_kpi],$D$22,Anexo_4[periodo],$Q$7)+SUMIFS(Anexo_4[base_imponible_10],Anexo_4[gastos_operativos_kpi],$D$22,Anexo_4[periodo],$Q$7) -> 0 | R22: =SUM(F22:Q22) -> 610.17 | S22: =AVERAGE(F22:Q22) -> 50.8475
D23: Impresión de manifiestos | E23: Moneda | F23: =SUMIFS(Anexo_4[base_imponible_18],Anexo_4[gastos_operativos_kpi],$D$23,Anexo_4[periodo],$F$7)+SUMIFS(Anexo_4[base_imponible_10],Anexo_4[gastos_operativos_kpi],$D$23,Anexo_4[periodo],$F$7) -> 0 | G23: =SUMIFS(Anexo_4[base_imponible_18],Anexo_4[gastos_operativos_kpi],$D$23,Anexo_4[periodo],$G$7)+SUMIFS(Anexo_4[base_imponible_10],Anexo_4[gastos_operativos_kpi],$D$23,Anexo_4[periodo],$G$7) -> 0 | H23: =SUMIFS(Anexo_4[base_imponible_18],Anexo_4[gastos_operativos_kpi],$D$23,Anexo_4[periodo],$H$7)+SUMIFS(Anexo_4[base_imponible_10],Anexo_4[gastos_operativos_kpi],$D$23,Anexo_4[periodo],$H$7) -> 0 | I23: =SUMIFS(Anexo_4[base_imponible_18],Anexo_4[gastos_operativos_kpi],$D$23,Anexo_4[periodo],$I$7)+SUMIFS(Anexo_4[base_imponible_10],Anexo_4[gastos_operativos_kpi],$D$23,Anexo_4[periodo],$I$7) -> 0 | J23: =SUMIFS(Anexo_4[base_imponible_18],Anexo_4[gastos_operativos_kpi],$D$23,Anexo_4[periodo],$J$7)+SUMIFS(Anexo_4[base_imponible_10],Anexo_4[gastos_operativos_kpi],$D$23,Anexo_4[periodo],$J$7) -> 0 | K23: =SUMIFS(Anexo_4[base_imponible_18],Anexo_4[gastos_operativos_kpi],$D$23,Anexo_4[periodo],$K$7)+SUMIFS(Anexo_4[base_imponible_10],Anexo_4[gastos_operativos_kpi],$D$23,Anexo_4[periodo],$K$7) -> 0 | L23: =SUMIFS(Anexo_4[base_imponible_18],Anexo_4[gastos_operativos_kpi],$D$23,Anexo_4[periodo],$L$7)+SUMIFS(Anexo_4[base_imponible_10],Anexo_4[gastos_operativos_kpi],$D$23,Anexo_4[periodo],$L$7) -> 0 | M23: =SUMIFS(Anexo_4[base_imponible_18],Anexo_4[gastos_operativos_kpi],$D$23,Anexo_4[periodo],$M$7)+SUMIFS(Anexo_4[base_imponible_10],Anexo_4[gastos_operativos_kpi],$D$23,Anexo_4[periodo],$M$7) -> 0 | N23: =SUMIFS(Anexo_4[base_imponible_18],Anexo_4[gastos_operativos_kpi],$D$23,Anexo_4[periodo],$N$7)+SUMIFS(Anexo_4[base_imponible_10],Anexo_4[gastos_operativos_kpi],$D$23,Anexo_4[periodo],$N$7) -> 0 | O23: =SUMIFS(Anexo_4[base_imponible_18],Anexo_4[gastos_operativos_kpi],$D$23,Anexo_4[periodo],$O$7)+SUMIFS(Anexo_4[base_imponible_10],Anexo_4[gastos_operativos_kpi],$D$23,Anexo_4[periodo],$O$7) -> 0 | P23: =SUMIFS(Anexo_4[base_imponible_18],Anexo_4[gastos_operativos_kpi],$D$23,Anexo_4[periodo],$P$7)+SUMIFS(Anexo_4[base_imponible_10],Anexo_4[gastos_operativos_kpi],$D$23,Anexo_4[periodo],$P$7) -> 0 | Q23: =SUMIFS(Anexo_4[base_imponible_18],Anexo_4[gastos_operativos_kpi],$D$23,Anexo_4[periodo],$Q$7)+SUMIFS(Anexo_4[base_imponible_10],Anexo_4[gastos_operativos_kpi],$D$23,Anexo_4[periodo],$Q$7) -> 0 | R23: =SUM(F23:Q23) -> 0 | S23: =AVERAGE(F23:Q23) -> 0
D24: Mantenimiento de Motobombas | E24: Moneda | F24: =SUMIFS(Anexo_4[base_imponible_18],Anexo_4[gastos_operativos_kpi],$D$24,Anexo_4[periodo],$F$7)+SUMIFS(Anexo_4[base_imponible_10],Anexo_4[gastos_operativos_kpi],$D$24,Anexo_4[periodo],$F$7) -> 0 | G24: =SUMIFS(Anexo_4[base_imponible_18],Anexo_4[gastos_operativos_kpi],$D$24,Anexo_4[periodo],$G$7)+SUMIFS(Anexo_4[base_imponible_10],Anexo_4[gastos_operativos_kpi],$D$24,Anexo_4[periodo],$G$7) -> 0 | H24: =SUMIFS(Anexo_4[base_imponible_18],Anexo_4[gastos_operativos_kpi],$D$24,Anexo_4[periodo],$H$7)+SUMIFS(Anexo_4[base_imponible_10],Anexo_4[gastos_operativos_kpi],$D$24,Anexo_4[periodo],$H$7) -> 0 | I24: =SUMIFS(Anexo_4[base_imponible_18],Anexo_4[gastos_operativos_kpi],$D$24,Anexo_4[periodo],$I$7)+SUMIFS(Anexo_4[base_imponible_10],Anexo_4[gastos_operativos_kpi],$D$24,Anexo_4[periodo],$I$7) -> 0 | J24: =SUMIFS(Anexo_4[base_imponible_18],Anexo_4[gastos_operativos_kpi],$D$24,Anexo_4[periodo],$J$7)+SUMIFS(Anexo_4[base_imponible_10],Anexo_4[gastos_operativos_kpi],$D$24,Anexo_4[periodo],$J$7) -> 0 | K24: =SUMIFS(Anexo_4[base_imponible_18],Anexo_4[gastos_operativos_kpi],$D$24,Anexo_4[periodo],$K$7)+SUMIFS(Anexo_4[base_imponible_10],Anexo_4[gastos_operativos_kpi],$D$24,Anexo_4[periodo],$K$7) -> 0 | L24: =SUMIFS(Anexo_4[base_imponible_18],Anexo_4[gastos_operativos_kpi],$D$24,Anexo_4[periodo],$L$7)+SUMIFS(Anexo_4[base_imponible_10],Anexo_4[gastos_operativos_kpi],$D$24,Anexo_4[periodo],$L$7) -> 0 | M24: =SUMIFS(Anexo_4[base_imponible_18],Anexo_4[gastos_operativos_kpi],$D$24,Anexo_4[periodo],$M$7)+SUMIFS(Anexo_4[base_imponible_10],Anexo_4[gastos_operativos_kpi],$D$24,Anexo_4[periodo],$M$7) -> 0 | N24: =SUMIFS(Anexo_4[base_imponible_18],Anexo_4[gastos_operativos_kpi],$D$24,Anexo_4[periodo],$N$7)+SUMIFS(Anexo_4[base_imponible_10],Anexo_4[gastos_operativos_kpi],$D$24,Anexo_4[periodo],$N$7) -> 0 | O24: =SUMIFS(Anexo_4[base_imponible_18],Anexo_4[gastos_operativos_kpi],$D$24,Anexo_4[periodo],$O$7)+SUMIFS(Anexo_4[base_imponible_10],Anexo_4[gastos_operativos_kpi],$D$24,Anexo_4[periodo],$O$7) -> 0 | P24: =SUMIFS(Anexo_4[base_imponible_18],Anexo_4[gastos_operativos_kpi],$D$24,Anexo_4[periodo],$P$7)+SUMIFS(Anexo_4[base_imponible_10],Anexo_4[gastos_operativos_kpi],$D$24,Anexo_4[periodo],$P$7) -> 0 | Q24: =SUMIFS(Anexo_4[base_imponible_18],Anexo_4[gastos_operativos_kpi],$D$24,Anexo_4[periodo],$Q$7)+SUMIFS(Anexo_4[base_imponible_10],Anexo_4[gastos_operativos_kpi],$D$24,Anexo_4[periodo],$Q$7) -> 0 | R24: =SUM(F24:Q24) -> 0 | S24: =AVERAGE(F24:Q24) -> 0
D25: Stockas | E25: Moneda | F25: =SUMIFS(Anexo_4[base_imponible_18],Anexo_4[gastos_operativos_kpi],$D$25,Anexo_4[periodo],$F$7)+SUMIFS(Anexo_4[base_imponible_10],Anexo_4[gastos_operativos_kpi],$D$25,Anexo_4[periodo],$F$7) -> 0 | G25: =SUMIFS(Anexo_4[base_imponible_18],Anexo_4[gastos_operativos_kpi],$D$25,Anexo_4[periodo],$G$7)+SUMIFS(Anexo_4[base_imponible_10],Anexo_4[gastos_operativos_kpi],$D$25,Anexo_4[periodo],$G$7) -> 0 | H25: =SUMIFS(Anexo_4[base_imponible_18],Anexo_4[gastos_operativos_kpi],$D$25,Anexo_4[periodo],$H$7)+SUMIFS(Anexo_4[base_imponible_10],Anexo_4[gastos_operativos_kpi],$D$25,Anexo_4[periodo],$H$7) -> 0 | I25: =SUMIFS(Anexo_4[base_imponible_18],Anexo_4[gastos_operativos_kpi],$D$25,Anexo_4[periodo],$I$7)+SUMIFS(Anexo_4[base_imponible_10],Anexo_4[gastos_operativos_kpi],$D$25,Anexo_4[periodo],$I$7) -> 0 | J25: =SUMIFS(Anexo_4[base_imponible_18],Anexo_4[gastos_operativos_kpi],$D$25,Anexo_4[periodo],$J$7)+SUMIFS(Anexo_4[base_imponible_10],Anexo_4[gastos_operativos_kpi],$D$25,Anexo_4[periodo],$J$7) -> 0 | K25: =SUMIFS(Anexo_4[base_imponible_18],Anexo_4[gastos_operativos_kpi],$D$25,Anexo_4[periodo],$K$7)+SUMIFS(Anexo_4[base_imponible_10],Anexo_4[gastos_operativos_kpi],$D$25,Anexo_4[periodo],$K$7) -> 1131.7 | L25: =SUMIFS(Anexo_4[base_imponible_18],Anexo_4[gastos_operativos_kpi],$D$25,Anexo_4[periodo],$L$7)+SUMIFS(Anexo_4[base_imponible_10],Anexo_4[gastos_operativos_kpi],$D$25,Anexo_4[periodo],$L$7) -> 0 | M25: =SUMIFS(Anexo_4[base_imponible_18],Anexo_4[gastos_operativos_kpi],$D$25,Anexo_4[periodo],$M$7)+SUMIFS(Anexo_4[base_imponible_10],Anexo_4[gastos_operativos_kpi],$D$25,Anexo_4[periodo],$M$7) -> 0 | N25: =SUMIFS(Anexo_4[base_imponible_18],Anexo_4[gastos_operativos_kpi],$D$25,Anexo_4[periodo],$N$7)+SUMIFS(Anexo_4[base_imponible_10],Anexo_4[gastos_operativos_kpi],$D$25,Anexo_4[periodo],$N$7) -> 0 | O25: =SUMIFS(Anexo_4[base_imponible_18],Anexo_4[gastos_operativos_kpi],$D$25,Anexo_4[periodo],$O$7)+SUMIFS(Anexo_4[base_imponible_10],Anexo_4[gastos_operativos_kpi],$D$25,Anexo_4[periodo],$O$7) -> 0 | P25: =SUMIFS(Anexo_4[base_imponible_18],Anexo_4[gastos_operativos_kpi],$D$25,Anexo_4[periodo],$P$7)+SUMIFS(Anexo_4[base_imponible_10],Anexo_4[gastos_operativos_kpi],$D$25,Anexo_4[periodo],$P$7) -> 0 | Q25: =SUMIFS(Anexo_4[base_imponible_18],Anexo_4[gastos_operativos_kpi],$D$25,Anexo_4[periodo],$Q$7)+SUMIFS(Anexo_4[base_imponible_10],Anexo_4[gastos_operativos_kpi],$D$25,Anexo_4[periodo],$Q$7) -> 0 | R25: =SUM(F25:Q25) -> 1131.7 | S25: =AVERAGE(F25:Q25) -> 94.308333
D26: Mantenimiento de Balanzas | E26: Moneda | F26: =SUMIFS(Anexo_4[base_imponible_18],Anexo_4[gastos_operativos_kpi],$D$26,Anexo_4[periodo],$F$7)+SUMIFS(Anexo_4[base_imponible_10],Anexo_4[gastos_operativos_kpi],$D$26,Anexo_4[periodo],$F$7) -> 0 | G26: =SUMIFS(Anexo_4[base_imponible_18],Anexo_4[gastos_operativos_kpi],$D$26,Anexo_4[periodo],$G$7)+SUMIFS(Anexo_4[base_imponible_10],Anexo_4[gastos_operativos_kpi],$D$26,Anexo_4[periodo],$G$7) -> 0 | H26: =SUMIFS(Anexo_4[base_imponible_18],Anexo_4[gastos_operativos_kpi],$D$26,Anexo_4[periodo],$H$7)+SUMIFS(Anexo_4[base_imponible_10],Anexo_4[gastos_operativos_kpi],$D$26,Anexo_4[periodo],$H$7) -> 0 | I26: =SUMIFS(Anexo_4[base_imponible_18],Anexo_4[gastos_operativos_kpi],$D$26,Anexo_4[periodo],$I$7)+SUMIFS(Anexo_4[base_imponible_10],Anexo_4[gastos_operativos_kpi],$D$26,Anexo_4[periodo],$I$7) -> 0 | J26: =SUMIFS(Anexo_4[base_imponible_18],Anexo_4[gastos_operativos_kpi],$D$26,Anexo_4[periodo],$J$7)+SUMIFS(Anexo_4[base_imponible_10],Anexo_4[gastos_operativos_kpi],$D$26,Anexo_4[periodo],$J$7) -> 0 | K26: =SUMIFS(Anexo_4[base_imponible_18],Anexo_4[gastos_operativos_kpi],$D$26,Anexo_4[periodo],$K$7)+SUMIFS(Anexo_4[base_imponible_10],Anexo_4[gastos_operativos_kpi],$D$26,Anexo_4[periodo],$K$7) -> 0 | L26: =SUMIFS(Anexo_4[base_imponible_18],Anexo_4[gastos_operativos_kpi],$D$26,Anexo_4[periodo],$L$7)+SUMIFS(Anexo_4[base_imponible_10],Anexo_4[gastos_operativos_kpi],$D$26,Anexo_4[periodo],$L$7) -> 42.37 | M26: =SUMIFS(Anexo_4[base_imponible_18],Anexo_4[gastos_operativos_kpi],$D$26,Anexo_4[periodo],$M$7)+SUMIFS(Anexo_4[base_imponible_10],Anexo_4[gastos_operativos_kpi],$D$26,Anexo_4[periodo],$M$7) -> 1074.55 | N26: =SUMIFS(Anexo_4[base_imponible_18],Anexo_4[gastos_operativos_kpi],$D$26,Anexo_4[periodo],$N$7)+SUMIFS(Anexo_4[base_imponible_10],Anexo_4[gastos_operativos_kpi],$D$26,Anexo_4[periodo],$N$7) -> 0 | O26: =SUMIFS(Anexo_4[base_imponible_18],Anexo_4[gastos_operativos_kpi],$D$26,Anexo_4[periodo],$O$7)+SUMIFS(Anexo_4[base_imponible_10],Anexo_4[gastos_operativos_kpi],$D$26,Anexo_4[periodo],$O$7) -> 0 | P26: =SUMIFS(Anexo_4[base_imponible_18],Anexo_4[gastos_operativos_kpi],$D$26,Anexo_4[periodo],$P$7)+SUMIFS(Anexo_4[base_imponible_10],Anexo_4[gastos_operativos_kpi],$D$26,Anexo_4[periodo],$P$7) -> 0 | Q26: =SUMIFS(Anexo_4[base_imponible_18],Anexo_4[gastos_operativos_kpi],$D$26,Anexo_4[periodo],$Q$7)+SUMIFS(Anexo_4[base_imponible_10],Anexo_4[gastos_operativos_kpi],$D$26,Anexo_4[periodo],$Q$7) -> 0 | R26: =SUM(F26:Q26) -> 1116.92 | S26: =AVERAGE(F26:Q26) -> 93.076667
D27: Apoyo operativo (Maquinaria) | E27: Moneda | F27: =SUMIFS(Anexo_4[base_imponible_18],Anexo_4[gastos_operativos_kpi],$D$27,Anexo_4[periodo],$F$7)+SUMIFS(Anexo_4[base_imponible_10],Anexo_4[gastos_operativos_kpi],$D$27,Anexo_4[periodo],$F$7) -> 0 | G27: =SUMIFS(Anexo_4[base_imponible_18],Anexo_4[gastos_operativos_kpi],$D$27,Anexo_4[periodo],$G$7)+SUMIFS(Anexo_4[base_imponible_10],Anexo_4[gastos_operativos_kpi],$D$27,Anexo_4[periodo],$G$7) -> 0 | H27: =SUMIFS(Anexo_4[base_imponible_18],Anexo_4[gastos_operativos_kpi],$D$27,Anexo_4[periodo],$H$7)+SUMIFS(Anexo_4[base_imponible_10],Anexo_4[gastos_operativos_kpi],$D$27,Anexo_4[periodo],$H$7) -> 0 | I27: =SUMIFS(Anexo_4[base_imponible_18],Anexo_4[gastos_operativos_kpi],$D$27,Anexo_4[periodo],$I$7)+SUMIFS(Anexo_4[base_imponible_10],Anexo_4[gastos_operativos_kpi],$D$27,Anexo_4[periodo],$I$7) -> 0 | J27: =SUMIFS(Anexo_4[base_imponible_18],Anexo_4[gastos_operativos_kpi],$D$27,Anexo_4[periodo],$J$7)+SUMIFS(Anexo_4[base_imponible_10],Anexo_4[gastos_operativos_kpi],$D$27,Anexo_4[periodo],$J$7) -> 0 | K27: =SUMIFS(Anexo_4[base_imponible_18],Anexo_4[gastos_operativos_kpi],$D$27,Anexo_4[periodo],$K$7)+SUMIFS(Anexo_4[base_imponible_10],Anexo_4[gastos_operativos_kpi],$D$27,Anexo_4[periodo],$K$7) -> 0 | L27: =SUMIFS(Anexo_4[base_imponible_18],Anexo_4[gastos_operativos_kpi],$D$27,Anexo_4[periodo],$L$7)+SUMIFS(Anexo_4[base_imponible_10],Anexo_4[gastos_operativos_kpi],$D$27,Anexo_4[periodo],$L$7) -> 0 | M27: =SUMIFS(Anexo_4[base_imponible_18],Anexo_4[gastos_operativos_kpi],$D$27,Anexo_4[periodo],$M$7)+SUMIFS(Anexo_4[base_imponible_10],Anexo_4[gastos_operativos_kpi],$D$27,Anexo_4[periodo],$M$7) -> 0 | N27: =SUMIFS(Anexo_4[base_imponible_18],Anexo_4[gastos_operativos_kpi],$D$27,Anexo_4[periodo],$N$7)+SUMIFS(Anexo_4[base_imponible_10],Anexo_4[gastos_operativos_kpi],$D$27,Anexo_4[periodo],$N$7) -> 0 | O27: =SUMIFS(Anexo_4[base_imponible_18],Anexo_4[gastos_operativos_kpi],$D$27,Anexo_4[periodo],$O$7)+SUMIFS(Anexo_4[base_imponible_10],Anexo_4[gastos_operativos_kpi],$D$27,Anexo_4[periodo],$O$7) -> 0 | P27: =SUMIFS(Anexo_4[base_imponible_18],Anexo_4[gastos_operativos_kpi],$D$27,Anexo_4[periodo],$P$7)+SUMIFS(Anexo_4[base_imponible_10],Anexo_4[gastos_operativos_kpi],$D$27,Anexo_4[periodo],$P$7) -> 0 | Q27: =SUMIFS(Anexo_4[base_imponible_18],Anexo_4[gastos_operativos_kpi],$D$27,Anexo_4[periodo],$Q$7)+SUMIFS(Anexo_4[base_imponible_10],Anexo_4[gastos_operativos_kpi],$D$27,Anexo_4[periodo],$Q$7) -> 0 | R27: =SUM(F27:Q27) -> 0 | S27: =AVERAGE(F27:Q27) -> 0
D28: Impresión de fichas de servicio / Check List | E28: Moneda | F28: =SUMIFS(Anexo_4[base_imponible_18],Anexo_4[gastos_operativos_kpi],$D$28,Anexo_4[periodo],$F$7)+SUMIFS(Anexo_4[base_imponible_10],Anexo_4[gastos_operativos_kpi],$D$28,Anexo_4[periodo],$F$7) -> 0 | G28: =SUMIFS(Anexo_4[base_imponible_18],Anexo_4[gastos_operativos_kpi],$D$28,Anexo_4[periodo],$G$7)+SUMIFS(Anexo_4[base_imponible_10],Anexo_4[gastos_operativos_kpi],$D$28,Anexo_4[periodo],$G$7) -> 0 | H28: =SUMIFS(Anexo_4[base_imponible_18],Anexo_4[gastos_operativos_kpi],$D$28,Anexo_4[periodo],$H$7)+SUMIFS(Anexo_4[base_imponible_10],Anexo_4[gastos_operativos_kpi],$D$28,Anexo_4[periodo],$H$7) -> 0 | I28: =SUMIFS(Anexo_4[base_imponible_18],Anexo_4[gastos_operativos_kpi],$D$28,Anexo_4[periodo],$I$7)+SUMIFS(Anexo_4[base_imponible_10],Anexo_4[gastos_operativos_kpi],$D$28,Anexo_4[periodo],$I$7) -> 0 | J28: =SUMIFS(Anexo_4[base_imponible_18],Anexo_4[gastos_operativos_kpi],$D$28,Anexo_4[periodo],$J$7)+SUMIFS(Anexo_4[base_imponible_10],Anexo_4[gastos_operativos_kpi],$D$28,Anexo_4[periodo],$J$7) -> 0 | K28: =SUMIFS(Anexo_4[base_imponible_18],Anexo_4[gastos_operativos_kpi],$D$28,Anexo_4[periodo],$K$7)+SUMIFS(Anexo_4[base_imponible_10],Anexo_4[gastos_operativos_kpi],$D$28,Anexo_4[periodo],$K$7) -> 517.37 | L28: =SUMIFS(Anexo_4[base_imponible_18],Anexo_4[gastos_operativos_kpi],$D$28,Anexo_4[periodo],$L$7)+SUMIFS(Anexo_4[base_imponible_10],Anexo_4[gastos_operativos_kpi],$D$28,Anexo_4[periodo],$L$7) -> 0 | M28: =SUMIFS(Anexo_4[base_imponible_18],Anexo_4[gastos_operativos_kpi],$D$28,Anexo_4[periodo],$M$7)+SUMIFS(Anexo_4[base_imponible_10],Anexo_4[gastos_operativos_kpi],$D$28,Anexo_4[periodo],$M$7) -> 0 | N28: =SUMIFS(Anexo_4[base_imponible_18],Anexo_4[gastos_operativos_kpi],$D$28,Anexo_4[periodo],$N$7)+SUMIFS(Anexo_4[base_imponible_10],Anexo_4[gastos_operativos_kpi],$D$28,Anexo_4[periodo],$N$7) -> 0 | O28: =SUMIFS(Anexo_4[base_imponible_18],Anexo_4[gastos_operativos_kpi],$D$28,Anexo_4[periodo],$O$7)+SUMIFS(Anexo_4[base_imponible_10],Anexo_4[gastos_operativos_kpi],$D$28,Anexo_4[periodo],$O$7) -> 0 | P28: =SUMIFS(Anexo_4[base_imponible_18],Anexo_4[gastos_operativos_kpi],$D$28,Anexo_4[periodo],$P$7)+SUMIFS(Anexo_4[base_imponible_10],Anexo_4[gastos_operativos_kpi],$D$28,Anexo_4[periodo],$P$7) -> 0 | Q28: =SUMIFS(Anexo_4[base_imponible_18],Anexo_4[gastos_operativos_kpi],$D$28,Anexo_4[periodo],$Q$7)+SUMIFS(Anexo_4[base_imponible_10],Anexo_4[gastos_operativos_kpi],$D$28,Anexo_4[periodo],$Q$7) -> 0 | R28: =SUM(F28:Q28) -> 517.37 | S28: =AVERAGE(F28:Q28) -> 43.114167
D29: Impresión de formatos | E29: Moneda | F29: =SUMIFS(Anexo_4[base_imponible_18],Anexo_4[gastos_operativos_kpi],$D$29,Anexo_4[periodo],$F$7)+SUMIFS(Anexo_4[base_imponible_10],Anexo_4[gastos_operativos_kpi],$D$29,Anexo_4[periodo],$F$7) -> 0 | G29: =SUMIFS(Anexo_4[base_imponible_18],Anexo_4[gastos_operativos_kpi],$D$29,Anexo_4[periodo],$G$7)+SUMIFS(Anexo_4[base_imponible_10],Anexo_4[gastos_operativos_kpi],$D$29,Anexo_4[periodo],$G$7) -> 0 | H29: =SUMIFS(Anexo_4[base_imponible_18],Anexo_4[gastos_operativos_kpi],$D$29,Anexo_4[periodo],$H$7)+SUMIFS(Anexo_4[base_imponible_10],Anexo_4[gastos_operativos_kpi],$D$29,Anexo_4[periodo],$H$7) -> 0 | I29: =SUMIFS(Anexo_4[base_imponible_18],Anexo_4[gastos_operativos_kpi],$D$29,Anexo_4[periodo],$I$7)+SUMIFS(Anexo_4[base_imponible_10],Anexo_4[gastos_operativos_kpi],$D$29,Anexo_4[periodo],$I$7) -> 0 | J29: =SUMIFS(Anexo_4[base_imponible_18],Anexo_4[gastos_operativos_kpi],$D$29,Anexo_4[periodo],$J$7)+SUMIFS(Anexo_4[base_imponible_10],Anexo_4[gastos_operativos_kpi],$D$29,Anexo_4[periodo],$J$7) -> 0 | K29: =SUMIFS(Anexo_4[base_imponible_18],Anexo_4[gastos_operativos_kpi],$D$29,Anexo_4[periodo],$K$7)+SUMIFS(Anexo_4[base_imponible_10],Anexo_4[gastos_operativos_kpi],$D$29,Anexo_4[periodo],$K$7) -> 0 | L29: =SUMIFS(Anexo_4[base_imponible_18],Anexo_4[gastos_operativos_kpi],$D$29,Anexo_4[periodo],$L$7)+SUMIFS(Anexo_4[base_imponible_10],Anexo_4[gastos_operativos_kpi],$D$29,Anexo_4[periodo],$L$7) -> 0 | M29: =SUMIFS(Anexo_4[base_imponible_18],Anexo_4[gastos_operativos_kpi],$D$29,Anexo_4[periodo],$M$7)+SUMIFS(Anexo_4[base_imponible_10],Anexo_4[gastos_operativos_kpi],$D$29,Anexo_4[periodo],$M$7) -> 0 | N29: =SUMIFS(Anexo_4[base_imponible_18],Anexo_4[gastos_operativos_kpi],$D$29,Anexo_4[periodo],$N$7)+SUMIFS(Anexo_4[base_imponible_10],Anexo_4[gastos_operativos_kpi],$D$29,Anexo_4[periodo],$N$7) -> 0 | O29: =SUMIFS(Anexo_4[base_imponible_18],Anexo_4[gastos_operativos_kpi],$D$29,Anexo_4[periodo],$O$7)+SUMIFS(Anexo_4[base_imponible_10],Anexo_4[gastos_operativos_kpi],$D$29,Anexo_4[periodo],$O$7) -> 0 | P29: =SUMIFS(Anexo_4[base_imponible_18],Anexo_4[gastos_operativos_kpi],$D$29,Anexo_4[periodo],$P$7)+SUMIFS(Anexo_4[base_imponible_10],Anexo_4[gastos_operativos_kpi],$D$29,Anexo_4[periodo],$P$7) -> 0 | Q29: =SUMIFS(Anexo_4[base_imponible_18],Anexo_4[gastos_operativos_kpi],$D$29,Anexo_4[periodo],$Q$7)+SUMIFS(Anexo_4[base_imponible_10],Anexo_4[gastos_operativos_kpi],$D$29,Anexo_4[periodo],$Q$7) -> 0 | R29: =SUM(F29:Q29) -> 0 | S29: =AVERAGE(F29:Q29) -> 0
D30: Combustible (Vehiculos) | E30: Moneda | F30: =SUMIFS(Anexo_4[base_imponible_18],Anexo_4[gastos_operativos_kpi],$D$30,Anexo_4[periodo],$F$7)+SUMIFS(Anexo_4[base_imponible_10],Anexo_4[gastos_operativos_kpi],$D$30,Anexo_4[periodo],$F$7) -> 0 | G30: =SUMIFS(Anexo_4[base_imponible_18],Anexo_4[gastos_operativos_kpi],$D$30,Anexo_4[periodo],$G$7)+SUMIFS(Anexo_4[base_imponible_10],Anexo_4[gastos_operativos_kpi],$D$30,Anexo_4[periodo],$G$7) -> 0 | H30: =SUMIFS(Anexo_4[base_imponible_18],Anexo_4[gastos_operativos_kpi],$D$30,Anexo_4[periodo],$H$7)+SUMIFS(Anexo_4[base_imponible_10],Anexo_4[gastos_operativos_kpi],$D$30,Anexo_4[periodo],$H$7) -> 0 | I30: =SUMIFS(Anexo_4[base_imponible_18],Anexo_4[gastos_operativos_kpi],$D$30,Anexo_4[periodo],$I$7)+SUMIFS(Anexo_4[base_imponible_10],Anexo_4[gastos_operativos_kpi],$D$30,Anexo_4[periodo],$I$7) -> 0 | J30: =SUMIFS(Anexo_4[base_imponible_18],Anexo_4[gastos_operativos_kpi],$D$30,Anexo_4[periodo],$J$7)+SUMIFS(Anexo_4[base_imponible_10],Anexo_4[gastos_operativos_kpi],$D$30,Anexo_4[periodo],$J$7) -> 0 | K30: =SUMIFS(Anexo_4[base_imponible_18],Anexo_4[gastos_operativos_kpi],$D$30,Anexo_4[periodo],$K$7)+SUMIFS(Anexo_4[base_imponible_10],Anexo_4[gastos_operativos_kpi],$D$30,Anexo_4[periodo],$K$7) -> 11250.6 | L30: =SUMIFS(Anexo_4[base_imponible_18],Anexo_4[gastos_operativos_kpi],$D$30,Anexo_4[periodo],$L$7)+SUMIFS(Anexo_4[base_imponible_10],Anexo_4[gastos_operativos_kpi],$D$30,Anexo_4[periodo],$L$7) -> 9813.76 | M30: =SUMIFS(Anexo_4[base_imponible_18],Anexo_4[gastos_operativos_kpi],$D$30,Anexo_4[periodo],$M$7)+SUMIFS(Anexo_4[base_imponible_10],Anexo_4[gastos_operativos_kpi],$D$30,Anexo_4[periodo],$M$7) -> 10625.02 | N30: =SUMIFS(Anexo_4[base_imponible_18],Anexo_4[gastos_operativos_kpi],$D$30,Anexo_4[periodo],$N$7)+SUMIFS(Anexo_4[base_imponible_10],Anexo_4[gastos_operativos_kpi],$D$30,Anexo_4[periodo],$N$7) -> 13290.86 | O30: =SUMIFS(Anexo_4[base_imponible_18],Anexo_4[gastos_operativos_kpi],$D$30,Anexo_4[periodo],$O$7)+SUMIFS(Anexo_4[base_imponible_10],Anexo_4[gastos_operativos_kpi],$D$30,Anexo_4[periodo],$O$7) -> 0 | P30: =SUMIFS(Anexo_4[base_imponible_18],Anexo_4[gastos_operativos_kpi],$D$30,Anexo_4[periodo],$P$7)+SUMIFS(Anexo_4[base_imponible_10],Anexo_4[gastos_operativos_kpi],$D$30,Anexo_4[periodo],$P$7) -> 0 | Q30: =SUMIFS(Anexo_4[base_imponible_18],Anexo_4[gastos_operativos_kpi],$D$30,Anexo_4[periodo],$Q$7)+SUMIFS(Anexo_4[base_imponible_10],Anexo_4[gastos_operativos_kpi],$D$30,Anexo_4[periodo],$Q$7) -> 0 | R30: =SUM(F30:Q30) -> 44980.24 | S30: =AVERAGE(F30:Q30) -> 3748.3533
D31: Combustible (Montacarga) | E31: Moneda | F31: =SUMIFS(Anexo_4[base_imponible_18],Anexo_4[gastos_operativos_kpi],$D$31,Anexo_4[periodo],$F$7)+SUMIFS(Anexo_4[base_imponible_10],Anexo_4[gastos_operativos_kpi],$D$31,Anexo_4[periodo],$F$7) -> 0 | G31: =SUMIFS(Anexo_4[base_imponible_18],Anexo_4[gastos_operativos_kpi],$D$31,Anexo_4[periodo],$G$7)+SUMIFS(Anexo_4[base_imponible_10],Anexo_4[gastos_operativos_kpi],$D$31,Anexo_4[periodo],$G$7) -> 0 | H31: =SUMIFS(Anexo_4[base_imponible_18],Anexo_4[gastos_operativos_kpi],$D$31,Anexo_4[periodo],$H$7)+SUMIFS(Anexo_4[base_imponible_10],Anexo_4[gastos_operativos_kpi],$D$31,Anexo_4[periodo],$H$7) -> 0 | I31: =SUMIFS(Anexo_4[base_imponible_18],Anexo_4[gastos_operativos_kpi],$D$31,Anexo_4[periodo],$I$7)+SUMIFS(Anexo_4[base_imponible_10],Anexo_4[gastos_operativos_kpi],$D$31,Anexo_4[periodo],$I$7) -> 0 | J31: =SUMIFS(Anexo_4[base_imponible_18],Anexo_4[gastos_operativos_kpi],$D$31,Anexo_4[periodo],$J$7)+SUMIFS(Anexo_4[base_imponible_10],Anexo_4[gastos_operativos_kpi],$D$31,Anexo_4[periodo],$J$7) -> 0 | K31: =SUMIFS(Anexo_4[base_imponible_18],Anexo_4[gastos_operativos_kpi],$D$31,Anexo_4[periodo],$K$7)+SUMIFS(Anexo_4[base_imponible_10],Anexo_4[gastos_operativos_kpi],$D$31,Anexo_4[periodo],$K$7) -> 0 | L31: =SUMIFS(Anexo_4[base_imponible_18],Anexo_4[gastos_operativos_kpi],$D$31,Anexo_4[periodo],$L$7)+SUMIFS(Anexo_4[base_imponible_10],Anexo_4[gastos_operativos_kpi],$D$31,Anexo_4[periodo],$L$7) -> 0 | M31: =SUMIFS(Anexo_4[base_imponible_18],Anexo_4[gastos_operativos_kpi],$D$31,Anexo_4[periodo],$M$7)+SUMIFS(Anexo_4[base_imponible_10],Anexo_4[gastos_operativos_kpi],$D$31,Anexo_4[periodo],$M$7) -> 0 | N31: =SUMIFS(Anexo_4[base_imponible_18],Anexo_4[gastos_operativos_kpi],$D$31,Anexo_4[periodo],$N$7)+SUMIFS(Anexo_4[base_imponible_10],Anexo_4[gastos_operativos_kpi],$D$31,Anexo_4[periodo],$N$7) -> 0 | O31: =SUMIFS(Anexo_4[base_imponible_18],Anexo_4[gastos_operativos_kpi],$D$31,Anexo_4[periodo],$O$7)+SUMIFS(Anexo_4[base_imponible_10],Anexo_4[gastos_operativos_kpi],$D$31,Anexo_4[periodo],$O$7) -> 0 | P31: =SUMIFS(Anexo_4[base_imponible_18],Anexo_4[gastos_operativos_kpi],$D$31,Anexo_4[periodo],$P$7)+SUMIFS(Anexo_4[base_imponible_10],Anexo_4[gastos_operativos_kpi],$D$31,Anexo_4[periodo],$P$7) -> 0 | Q31: =SUMIFS(Anexo_4[base_imponible_18],Anexo_4[gastos_operativos_kpi],$D$31,Anexo_4[periodo],$Q$7)+SUMIFS(Anexo_4[base_imponible_10],Anexo_4[gastos_operativos_kpi],$D$31,Anexo_4[periodo],$Q$7) -> 0 | R31: =SUM(F31:Q31) -> 0 | S31: =AVERAGE(F31:Q31) -> 0
D32: Gastos de Ferreteria | E32: Moneda | F32: =SUMIFS(Anexo_4[base_imponible_18],Anexo_4[gastos_operativos_kpi],$D$32,Anexo_4[periodo],$F$7)+SUMIFS(Anexo_4[base_imponible_10],Anexo_4[gastos_operativos_kpi],$D$32,Anexo_4[periodo],$F$7) -> 0 | G32: =SUMIFS(Anexo_4[base_imponible_18],Anexo_4[gastos_operativos_kpi],$D$32,Anexo_4[periodo],$G$7)+SUMIFS(Anexo_4[base_imponible_10],Anexo_4[gastos_operativos_kpi],$D$32,Anexo_4[periodo],$G$7) -> 0 | H32: =SUMIFS(Anexo_4[base_imponible_18],Anexo_4[gastos_operativos_kpi],$D$32,Anexo_4[periodo],$H$7)+SUMIFS(Anexo_4[base_imponible_10],Anexo_4[gastos_operativos_kpi],$D$32,Anexo_4[periodo],$H$7) -> 0 | I32: =SUMIFS(Anexo_4[base_imponible_18],Anexo_4[gastos_operativos_kpi],$D$32,Anexo_4[periodo],$I$7)+SUMIFS(Anexo_4[base_imponible_10],Anexo_4[gastos_operativos_kpi],$D$32,Anexo_4[periodo],$I$7) -> 0 | J32: =SUMIFS(Anexo_4[base_imponible_18],Anexo_4[gastos_operativos_kpi],$D$32,Anexo_4[periodo],$J$7)+SUMIFS(Anexo_4[base_imponible_10],Anexo_4[gastos_operativos_kpi],$D$32,Anexo_4[periodo],$J$7) -> 0 | K32: =SUMIFS(Anexo_4[base_imponible_18],Anexo_4[gastos_operativos_kpi],$D$32,Anexo_4[periodo],$K$7)+SUMIFS(Anexo_4[base_imponible_10],Anexo_4[gastos_operativos_kpi],$D$32,Anexo_4[periodo],$K$7) -> 208.05 | L32: =SUMIFS(Anexo_4[base_imponible_18],Anexo_4[gastos_operativos_kpi],$D$32,Anexo_4[periodo],$L$7)+SUMIFS(Anexo_4[base_imponible_10],Anexo_4[gastos_operativos_kpi],$D$32,Anexo_4[periodo],$L$7) -> 0 | M32: =SUMIFS(Anexo_4[base_imponible_18],Anexo_4[gastos_operativos_kpi],$D$32,Anexo_4[periodo],$M$7)+SUMIFS(Anexo_4[base_imponible_10],Anexo_4[gastos_operativos_kpi],$D$32,Anexo_4[periodo],$M$7) -> 0 | N32: =SUMIFS(Anexo_4[base_imponible_18],Anexo_4[gastos_operativos_kpi],$D$32,Anexo_4[periodo],$N$7)+SUMIFS(Anexo_4[base_imponible_10],Anexo_4[gastos_operativos_kpi],$D$32,Anexo_4[periodo],$N$7) -> 10.59 | O32: =SUMIFS(Anexo_4[base_imponible_18],Anexo_4[gastos_operativos_kpi],$D$32,Anexo_4[periodo],$O$7)+SUMIFS(Anexo_4[base_imponible_10],Anexo_4[gastos_operativos_kpi],$D$32,Anexo_4[periodo],$O$7) -> 0 | P32: =SUMIFS(Anexo_4[base_imponible_18],Anexo_4[gastos_operativos_kpi],$D$32,Anexo_4[periodo],$P$7)+SUMIFS(Anexo_4[base_imponible_10],Anexo_4[gastos_operativos_kpi],$D$32,Anexo_4[periodo],$P$7) -> 0 | Q32: =SUMIFS(Anexo_4[base_imponible_18],Anexo_4[gastos_operativos_kpi],$D$32,Anexo_4[periodo],$Q$7)+SUMIFS(Anexo_4[base_imponible_10],Anexo_4[gastos_operativos_kpi],$D$32,Anexo_4[periodo],$Q$7) -> 0 | R32: =SUM(F32:Q32) -> 218.64 | S32: =AVERAGE(F32:Q32) -> 18.22
